Workbook

Sheet Executive Summary
A1: JUNIPER GREEN ENERGY LIMITED — EXECUTIVE SUMMARY
G2: Bear | H2: Base | I2: Bull
A3: Active Scenario (drives all detailed tabs): | B3: =Assumptions!$B$4 -> Base | C3: (change on the Assumptions tab, cell B4 — this cell mirrors it) | G3: 186.22403 | H3: 328.63564 | I3: 480.25358
G4: =G3/$B$16-1 -> -0.27256238 | H4: =H3/$B$16-1 -> 0.28373297 | I4: =I3/$B$16-1 -> 0.87599053
A6: FINANCIAL SNAPSHOT (current Active Scenario)
B7: FY26A | C7: FY27E | D7: FY28E | E7: FY29E | F7: FY30E | G7: FY31E
A8: Revenue (Rs cr) | B8: ='P&L'!D5 -> 718.934 | C8: ='P&L'!E5 -> 2437.5935 | D8: ='P&L'!F5 -> 5937.1108 | E8: ='P&L'!G5 -> 8038.7308 | F8: ='P&L'!H5 -> 10353.315 | G8: ='P&L'!I5 -> 11021.703
A9: EBITDA (Rs cr) | B9: ='P&L'!D26 -> 692.184 | C9: ='P&L'!E26 -> 2288.6528 | D9: ='P&L'!F26 -> 5667.7714 | E9: ='P&L'!G26 -> 7636.8088 | F9: ='P&L'!H26 -> 9828.8172 | G9: ='P&L'!I26 -> 10453.645
A10: EBITDA Margin % | B10: ='P&L'!D27 -> 0.85993068 | C10: ='P&L'!E27 -> 0.90536117 | D10: ='P&L'!F27 -> 0.93962953 | E10: ='P&L'!G27 -> 0.93838097 | F10: ='P&L'!H27 -> 0.93985118 | G10: ='P&L'!I27 -> 0.93910827
A11: PAT (Rs cr) | B11: ='P&L'!D38 -> 40.464 | C11: ='P&L'!E38 -> 327.01351 | D11: ='P&L'!F38 -> 1272.207 | E11: ='P&L'!G38 -> 1907.7001 | F11: ='P&L'!H38 -> 3169.1666 | G11: ='P&L'!I38 -> 3621.1844
A12: Net Debt/Equity (x) | B12: =Ratios!D14 -> 2.7930405 | C12: =Ratios!E14 -> 4.5342092 | D12: =Ratios!F14 -> 4.5118083 | E12: =Ratios!G14 -> 3.4990782 | F12: =Ratios!H14 -> 2.1831352 | G12: =Ratios!I14 -> 1.2986758
A14: VALUATION SUMMARY (current Active Scenario)
A15: FCFE-DCF Value per Share (Rs) | B15: =Valuation!$B$17 -> 328.63564
A16: CMP | B16: 256
A17: Implied Upside/(Downside) | B17: =Valuation!$B$19 -> 0.28373297
A18: EV/EBITDA (Forward, FY27E) | B18: =Valuation!E32 -> 10.542958
A19: P/E (Forward, FY27E) | B19: =Valuation!E35 -> 44.542887
A21: SCENARIO COMPARISON — BEAR / BASE / BULL (always live, independent of the switch above)
A22: Simplified portfolio-level approximation, NOT a full re-run of the 48-SPV detail. Isolates the two levers with a clean, quantifiable portfolio-wide effect (WSH/FDRE post-COD CUF; merchant tariff). Holds cost structure, tax rate, and D&A at Base-case levels. UCA timeline lever is excluded here as it washes out by FY31 in the detailed model (affects the ramp path and peak leverage, not the FY31 snapshot) — see Debt Model tab for its full effect.
B25: Bear | C25: Base | D25: Bull
A26: WSH/FDRE post-COD CUF | B26: =Assumptions!B40 -> 0.35 | C26: =Assumptions!C40 -> 0.4 | D26: =Assumptions!D40 -> 0.45
A27: Merchant tariff (Rs/kWh) | B27: =Assumptions!B49 -> 2.3 | C27: =Assumptions!C49 -> 2.83 | D27: =Assumptions!D49 -> 3.4
A29: Base-case FY31E Revenue (Rs cr) | C29: 7442.2887
A30: Adj: WSH/FDRE CUF delta impact (5,875.4 MW x 8760 x 1000 x d(CUF) x Rs3.939/kWh /1e6) | B30: =5875.4*8760*1000*(Assumptions!B40-Assumptions!$C$40)*3.939/10000000 -> -1013.6722 | D30: =5875.4*8760*1000*(Assumptions!D40-Assumptions!$C$40)*3.939/10000000 -> 1013.6722
A31: Adj: Merchant tariff delta impact (170 MW x 8760 x 1000 x 24.48% x d(Tariff) /1e6) | B31: =170*8760*1000*0.2448*(Assumptions!B49-Assumptions!$C$49)/10000000 -> -19.321476 | D31: =170*8760*1000*0.2448*(Assumptions!D49-Assumptions!$C$49)/10000000 -> 20.779701
A32: Scenario FY31E Revenue (Rs cr) | B32: =$C$29+B30+B31 -> 6409.295 | C32: =$C$29 -> 7442.2887 | D32: =$C$29+D30+D31 -> 8476.7405
A34: Scenario FY31E EBITDA (Rs cr, Base margin applied) | B34: =B32*$C$10 -> 5802.7268 | C34: =C32*$C$10 -> 6737.9591 | D34: =D32*$C$10 -> 7674.5117
A35: Scenario FY31E PAT (Rs cr, Base PAT margin applied) | B35: =B32*($C$11/$C$8) -> 859.83412 | C35: =C32*($C$11/$C$8) -> 998.4146 | D35: =D32*($C$11/$C$8) -> 1137.1907
A37: Approx. Value/Share (Rs) — Base DCF value scaled by scenario/Base FY31E PAT ratio | B37: 235.57337 | C37: 386.47239 | D37: 553.07614

Sheet Assumptions
A1: JUNIPER GREEN ENERGY LIMITED — MODEL ASSUMPTIONS
A3: SCENARIO SWITCH | I3: 2 | J3: Bear
A4: Active Scenario | B4: =INDEX(J3:J5,I3) -> Base | J4: Base
A5: (Drives WSH/FDRE post-COD CUF, UCA commissioning timeline, and merchant tariff below — Sections 6-8) | J5: Bull
A7: 1. COST OF EQUITY (CAPM) — user-specified, not independently sourced
A8: Risk-free rate (Rf) | B8: 0.0677
A9: Equity risk premium (ERP) | B9: 0.0708
A10: Beta | B10: 1.45
A11: Cost of Equity (Ke = Rf + Beta x ERP) | B11: =B8+B9*B10 -> 0.17036
A13: 2. TAX — Source: RHP tax notes; parent & Sigma on Sec.115BAA (25.168%); Field & Three on Sec.115BAB (17.16%); FY26 actual eff. rate 26.69%
A14: Blended effective tax rate (forward) | B14: 0.255
A16: 3. OPEX INFLATION & TERMINAL GROWTH — fixed across all scenarios per user instruction
A17: Opex inflation rate p.a. (CRISIL FY27P CPI, RHP Table 2) | B17: 0.05
A18: Terminal fade growth, Yrs 6-8 (FY32-FY34) | B18: 0.08
A19: Terminal growth, Yr 9+ (FY35 onward, Gordon growth) | B19: 0.05
A21: 4. DEBT FINANCING — Source: RHP Financial Indebtedness note, p.654 & management-cited project D:E
A22: New capex financing — Debt % | B22: 0.8
A23: New capex financing — Equity % | B23: =1-B22 -> 0.2
A24: New debt interest rate p.a. (upper-half of disclosed 7.75-9.75% term loan band) | B24: 0.09
A25: Existing debt blended effective rate p.a. | B25: 0.0875
A26: Assumed weighted-avg amortization tenor (years) — simplification, no per-loan maturity ladder disclosed | B26: 15
A28: 5. DEPRECIATION — USEFUL LIVES (Source: RHP Significant Accounting Policies, p.504)
A29: Solar power projects (technical assessment) | B29: 25
A30: Wind / WSH / FDRE / BESS plant & equipment (within 20-25yr band; conservative mid-point) | B30: 22
A31: Leasehold land (ROU) | B31: 29
A33: 6. GENERATION — CAPACITY UTILISATION FACTOR (CUF)
A34: Solar CUF (FY26 actual, RHP KPI table p.192) | B34: 0.2448 | K34: =IF(B34="Solar",Assumptions!$B$34,IF(B34="Wind",Assumptions!$B$35,IF(A34="Operational",Assumptions!$B$36,IF(B34="WSH",Assumptions!$E$40,)))) -> 0
A35: Wind CUF (FY26 actual, RHP KPI table p.192) | B35: 0.3184
A36: WSH/FDRE CUF — Operational bucket (solar-leg only commissioned; footnotes confirm wind-leg not yet built) | B36: =B34 -> 0.2448
A37: WSH/FDRE Operational bucket — effective interim tariff (solar-leg-only billing; weighted avg solar tariff proxy per RHP phased-billing mechanic p.21102) | B37: 2.8
A38: WSH/FDRE CUF post-COD (full hybrid), by scenario:
B39: Bear | C39: Base | D39: Bull | E39: Active
A40: WSH/FDRE CUF post-COD | B40: 0.35 | C40: 0.4 | D40: 0.45 | E40: =IF($B$4="Bear",B40,IF($B$4="Base",C40,D40)) -> 0.4
A41: FDRE CUF post-COD | B41: 0.4 | C41: 0.5 | D41: 0.6 | E41: =IF($B$4="Bear",B41,IF($B$4="Base",C41,D41)) -> 0.5
A42: 7. UNDER CONSTRUCTION AWARDED — MONTHS FROM LOA TO SCOD, by scenario (Source: RHP disclosed 13-24mo / 24-30mo implementation windows)
B43: Bear | C43: Base | D43: Bull | E43: Active
A44: WSH (13-24mo disclosed range) | B44: 54 | C44: 48 | D44: 40 | E44: =IF($B$4="Bear",B44,IF($B$4="Base",C44,D44)) -> 48
A45: FDRE (24-30mo disclosed range) | B45: 60 | C45: 54 | D45: 48 | E45: =IF($B$4="Bear",B45,IF($B$4="Base",C45,D45)) -> 54
A47: 8. MERCHANT POWER TARIFF ₹/kWh, by scenario (Base = FY26 disclosed historical realized average)
B48: Bear | C48: Base | D48: Bull | E48: Active
A49: Merchant tariff (₹/kWh) | B49: 2.3 | C49: 2.83 | D49: 3.4 | E49: =IF($B$4="Bear",B49,IF($B$4="Base",C49,D49)) -> 2.83
A51: 9. CAPEX RATES ₹ CRORE/MW (implied from RHP disclosed aggregate pipeline cost / planned AC MW, p.170 & MD&A)
A52: UCC implied rate (Total est. cost Rs.24,764.95cr / 2,875.40 MW) | B52: =24764.952/2875.4 -> 8.6126981
A53: UCA implied rate (Total est. cost Rs.19,050.37cr / 3,240.00 MW) | B53: =19050.366/3240 -> 5.8797426
A54: UCC remaining-spend factor (Capital commitments Rs.8,995.47cr / Total UCC est. cost Rs.24,764.95cr, per RHP MD&A — balance already spent/capitalised in FY24-26, pre-dates this forecast) | B54: 0.36323386
A55: 10. WORKING CAPITAL
A56: Trade receivable days (FY26 actual, RHP KPI table) | B56: 21.88
A57: Trade payable days (assumption — mid of disclosed 0-90 day settlement terms) | B57: 45
A59: 11. SHARE CAPITAL & VALUATION INPUTS
A60: Pre-issue equity shares (RHP Capital Structure, p.148) | B60: 488989292
A61: IPO Price — upper band per user instruction (band disclosed ex-RHP: Rs.214-225) | B61: 225
A62: Fresh issue size (Rs crore) | B62: 1800
A63: Fresh issue shares | B63: =B62*10000000/B61 -> 80000000
A64: Post-issue equity shares | B64: =B60+B63 -> 568989292
A65: Market Capitalisation (Rs crore) | B65: =B64*B61/10000000 -> 12802.259
A66: IPO-funded debt repayment — parent (Rs cr, FY27, Objects of Issue p.170) | B66: 683.235
A67: IPO-funded debt repayment — subsidiaries (Rs cr, FY27, Objects of Issue p.170) | B67: 728.686
A68: Total IPO-funded debt repayment (Rs cr) | B68: =B66+B67 -> 1411.921
A70: 12. CSR (statutory formula, Companies Act s.135)
A71: CSR % of trailing 3-yr average net profit | B71: 0.02
A73: 13. MODEL TIMELINE
A74: Forecast start (FY27 = FY ending March 31, 2027) | B74: 46113
A76: FY26 year-end operational MW baseline (RHP portfolio table, Mar 31, 2026) | B76: 1324.2
A77: Employee statutory add-ons as % of cash salary (PF+Gratuity+Comp.Absences / Salary, FY26 actual) | B77: 0.1488
A78: Historical PAT for CSR trailing avg: FY24 (Rs cr) | B78: 40.064
A79: Historical PAT: FY25 (Rs cr) | B79: 36.478
A81: 14. ROU ASSET & LEASE FINANCING (new capacity requires new land leases — driven by MW added, not revenue)
A82: Lease effective interest rate p.a. (RHP-disclosed range 8.10%-11.08%, blended) | B82: 0.095
A83: ROU asset intensity — Rs cr per new MW (implied: FY26A ROU balance / FY26 year-end operational MW) | B83: ='Balance Sheet'!D8/B76 -> 0.81044857

Sheet Revenue Model
A1: REVENUE MODEL — SPV LEVEL (48 PPAs/LOAs)
A2: Generation = AC Capacity(MW) x 1,000 x 8,760hrs x CUF x (Months Operational/12); Revenue = Generation x Tariff. COD-based monthly proration vs FY27 (Apr'26) start. All Rs in crores.
A4: Category | B4: Tech | C4: Entity | D4: Off-taker | E4: AC MW | F4: Base Tariff (Rs/kWh) | G4: Eff. Tariff (Rs/kWh) | H4: Base Date (PPA/LOA) | I4: COD | J4: COD Mth Idx | K4: CUF Applied | L4: FY27 Mths Op | M4: FY27 Rev | N4: FY28 Mths Op | O4: FY28 Rev | P4: FY29 Mths Op | Q4: FY29 Rev | R4: FY30 Mths Op | S4: FY30 Rev | T4: FY31 Mths Op | U4: FY31 Rev
A5: Operational | B5: Solar | C5: Nisagra Renewable Energy Pvt Ltd + Juniper Green Energy Ltd | D5: MSEDCL | E5: 100 | F5: 3.15 | G5: =IF(D5="Merchant",Assumptions!$E$49,IF(AND(A5="Operational",OR(B5="WSH",B5="FDRE")),Assumptions!$B$37,F5)) -> 3.15 | H5: 43461 | I5: 43831 | J5: =MAX(0,(YEAR(I5)-YEAR(Assumptions!$B$74))*12+(MONTH(I5)-MONTH(Assumptions!$B$74))) -> 0 | K5: =IF(B5="Solar",Assumptions!$B$34,IF(B5="Wind",Assumptions!$B$35,IF(B5="WSH",Assumptions!$E$40,Assumptions!$E$41))) -> 0.2448 | L5: =MAX(0,MIN(12,60)-MAX(0,$J5)) -> 12 | M5: =$E5*1000*8760*$K5*$G5*L5/12/10000000 -> 67.550112 | N5: =MAX(0,MIN(24,60)-MAX(12,$J5)) -> 12 | O5: =$E5*1000*8760*$K5*$G5*N5/12/10000000 -> 67.550112 | P5: =MAX(0,MIN(36,60)-MAX(24,$J5)) -> 12 | Q5: =$E5*1000*8760*$K5*$G5*P5/12/10000000 -> 67.550112 | R5: =MAX(0,MIN(48,60)-MAX(36,$J5)) -> 12 | S5: =$E5*1000*8760*$K5*$G5*R5/12/10000000 -> 67.550112 | T5: =MAX(0,MIN(60,60)-MAX(48,$J5)) -> 12 | U5: =$E5*1000*8760*$K5*$G5*T5/12/10000000 -> 67.550112
A6: Operational | B6: Solar | C6: Juniper Green Sigma Pvt Ltd | D6: GUVNL | E6: 120 | F6: 2.67 | G6: =IF(D6="Merchant",Assumptions!$E$49,IF(AND(A6="Operational",OR(B6="WSH",B6="FDRE")),Assumptions!$B$37,F6)) -> 2.67 | H6: 43606 | I6: 43831 | J6: =MAX(0,(YEAR(I6)-YEAR(Assumptions!$B$74))*12+(MONTH(I6)-MONTH(Assumptions!$B$74))) -> 0 | K6: =IF(B6="Solar",Assumptions!$B$34,IF(B6="Wind",Assumptions!$B$35,IF(B6="WSH",Assumptions!$E$40,Assumptions!$E$41))) -> 0.2448 | L6: =MAX(0,MIN(12,60)-MAX(0,$J6)) -> 12 | M6: =$E6*1000*8760*$K6*$G6*L6/12/10000000 -> 68.708114 | N6: =MAX(0,MIN(24,60)-MAX(12,$J6)) -> 12 | O6: =$E6*1000*8760*$K6*$G6*N6/12/10000000 -> 68.708114 | P6: =MAX(0,MIN(36,60)-MAX(24,$J6)) -> 12 | Q6: =$E6*1000*8760*$K6*$G6*P6/12/10000000 -> 68.708114 | R6: =MAX(0,MIN(48,60)-MAX(36,$J6)) -> 12 | S6: =$E6*1000*8760*$K6*$G6*R6/12/10000000 -> 68.708114 | T6: =MAX(0,MIN(60,60)-MAX(48,$J6)) -> 12 | U6: =$E6*1000*8760*$K6*$G6*T6/12/10000000 -> 68.708114
A7: Operational | B7: Solar | C7: Juniper Green Three Pvt Ltd | D7: GUVNL | E7: 190 | F7: 2.63 | G7: =IF(D7="Merchant",Assumptions!$E$49,IF(AND(A7="Operational",OR(B7="WSH",B7="FDRE")),Assumptions!$B$37,F7)) -> 2.63 | H7: 44020 | I7: 43831 | J7: =MAX(0,(YEAR(I7)-YEAR(Assumptions!$B$74))*12+(MONTH(I7)-MONTH(Assumptions!$B$74))) -> 0 | K7: =IF(B7="Solar",Assumptions!$B$34,IF(B7="Wind",Assumptions!$B$35,IF(B7="WSH",Assumptions!$E$40,Assumptions!$E$41))) -> 0.2448 | L7: =MAX(0,MIN(12,60)-MAX(0,$J7)) -> 12 | M7: =$E7*1000*8760*$K7*$G7*L7/12/10000000 -> 107.15807 | N7: =MAX(0,MIN(24,60)-MAX(12,$J7)) -> 12 | O7: =$E7*1000*8760*$K7*$G7*N7/12/10000000 -> 107.15807 | P7: =MAX(0,MIN(36,60)-MAX(24,$J7)) -> 12 | Q7: =$E7*1000*8760*$K7*$G7*P7/12/10000000 -> 107.15807 | R7: =MAX(0,MIN(48,60)-MAX(36,$J7)) -> 12 | S7: =$E7*1000*8760*$K7*$G7*R7/12/10000000 -> 107.15807 | T7: =MAX(0,MIN(60,60)-MAX(48,$J7)) -> 12 | U7: =$E7*1000*8760*$K7*$G7*T7/12/10000000 -> 107.15807
A8: Operational | B8: Solar | C8: Juniper Green Field Pvt Ltd | D8: MSEDCL | E8: 150 | F8: 2.89 | G8: =IF(D8="Merchant",Assumptions!$E$49,IF(AND(A8="Operational",OR(B8="WSH",B8="FDRE")),Assumptions!$B$37,F8)) -> 2.89 | H8: 44092 | I8: 43831 | J8: =MAX(0,(YEAR(I8)-YEAR(Assumptions!$B$74))*12+(MONTH(I8)-MONTH(Assumptions!$B$74))) -> 0 | K8: =IF(B8="Solar",Assumptions!$B$34,IF(B8="Wind",Assumptions!$B$35,IF(B8="WSH",Assumptions!$E$40,Assumptions!$E$41))) -> 0.2448 | L8: =MAX(0,MIN(12,60)-MAX(0,$J8)) -> 12 | M8: =$E8*1000*8760*$K8*$G8*L8/12/10000000 -> 92.961821 | N8: =MAX(0,MIN(24,60)-MAX(12,$J8)) -> 12 | O8: =$E8*1000*8760*$K8*$G8*N8/12/10000000 -> 92.961821 | P8: =MAX(0,MIN(36,60)-MAX(24,$J8)) -> 12 | Q8: =$E8*1000*8760*$K8*$G8*P8/12/10000000 -> 92.961821 | R8: =MAX(0,MIN(48,60)-MAX(36,$J8)) -> 12 | S8: =$E8*1000*8760*$K8*$G8*R8/12/10000000 -> 92.961821 | T8: =MAX(0,MIN(60,60)-MAX(48,$J8)) -> 12 | U8: =$E8*1000*8760*$K8*$G8*T8/12/10000000 -> 92.961821
A9: Operational | B9: Solar | C9: Juniper Green Gamma One Pvt Ltd | D9: MSEDCL | E9: 75 | F9: 2.9 | G9: =IF(D9="Merchant",Assumptions!$E$49,IF(AND(A9="Operational",OR(B9="WSH",B9="FDRE")),Assumptions!$B$37,F9)) -> 2.9 | H9: 45111 | I9: 43831 | J9: =MAX(0,(YEAR(I9)-YEAR(Assumptions!$B$74))*12+(MONTH(I9)-MONTH(Assumptions!$B$74))) -> 0 | K9: =IF(B9="Solar",Assumptions!$B$34,IF(B9="Wind",Assumptions!$B$35,IF(B9="WSH",Assumptions!$E$40,Assumptions!$E$41))) -> 0.2448 | L9: =MAX(0,MIN(12,60)-MAX(0,$J9)) -> 12 | M9: =$E9*1000*8760*$K9*$G9*L9/12/10000000 -> 46.641744 | N9: =MAX(0,MIN(24,60)-MAX(12,$J9)) -> 12 | O9: =$E9*1000*8760*$K9*$G9*N9/12/10000000 -> 46.641744 | P9: =MAX(0,MIN(36,60)-MAX(24,$J9)) -> 12 | Q9: =$E9*1000*8760*$K9*$G9*P9/12/10000000 -> 46.641744 | R9: =MAX(0,MIN(48,60)-MAX(36,$J9)) -> 12 | S9: =$E9*1000*8760*$K9*$G9*R9/12/10000000 -> 46.641744 | T9: =MAX(0,MIN(60,60)-MAX(48,$J9)) -> 12 | U9: =$E9*1000*8760*$K9*$G9*T9/12/10000000 -> 46.641744
A10: Operational | B10: Solar | C10: Juniper Green Cosmic Pvt Ltd | D10: Merchant | E10: 100 | G10: =IF(D10="Merchant",Assumptions!$E$49,IF(AND(A10="Operational",OR(B10="WSH",B10="FDRE")),Assumptions!$B$37,F10)) -> 2.83 | H10: 45575 | I10: 43831 | J10: =MAX(0,(YEAR(I10)-YEAR(Assumptions!$B$74))*12+(MONTH(I10)-MONTH(Assumptions!$B$74))) -> 0 | K10: =IF(B10="Solar",Assumptions!$B$34,IF(B10="Wind",Assumptions!$B$35,IF(B10="WSH",Assumptions!$E$40,Assumptions!$E$41))) -> 0.2448 | L10: =MAX(0,MIN(12,60)-MAX(0,$J10)) -> 12 | M10: =$E10*1000*8760*$K10*$G10*L10/12/10000000 -> 60.687878 | N10: =MAX(0,MIN(24,60)-MAX(12,$J10)) -> 12 | O10: =$E10*1000*8760*$K10*$G10*N10/12/10000000 -> 60.687878 | P10: =MAX(0,MIN(36,60)-MAX(24,$J10)) -> 12 | Q10: =$E10*1000*8760*$K10*$G10*P10/12/10000000 -> 60.687878 | R10: =MAX(0,MIN(48,60)-MAX(36,$J10)) -> 12 | S10: =$E10*1000*8760*$K10*$G10*R10/12/10000000 -> 60.687878 | T10: =MAX(0,MIN(60,60)-MAX(48,$J10)) -> 12 | U10: =$E10*1000*8760*$K10*$G10*T10/12/10000000 -> 60.687878
A11: Operational | B11: Solar | C11: Juniper Nirjara Energy Pvt Ltd | D11: Merchant | E11: 50 | G11: =IF(D11="Merchant",Assumptions!$E$49,IF(AND(A11="Operational",OR(B11="WSH",B11="FDRE")),Assumptions!$B$37,F11)) -> 2.83 | H11: 45739 | I11: 43831 | J11: =MAX(0,(YEAR(I11)-YEAR(Assumptions!$B$74))*12+(MONTH(I11)-MONTH(Assumptions!$B$74))) -> 0 | K11: =IF(B11="Solar",Assumptions!$B$34,IF(B11="Wind",Assumptions!$B$35,IF(B11="WSH",Assumptions!$E$40,Assumptions!$E$41))) -> 0.2448 | L11: =MAX(0,MIN(12,60)-MAX(0,$J11)) -> 12 | M11: =$E11*1000*8760*$K11*$G11*L11/12/10000000 -> 30.343939 | N11: =MAX(0,MIN(24,60)-MAX(12,$J11)) -> 12 | O11: =$E11*1000*8760*$K11*$G11*N11/12/10000000 -> 30.343939 | P11: =MAX(0,MIN(36,60)-MAX(24,$J11)) -> 12 | Q11: =$E11*1000*8760*$K11*$G11*P11/12/10000000 -> 30.343939 | R11: =MAX(0,MIN(48,60)-MAX(36,$J11)) -> 12 | S11: =$E11*1000*8760*$K11*$G11*R11/12/10000000 -> 30.343939 | T11: =MAX(0,MIN(60,60)-MAX(48,$J11)) -> 12 | U11: =$E11*1000*8760*$K11*$G11*T11/12/10000000 -> 30.343939
A12: Operational | B12: Solar | C12: Juniper Green Ray Two Pvt Ltd | D12: MSEDCL | E12: 150 | F12: 2.75 | G12: =IF(D12="Merchant",Assumptions!$E$49,IF(AND(A12="Operational",OR(B12="WSH",B12="FDRE")),Assumptions!$B$37,F12)) -> 2.75 | H12: 45784 | I12: 43831 | J12: =MAX(0,(YEAR(I12)-YEAR(Assumptions!$B$74))*12+(MONTH(I12)-MONTH(Assumptions!$B$74))) -> 0 | K12: =IF(B12="Solar",Assumptions!$B$34,IF(B12="Wind",Assumptions!$B$35,IF(B12="WSH",Assumptions!$E$40,Assumptions!$E$41))) -> 0.2448 | L12: =MAX(0,MIN(12,60)-MAX(0,$J12)) -> 12 | M12: =$E12*1000*8760*$K12*$G12*L12/12/10000000 -> 88.45848 | N12: =MAX(0,MIN(24,60)-MAX(12,$J12)) -> 12 | O12: =$E12*1000*8760*$K12*$G12*N12/12/10000000 -> 88.45848 | P12: =MAX(0,MIN(36,60)-MAX(24,$J12)) -> 12 | Q12: =$E12*1000*8760*$K12*$G12*P12/12/10000000 -> 88.45848 | R12: =MAX(0,MIN(48,60)-MAX(36,$J12)) -> 12 | S12: =$E12*1000*8760*$K12*$G12*R12/12/10000000 -> 88.45848 | T12: =MAX(0,MIN(60,60)-MAX(48,$J12)) -> 12 | U12: =$E12*1000*8760*$K12*$G12*T12/12/10000000 -> 88.45848
A13: Operational | B13: Wind | C13: Juniper Green Beam Pvt Ltd | D13: GUVNL | E13: 69.3 | F13: 2.9 | G13: =IF(D13="Merchant",Assumptions!$E$49,IF(AND(A13="Operational",OR(B13="WSH",B13="FDRE")),Assumptions!$B$37,F13)) -> 2.9 | H13: 44909 | I13: 43831 | J13: =MAX(0,(YEAR(I13)-YEAR(Assumptions!$B$74))*12+(MONTH(I13)-MONTH(Assumptions!$B$74))) -> 0 | K13: =IF(B13="Solar",Assumptions!$B$34,IF(B13="Wind",Assumptions!$B$35,IF(B13="WSH",Assumptions!$E$40,Assumptions!$E$41))) -> 0.3184 | L13: =MAX(0,MIN(12,60)-MAX(0,$J13)) -> 12 | M13: =$E13*1000*8760*$K13*$G13*L13/12/10000000 -> 56.054231 | N13: =MAX(0,MIN(24,60)-MAX(12,$J13)) -> 12 | O13: =$E13*1000*8760*$K13*$G13*N13/12/10000000 -> 56.054231 | P13: =MAX(0,MIN(36,60)-MAX(24,$J13)) -> 12 | Q13: =$E13*1000*8760*$K13*$G13*P13/12/10000000 -> 56.054231 | R13: =MAX(0,MIN(48,60)-MAX(36,$J13)) -> 12 | S13: =$E13*1000*8760*$K13*$G13*R13/12/10000000 -> 56.054231 | T13: =MAX(0,MIN(60,60)-MAX(48,$J13)) -> 12 | U13: =$E13*1000*8760*$K13*$G13*T13/12/10000000 -> 56.054231
A14: Operational | B14: Wind | C14: Juniper Green Beam Pvt Ltd | D14: GUVNL | E14: 50.4 | F14: 2.95 | G14: =IF(D14="Merchant",Assumptions!$E$49,IF(AND(A14="Operational",OR(B14="WSH",B14="FDRE")),Assumptions!$B$37,F14)) -> 2.95 | H14: 45056 | I14: 43831 | J14: =MAX(0,(YEAR(I14)-YEAR(Assumptions!$B$74))*12+(MONTH(I14)-MONTH(Assumptions!$B$74))) -> 0 | K14: =IF(B14="Solar",Assumptions!$B$34,IF(B14="Wind",Assumptions!$B$35,IF(B14="WSH",Assumptions!$E$40,Assumptions!$E$41))) -> 0.3184 | L14: =MAX(0,MIN(12,60)-MAX(0,$J14)) -> 12 | M14: =$E14*1000*8760*$K14*$G14*L14/12/10000000 -> 41.469588 | N14: =MAX(0,MIN(24,60)-MAX(12,$J14)) -> 12 | O14: =$E14*1000*8760*$K14*$G14*N14/12/10000000 -> 41.469588 | P14: =MAX(0,MIN(36,60)-MAX(24,$J14)) -> 12 | Q14: =$E14*1000*8760*$K14*$G14*P14/12/10000000 -> 41.469588 | R14: =MAX(0,MIN(48,60)-MAX(36,$J14)) -> 12 | S14: =$E14*1000*8760*$K14*$G14*R14/12/10000000 -> 41.469588 | T14: =MAX(0,MIN(60,60)-MAX(48,$J14)) -> 12 | U14: =$E14*1000*8760*$K14*$G14*T14/12/10000000 -> 41.469588
A15: Operational | B15: Wind | C15: Juniper Green Kite Pvt Ltd | D15: GUVNL | E15: 72.45 | F15: 3.11 | G15: =IF(D15="Merchant",Assumptions!$E$49,IF(AND(A15="Operational",OR(B15="WSH",B15="FDRE")),Assumptions!$B$37,F15)) -> 3.11 | H15: 45330 | I15: 43831 | J15: =MAX(0,(YEAR(I15)-YEAR(Assumptions!$B$74))*12+(MONTH(I15)-MONTH(Assumptions!$B$74))) -> 0 | K15: =IF(B15="Solar",Assumptions!$B$34,IF(B15="Wind",Assumptions!$B$35,IF(B15="WSH",Assumptions!$E$40,Assumptions!$E$41))) -> 0.3184 | L15: =MAX(0,MIN(12,60)-MAX(0,$J15)) -> 12 | M15: =$E15*1000*8760*$K15*$G15*L15/12/10000000 -> 62.845754 | N15: =MAX(0,MIN(24,60)-MAX(12,$J15)) -> 12 | O15: =$E15*1000*8760*$K15*$G15*N15/12/10000000 -> 62.845754 | P15: =MAX(0,MIN(36,60)-MAX(24,$J15)) -> 12 | Q15: =$E15*1000*8760*$K15*$G15*P15/12/10000000 -> 62.845754 | R15: =MAX(0,MIN(48,60)-MAX(36,$J15)) -> 12 | S15: =$E15*1000*8760*$K15*$G15*R15/12/10000000 -> 62.845754 | T15: =MAX(0,MIN(60,60)-MAX(48,$J15)) -> 12 | U15: =$E15*1000*8760*$K15*$G15*T15/12/10000000 -> 62.845754
A16: Operational | B16: Wind | C16: Juniper Green Kite Pvt Ltd | D16: GUVNL | E16: 20 | F16: 3.44 | G16: =IF(D16="Merchant",Assumptions!$E$49,IF(AND(A16="Operational",OR(B16="WSH",B16="FDRE")),Assumptions!$B$37,F16)) -> 3.44 | H16: 45463 | I16: 43831 | J16: =MAX(0,(YEAR(I16)-YEAR(Assumptions!$B$74))*12+(MONTH(I16)-MONTH(Assumptions!$B$74))) -> 0 | K16: =IF(B16="Solar",Assumptions!$B$34,IF(B16="Wind",Assumptions!$B$35,IF(B16="WSH",Assumptions!$E$40,Assumptions!$E$41))) -> 0.3184 | L16: =MAX(0,MIN(12,60)-MAX(0,$J16)) -> 12 | M16: =$E16*1000*8760*$K16*$G16*L16/12/10000000 -> 19.189586 | N16: =MAX(0,MIN(24,60)-MAX(12,$J16)) -> 12 | O16: =$E16*1000*8760*$K16*$G16*N16/12/10000000 -> 19.189586 | P16: =MAX(0,MIN(36,60)-MAX(24,$J16)) -> 12 | Q16: =$E16*1000*8760*$K16*$G16*P16/12/10000000 -> 19.189586 | R16: =MAX(0,MIN(48,60)-MAX(36,$J16)) -> 12 | S16: =$E16*1000*8760*$K16*$G16*R16/12/10000000 -> 19.189586 | T16: =MAX(0,MIN(60,60)-MAX(48,$J16)) -> 12 | U16: =$E16*1000*8760*$K16*$G16*T16/12/10000000 -> 19.189586
A17: Operational | B17: WSH | C17: Juniper Green Power Five Pvt Ltd | D17: MSEDCL | E17: 75 | F17: 3.6 | G17: =IF(D17="Merchant",Assumptions!$E$49,IF(AND(A17="Operational",OR(B17="WSH",B17="FDRE")),Assumptions!$B$37,F17)) -> 2.8 | H17: 44909 | I17: 43831 | J17: =MAX(0,(YEAR(I17)-YEAR(Assumptions!$B$74))*12+(MONTH(I17)-MONTH(Assumptions!$B$74))) -> 0 | K17: =IF(B17="Solar",Assumptions!$B$34,IF(B17="Wind",Assumptions!$B$35,IF(B17="WSH",Assumptions!$E$40,Assumptions!$E$41))) -> 0.4 | L17: =MAX(0,MIN(12,60)-MAX(0,$J17)) -> 12 | M17: =$E17*1000*8760*$K17*$G17*L17/12/10000000 -> 73.584 | N17: =MAX(0,MIN(24,60)-MAX(12,$J17)) -> 12 | O17: =$E17*1000*8760*$K17*$G17*N17/12/10000000 -> 73.584 | P17: =MAX(0,MIN(36,60)-MAX(24,$J17)) -> 12 | Q17: =$E17*1000*8760*$K17*$G17*P17/12/10000000 -> 73.584 | R17: =MAX(0,MIN(48,60)-MAX(36,$J17)) -> 12 | S17: =$E17*1000*8760*$K17*$G17*R17/12/10000000 -> 73.584 | T17: =MAX(0,MIN(60,60)-MAX(48,$J17)) -> 12 | U17: =$E17*1000*8760*$K17*$G17*T17/12/10000000 -> 73.584
A18: Operational | B18: WSH | C18: Juniper Green Spark Ten Pvt Ltd | D18: MSEDCL | E18: 75 | F18: 3.6 | G18: =IF(D18="Merchant",Assumptions!$E$49,IF(AND(A18="Operational",OR(B18="WSH",B18="FDRE")),Assumptions!$B$37,F18)) -> 2.8 | H18: 44909 | I18: 43831 | J18: =MAX(0,(YEAR(I18)-YEAR(Assumptions!$B$74))*12+(MONTH(I18)-MONTH(Assumptions!$B$74))) -> 0 | K18: =IF(B18="Solar",Assumptions!$B$34,IF(B18="Wind",Assumptions!$B$35,IF(B18="WSH",Assumptions!$E$40,Assumptions!$E$41))) -> 0.4 | L18: =MAX(0,MIN(12,60)-MAX(0,$J18)) -> 12 | M18: =$E18*1000*8760*$K18*$G18*L18/12/10000000 -> 73.584 | N18: =MAX(0,MIN(24,60)-MAX(12,$J18)) -> 12 | O18: =$E18*1000*8760*$K18*$G18*N18/12/10000000 -> 73.584 | P18: =MAX(0,MIN(36,60)-MAX(24,$J18)) -> 12 | Q18: =$E18*1000*8760*$K18*$G18*P18/12/10000000 -> 73.584 | R18: =MAX(0,MIN(48,60)-MAX(36,$J18)) -> 12 | S18: =$E18*1000*8760*$K18*$G18*R18/12/10000000 -> 73.584 | T18: =MAX(0,MIN(60,60)-MAX(48,$J18)) -> 12 | U18: =$E18*1000*8760*$K18*$G18*T18/12/10000000 -> 73.584
A19: Operational | B19: WSH | C19: Juniper Green Energy Ltd | D19: GUVNL | E19: 100.45 | F19: 3.04 | G19: =IF(D19="Merchant",Assumptions!$E$49,IF(AND(A19="Operational",OR(B19="WSH",B19="FDRE")),Assumptions!$B$37,F19)) -> 2.8 | H19: 45477 | I19: 43831 | J19: =MAX(0,(YEAR(I19)-YEAR(Assumptions!$B$74))*12+(MONTH(I19)-MONTH(Assumptions!$B$74))) -> 0 | K19: =IF(B19="Solar",Assumptions!$B$34,IF(B19="Wind",Assumptions!$B$35,IF(B19="WSH",Assumptions!$E$40,Assumptions!$E$41))) -> 0.4 | L19: =MAX(0,MIN(12,60)-MAX(0,$J19)) -> 12 | M19: =$E19*1000*8760*$K19*$G19*L19/12/10000000 -> 98.553504 | N19: =MAX(0,MIN(24,60)-MAX(12,$J19)) -> 12 | O19: =$E19*1000*8760*$K19*$G19*N19/12/10000000 -> 98.553504 | P19: =MAX(0,MIN(36,60)-MAX(24,$J19)) -> 12 | Q19: =$E19*1000*8760*$K19*$G19*P19/12/10000000 -> 98.553504 | R19: =MAX(0,MIN(48,60)-MAX(36,$J19)) -> 12 | S19: =$E19*1000*8760*$K19*$G19*R19/12/10000000 -> 98.553504 | T19: =MAX(0,MIN(60,60)-MAX(48,$J19)) -> 12 | U19: =$E19*1000*8760*$K19*$G19*T19/12/10000000 -> 98.553504
A20: Operational | B20: WSH | C20: Juniper Green Spark Four Pvt Ltd | D20: GUVNL | E20: 30.3 | F20: 3.3 | G20: =IF(D20="Merchant",Assumptions!$E$49,IF(AND(A20="Operational",OR(B20="WSH",B20="FDRE")),Assumptions!$B$37,F20)) -> 2.8 | H20: 45575 | I20: 43831 | J20: =MAX(0,(YEAR(I20)-YEAR(Assumptions!$B$74))*12+(MONTH(I20)-MONTH(Assumptions!$B$74))) -> 0 | K20: =IF(B20="Solar",Assumptions!$B$34,IF(B20="Wind",Assumptions!$B$35,IF(B20="WSH",Assumptions!$E$40,Assumptions!$E$41))) -> 0.4 | L20: =MAX(0,MIN(12,60)-MAX(0,$J20)) -> 12 | M20: =$E20*1000*8760*$K20*$G20*L20/12/10000000 -> 29.727936 | N20: =MAX(0,MIN(24,60)-MAX(12,$J20)) -> 12 | O20: =$E20*1000*8760*$K20*$G20*N20/12/10000000 -> 29.727936 | P20: =MAX(0,MIN(36,60)-MAX(24,$J20)) -> 12 | Q20: =$E20*1000*8760*$K20*$G20*P20/12/10000000 -> 29.727936 | R20: =MAX(0,MIN(48,60)-MAX(36,$J20)) -> 12 | S20: =$E20*1000*8760*$K20*$G20*R20/12/10000000 -> 29.727936 | T20: =MAX(0,MIN(60,60)-MAX(48,$J20)) -> 12 | U20: =$E20*1000*8760*$K20*$G20*T20/12/10000000 -> 29.727936
A21: Operational | B21: FDRE | C21: Juniper Green Stellar Pvt Ltd | D21: SJVN | E21: 266.9 | F21: 4.38 | G21: =IF(D21="Merchant",Assumptions!$E$49,IF(AND(A21="Operational",OR(B21="WSH",B21="FDRE")),Assumptions!$B$37,F21)) -> 2.8 | H21: 45412 | I21: 43831 | J21: =MAX(0,(YEAR(I21)-YEAR(Assumptions!$B$74))*12+(MONTH(I21)-MONTH(Assumptions!$B$74))) -> 0 | K21: =IF(B21="Solar",Assumptions!$B$34,IF(B21="Wind",Assumptions!$B$35,IF(B21="WSH",Assumptions!$E$40,Assumptions!$E$41))) -> 0.5 | L21: =MAX(0,MIN(12,60)-MAX(0,$J21)) -> 12 | M21: =$E21*1000*8760*$K21*$G21*L21/12/10000000 -> 327.32616 | N21: =MAX(0,MIN(24,60)-MAX(12,$J21)) -> 12 | O21: =$E21*1000*8760*$K21*$G21*N21/12/10000000 -> 327.32616 | P21: =MAX(0,MIN(36,60)-MAX(24,$J21)) -> 12 | Q21: =$E21*1000*8760*$K21*$G21*P21/12/10000000 -> 327.32616 | R21: =MAX(0,MIN(48,60)-MAX(36,$J21)) -> 12 | S21: =$E21*1000*8760*$K21*$G21*R21/12/10000000 -> 327.32616 | T21: =MAX(0,MIN(60,60)-MAX(48,$J21)) -> 12 | U21: =$E21*1000*8760*$K21*$G21*T21/12/10000000 -> 327.32616
A22: Operational | B22: FDRE | C22: Juniper Green Stellar Pvt Ltd | D22: SJVN | E22: 100 | F22: 4.38 | G22: =IF(D22="Merchant",Assumptions!$E$49,IF(AND(A22="Operational",OR(B22="WSH",B22="FDRE")),Assumptions!$B$37,F22)) -> 2.8 | H22: 45412 | I22: 43831 | J22: =MAX(0,(YEAR(I22)-YEAR(Assumptions!$B$74))*12+(MONTH(I22)-MONTH(Assumptions!$B$74))) -> 0 | K22: =IF(B22="Solar",Assumptions!$B$34,IF(B22="Wind",Assumptions!$B$35,IF(B22="WSH",Assumptions!$E$40,Assumptions!$E$41))) -> 0.5 | L22: =MAX(0,MIN(12,60)-MAX(0,$J22)) -> 12 | M22: =$E22*1000*8760*$K22*$G22*L22/12/10000000 -> 122.64 | N22: =MAX(0,MIN(24,60)-MAX(12,$J22)) -> 12 | O22: =$E22*1000*8760*$K22*$G22*N22/12/10000000 -> 122.64 | P22: =MAX(0,MIN(36,60)-MAX(24,$J22)) -> 12 | Q22: =$E22*1000*8760*$K22*$G22*P22/12/10000000 -> 122.64 | R22: =MAX(0,MIN(48,60)-MAX(36,$J22)) -> 12 | S22: =$E22*1000*8760*$K22*$G22*R22/12/10000000 -> 122.64 | T22: =MAX(0,MIN(60,60)-MAX(48,$J22)) -> 12 | U22: =$E22*1000*8760*$K22*$G22*T22/12/10000000 -> 122.64
A23: UCC | B23: Solar | C23: Juniper Green Beta Pvt Ltd | D23: Merchant | E23: 20 | G23: =IF(D23="Merchant",Assumptions!$E$49,IF(AND(A23="Operational",OR(B23="WSH",B23="FDRE")),Assumptions!$B$37,F23)) -> 2.83 | H23: 45292 | I23: 46192 | J23: =MAX(0,(YEAR(I23)-YEAR(Assumptions!$B$74))*12+(MONTH(I23)-MONTH(Assumptions!$B$74))) -> 2 | K23: =IF(B23="Solar",Assumptions!$B$34,IF(B23="Wind",Assumptions!$B$35,IF(B23="WSH",Assumptions!$E$40,Assumptions!$E$41))) -> 0.2448 | L23: =MAX(0,MIN(12,60)-MAX(0,$J23)) -> 10 | M23: =$E23*1000*8760*$K23*$G23*L23/12/10000000 -> 10.114646 | N23: =MAX(0,MIN(24,60)-MAX(12,$J23)) -> 12 | O23: =$E23*1000*8760*$K23*$G23*N23/12/10000000 -> 12.137576 | P23: =MAX(0,MIN(36,60)-MAX(24,$J23)) -> 12 | Q23: =$E23*1000*8760*$K23*$G23*P23/12/10000000 -> 12.137576 | R23: =MAX(0,MIN(48,60)-MAX(36,$J23)) -> 12 | S23: =$E23*1000*8760*$K23*$G23*R23/12/10000000 -> 12.137576 | T23: =MAX(0,MIN(60,60)-MAX(48,$J23)) -> 12 | U23: =$E23*1000*8760*$K23*$G23*T23/12/10000000 -> 12.137576
A24: UCC | B24: Wind | C24: Juniper Green Kite Pvt Ltd | D24: GUVNL | E24: 70 | F24: 3.44 | G24: =IF(D24="Merchant",Assumptions!$E$49,IF(AND(A24="Operational",OR(B24="WSH",B24="FDRE")),Assumptions!$B$37,F24)) -> 3.44 | H24: 45463 | I24: 46192 | J24: =MAX(0,(YEAR(I24)-YEAR(Assumptions!$B$74))*12+(MONTH(I24)-MONTH(Assumptions!$B$74))) -> 2 | K24: =IF(B24="Solar",Assumptions!$B$34,IF(B24="Wind",Assumptions!$B$35,IF(B24="WSH",Assumptions!$E$40,Assumptions!$E$41))) -> 0.3184 | L24: =MAX(0,MIN(12,60)-MAX(0,$J24)) -> 10 | M24: =$E24*1000*8760*$K24*$G24*L24/12/10000000 -> 55.969626 | N24: =MAX(0,MIN(24,60)-MAX(12,$J24)) -> 12 | O24: =$E24*1000*8760*$K24*$G24*N24/12/10000000 -> 67.163551 | P24: =MAX(0,MIN(36,60)-MAX(24,$J24)) -> 12 | Q24: =$E24*1000*8760*$K24*$G24*P24/12/10000000 -> 67.163551 | R24: =MAX(0,MIN(48,60)-MAX(36,$J24)) -> 12 | S24: =$E24*1000*8760*$K24*$G24*R24/12/10000000 -> 67.163551 | T24: =MAX(0,MIN(60,60)-MAX(48,$J24)) -> 12 | U24: =$E24*1000*8760*$K24*$G24*T24/12/10000000 -> 67.163551
A25: UCC | B25: Wind | C25: Juniper Green Bess Two Pvt Ltd | D25: GUVNL | E25: 100 | F25: 3.56 | G25: =IF(D25="Merchant",Assumptions!$E$49,IF(AND(A25="Operational",OR(B25="WSH",B25="FDRE")),Assumptions!$B$37,F25)) -> 3.56 | H25: 45856 | I25: 46585 | J25: =MAX(0,(YEAR(I25)-YEAR(Assumptions!$B$74))*12+(MONTH(I25)-MONTH(Assumptions!$B$74))) -> 15 | K25: =IF(B25="Solar",Assumptions!$B$34,IF(B25="Wind",Assumptions!$B$35,IF(B25="WSH",Assumptions!$E$40,Assumptions!$E$41))) -> 0.3184 | L25: =MAX(0,MIN(12,60)-MAX(0,$J25)) -> 0 | M25: =$E25*1000*8760*$K25*$G25*L25/12/10000000 -> 0 | N25: =MAX(0,MIN(24,60)-MAX(12,$J25)) -> 9 | O25: =$E25*1000*8760*$K25*$G25*N25/12/10000000 -> 74.471213 | P25: =MAX(0,MIN(36,60)-MAX(24,$J25)) -> 12 | Q25: =$E25*1000*8760*$K25*$G25*P25/12/10000000 -> 99.29495 | R25: =MAX(0,MIN(48,60)-MAX(36,$J25)) -> 12 | S25: =$E25*1000*8760*$K25*$G25*R25/12/10000000 -> 99.29495 | T25: =MAX(0,MIN(60,60)-MAX(48,$J25)) -> 12 | U25: =$E25*1000*8760*$K25*$G25*T25/12/10000000 -> 99.29495
A26: UCC | B26: Wind | C26: Juniper Green Bess Delta Pvt Ltd | D26: GUVNL | E26: 50 | F26: 3.65 | G26: =IF(D26="Merchant",Assumptions!$E$49,IF(AND(A26="Operational",OR(B26="WSH",B26="FDRE")),Assumptions!$B$37,F26)) -> 3.65 | H26: 45852 | I26: 46697 | J26: =MAX(0,(YEAR(I26)-YEAR(Assumptions!$B$74))*12+(MONTH(I26)-MONTH(Assumptions!$B$74))) -> 19 | K26: =IF(B26="Solar",Assumptions!$B$34,IF(B26="Wind",Assumptions!$B$35,IF(B26="WSH",Assumptions!$E$40,Assumptions!$E$41))) -> 0.3184 | L26: =MAX(0,MIN(12,60)-MAX(0,$J26)) -> 0 | M26: =$E26*1000*8760*$K26*$G26*L26/12/10000000 -> 0 | N26: =MAX(0,MIN(24,60)-MAX(12,$J26)) -> 5 | O26: =$E26*1000*8760*$K26*$G26*N26/12/10000000 -> 21.20942 | P26: =MAX(0,MIN(36,60)-MAX(24,$J26)) -> 12 | Q26: =$E26*1000*8760*$K26*$G26*P26/12/10000000 -> 50.902608 | R26: =MAX(0,MIN(48,60)-MAX(36,$J26)) -> 12 | S26: =$E26*1000*8760*$K26*$G26*R26/12/10000000 -> 50.902608 | T26: =MAX(0,MIN(60,60)-MAX(48,$J26)) -> 12 | U26: =$E26*1000*8760*$K26*$G26*T26/12/10000000 -> 50.902608
A27: UCC | B27: WSH | C27: Juniper Green Beam Eight Pvt Ltd | D27: TPCL | E27: 75 | F27: 3.27 | G27: =IF(D27="Merchant",Assumptions!$E$49,IF(AND(A27="Operational",OR(B27="WSH",B27="FDRE")),Assumptions!$B$37,F27)) -> 3.27 | H27: 45380 | I27: 46134 | J27: =MAX(0,(YEAR(I27)-YEAR(Assumptions!$B$74))*12+(MONTH(I27)-MONTH(Assumptions!$B$74))) -> 0 | K27: =IF(B27="Solar",Assumptions!$B$34,IF(B27="Wind",Assumptions!$B$35,IF(B27="WSH",Assumptions!$E$40,Assumptions!$E$41))) -> 0.4 | L27: =MAX(0,MIN(12,60)-MAX(0,$J27)) -> 12 | M27: =$E27*1000*8760*$K27*$G27*L27/12/10000000 -> 85.9356 | N27: =MAX(0,MIN(24,60)-MAX(12,$J27)) -> 12 | O27: =$E27*1000*8760*$K27*$G27*N27/12/10000000 -> 85.9356 | P27: =MAX(0,MIN(36,60)-MAX(24,$J27)) -> 12 | Q27: =$E27*1000*8760*$K27*$G27*P27/12/10000000 -> 85.9356 | R27: =MAX(0,MIN(48,60)-MAX(36,$J27)) -> 12 | S27: =$E27*1000*8760*$K27*$G27*R27/12/10000000 -> 85.9356 | T27: =MAX(0,MIN(60,60)-MAX(48,$J27)) -> 12 | U27: =$E27*1000*8760*$K27*$G27*T27/12/10000000 -> 85.9356
A28: UCC | B28: WSH | C28: Juniper Green Energy Ltd | D28: GUVNL | E28: 50 | F28: 3.04 | G28: =IF(D28="Merchant",Assumptions!$E$49,IF(AND(A28="Operational",OR(B28="WSH",B28="FDRE")),Assumptions!$B$37,F28)) -> 3.04 | H28: 45477 | I28: 46206 | J28: =MAX(0,(YEAR(I28)-YEAR(Assumptions!$B$74))*12+(MONTH(I28)-MONTH(Assumptions!$B$74))) -> 3 | K28: =IF(B28="Solar",Assumptions!$B$34,IF(B28="Wind",Assumptions!$B$35,IF(B28="WSH",Assumptions!$E$40,Assumptions!$E$41))) -> 0.4 | L28: =MAX(0,MIN(12,60)-MAX(0,$J28)) -> 9 | M28: =$E28*1000*8760*$K28*$G28*L28/12/10000000 -> 39.9456 | N28: =MAX(0,MIN(24,60)-MAX(12,$J28)) -> 12 | O28: =$E28*1000*8760*$K28*$G28*N28/12/10000000 -> 53.2608 | P28: =MAX(0,MIN(36,60)-MAX(24,$J28)) -> 12 | Q28: =$E28*1000*8760*$K28*$G28*P28/12/10000000 -> 53.2608 | R28: =MAX(0,MIN(48,60)-MAX(36,$J28)) -> 12 | S28: =$E28*1000*8760*$K28*$G28*R28/12/10000000 -> 53.2608 | T28: =MAX(0,MIN(60,60)-MAX(48,$J28)) -> 12 | U28: =$E28*1000*8760*$K28*$G28*T28/12/10000000 -> 53.2608
A29: UCC | B29: WSH | C29: Juniper Green Beta Pvt Ltd | D29: SECI | E29: 185 | F29: 3.21 | G29: =IF(D29="Merchant",Assumptions!$E$49,IF(AND(A29="Operational",OR(B29="WSH",B29="FDRE")),Assumptions!$B$37,F29)) -> 3.21 | H29: 45463 | I29: 46396 | J29: =MAX(0,(YEAR(I29)-YEAR(Assumptions!$B$74))*12+(MONTH(I29)-MONTH(Assumptions!$B$74))) -> 9 | K29: =IF(B29="Solar",Assumptions!$B$34,IF(B29="Wind",Assumptions!$B$35,IF(B29="WSH",Assumptions!$E$40,Assumptions!$E$41))) -> 0.4 | L29: =MAX(0,MIN(12,60)-MAX(0,$J29)) -> 3 | M29: =$E29*1000*8760*$K29*$G29*L29/12/10000000 -> 52.02126 | N29: =MAX(0,MIN(24,60)-MAX(12,$J29)) -> 12 | O29: =$E29*1000*8760*$K29*$G29*N29/12/10000000 -> 208.08504 | P29: =MAX(0,MIN(36,60)-MAX(24,$J29)) -> 12 | Q29: =$E29*1000*8760*$K29*$G29*P29/12/10000000 -> 208.08504 | R29: =MAX(0,MIN(48,60)-MAX(36,$J29)) -> 12 | S29: =$E29*1000*8760*$K29*$G29*R29/12/10000000 -> 208.08504 | T29: =MAX(0,MIN(60,60)-MAX(48,$J29)) -> 12 | U29: =$E29*1000*8760*$K29*$G29*T29/12/10000000 -> 208.08504
A30: UCC | B30: WSH | C30: Juniper Green Beta Pvt Ltd | D30: NTPC | E30: 238.1 | F30: 3.36 | G30: =IF(D30="Merchant",Assumptions!$E$49,IF(AND(A30="Operational",OR(B30="WSH",B30="FDRE")),Assumptions!$B$37,F30)) -> 3.36 | H30: 45472 | I30: 46201 | J30: =MAX(0,(YEAR(I30)-YEAR(Assumptions!$B$74))*12+(MONTH(I30)-MONTH(Assumptions!$B$74))) -> 2 | K30: =IF(B30="Solar",Assumptions!$B$34,IF(B30="Wind",Assumptions!$B$35,IF(B30="WSH",Assumptions!$E$40,Assumptions!$E$41))) -> 0.4 | L30: =MAX(0,MIN(12,60)-MAX(0,$J30)) -> 10 | M30: =$E30*1000*8760*$K30*$G30*L30/12/10000000 -> 233.60467 | N30: =MAX(0,MIN(24,60)-MAX(12,$J30)) -> 12 | O30: =$E30*1000*8760*$K30*$G30*N30/12/10000000 -> 280.32561 | P30: =MAX(0,MIN(36,60)-MAX(24,$J30)) -> 12 | Q30: =$E30*1000*8760*$K30*$G30*P30/12/10000000 -> 280.32561 | R30: =MAX(0,MIN(48,60)-MAX(36,$J30)) -> 12 | S30: =$E30*1000*8760*$K30*$G30*R30/12/10000000 -> 280.32561 | T30: =MAX(0,MIN(60,60)-MAX(48,$J30)) -> 12 | U30: =$E30*1000*8760*$K30*$G30*T30/12/10000000 -> 280.32561
A31: UCC | B31: WSH | C31: Juniper Green Power Five Pvt Ltd + Juniper Green ETA Five Pvt Ltd | D31: MSEDCL | E31: 127.8 | F31: 3.6 | G31: =IF(D31="Merchant",Assumptions!$E$49,IF(AND(A31="Operational",OR(B31="WSH",B31="FDRE")),Assumptions!$B$37,F31)) -> 3.6 | H31: 45614 | I31: 46343 | J31: =MAX(0,(YEAR(I31)-YEAR(Assumptions!$B$74))*12+(MONTH(I31)-MONTH(Assumptions!$B$74))) -> 7 | K31: =IF(B31="Solar",Assumptions!$B$34,IF(B31="Wind",Assumptions!$B$35,IF(B31="WSH",Assumptions!$E$40,Assumptions!$E$41))) -> 0.4 | L31: =MAX(0,MIN(12,60)-MAX(0,$J31)) -> 5 | M31: =$E31*1000*8760*$K31*$G31*L31/12/10000000 -> 67.17168 | N31: =MAX(0,MIN(24,60)-MAX(12,$J31)) -> 12 | O31: =$E31*1000*8760*$K31*$G31*N31/12/10000000 -> 161.21203 | P31: =MAX(0,MIN(36,60)-MAX(24,$J31)) -> 12 | Q31: =$E31*1000*8760*$K31*$G31*P31/12/10000000 -> 161.21203 | R31: =MAX(0,MIN(48,60)-MAX(36,$J31)) -> 12 | S31: =$E31*1000*8760*$K31*$G31*R31/12/10000000 -> 161.21203 | T31: =MAX(0,MIN(60,60)-MAX(48,$J31)) -> 12 | U31: =$E31*1000*8760*$K31*$G31*T31/12/10000000 -> 161.21203
A32: UCC | B32: WSH | C32: Juniper Green Spark Ten Pvt Ltd | D32: MSEDCL | E32: 25 | F32: 3.6 | G32: =IF(D32="Merchant",Assumptions!$E$49,IF(AND(A32="Operational",OR(B32="WSH",B32="FDRE")),Assumptions!$B$37,F32)) -> 3.6 | H32: 45614 | I32: 46343 | J32: =MAX(0,(YEAR(I32)-YEAR(Assumptions!$B$74))*12+(MONTH(I32)-MONTH(Assumptions!$B$74))) -> 7 | K32: =IF(B32="Solar",Assumptions!$B$34,IF(B32="Wind",Assumptions!$B$35,IF(B32="WSH",Assumptions!$E$40,Assumptions!$E$41))) -> 0.4 | L32: =MAX(0,MIN(12,60)-MAX(0,$J32)) -> 5 | M32: =$E32*1000*8760*$K32*$G32*L32/12/10000000 -> 13.14 | N32: =MAX(0,MIN(24,60)-MAX(12,$J32)) -> 12 | O32: =$E32*1000*8760*$K32*$G32*N32/12/10000000 -> 31.536 | P32: =MAX(0,MIN(36,60)-MAX(24,$J32)) -> 12 | Q32: =$E32*1000*8760*$K32*$G32*P32/12/10000000 -> 31.536 | R32: =MAX(0,MIN(48,60)-MAX(36,$J32)) -> 12 | S32: =$E32*1000*8760*$K32*$G32*R32/12/10000000 -> 31.536 | T32: =MAX(0,MIN(60,60)-MAX(48,$J32)) -> 12 | U32: =$E32*1000*8760*$K32*$G32*T32/12/10000000 -> 31.536
A33: UCC | B33: WSH | C33: Juniper Green Spark Four Pvt Ltd | D33: GUVNL | E33: 90 | F33: 3.3 | G33: =IF(D33="Merchant",Assumptions!$E$49,IF(AND(A33="Operational",OR(B33="WSH",B33="FDRE")),Assumptions!$B$37,F33)) -> 3.3 | H33: 45575 | I33: 46304 | J33: =MAX(0,(YEAR(I33)-YEAR(Assumptions!$B$74))*12+(MONTH(I33)-MONTH(Assumptions!$B$74))) -> 6 | K33: =IF(B33="Solar",Assumptions!$B$34,IF(B33="Wind",Assumptions!$B$35,IF(B33="WSH",Assumptions!$E$40,Assumptions!$E$41))) -> 0.4 | L33: =MAX(0,MIN(12,60)-MAX(0,$J33)) -> 6 | M33: =$E33*1000*8760*$K33*$G33*L33/12/10000000 -> 52.0344 | N33: =MAX(0,MIN(24,60)-MAX(12,$J33)) -> 12 | O33: =$E33*1000*8760*$K33*$G33*N33/12/10000000 -> 104.0688 | P33: =MAX(0,MIN(36,60)-MAX(24,$J33)) -> 12 | Q33: =$E33*1000*8760*$K33*$G33*P33/12/10000000 -> 104.0688 | R33: =MAX(0,MIN(48,60)-MAX(36,$J33)) -> 12 | S33: =$E33*1000*8760*$K33*$G33*R33/12/10000000 -> 104.0688 | T33: =MAX(0,MIN(60,60)-MAX(48,$J33)) -> 12 | U33: =$E33*1000*8760*$K33*$G33*T33/12/10000000 -> 104.0688
A34: UCC | B34: FDRE | C34: Juniper Green Stellar Pvt Ltd | D34: SJVN | E34: 209.7 | F34: 4.38 | G34: =IF(D34="Merchant",Assumptions!$E$49,IF(AND(A34="Operational",OR(B34="WSH",B34="FDRE")),Assumptions!$B$37,F34)) -> 4.38 | H34: 45412 | I34: 46356 | J34: =MAX(0,(YEAR(I34)-YEAR(Assumptions!$B$74))*12+(MONTH(I34)-MONTH(Assumptions!$B$74))) -> 7 | K34: =IF(B34="Solar",Assumptions!$B$34,IF(B34="Wind",Assumptions!$B$35,IF(B34="WSH",Assumptions!$E$40,Assumptions!$E$41))) -> 0.5 | L34: =MAX(0,MIN(12,60)-MAX(0,$J34)) -> 5 | M34: =$E34*1000*8760*$K34*$G34*L34/12/10000000 -> 167.62369 | N34: =MAX(0,MIN(24,60)-MAX(12,$J34)) -> 12 | O34: =$E34*1000*8760*$K34*$G34*N34/12/10000000 -> 402.29687 | P34: =MAX(0,MIN(36,60)-MAX(24,$J34)) -> 12 | Q34: =$E34*1000*8760*$K34*$G34*P34/12/10000000 -> 402.29687 | R34: =MAX(0,MIN(48,60)-MAX(36,$J34)) -> 12 | S34: =$E34*1000*8760*$K34*$G34*R34/12/10000000 -> 402.29687 | T34: =MAX(0,MIN(60,60)-MAX(48,$J34)) -> 12 | U34: =$E34*1000*8760*$K34*$G34*T34/12/10000000 -> 402.29687
A35: UCC | B35: FDRE | C35: Juniper Green Stellar Pvt Ltd | D35: SJVN | E35: 92.4 | F35: 4.38 | G35: =IF(D35="Merchant",Assumptions!$E$49,IF(AND(A35="Operational",OR(B35="WSH",B35="FDRE")),Assumptions!$B$37,F35)) -> 4.38 | H35: 45412 | I35: 46356 | J35: =MAX(0,(YEAR(I35)-YEAR(Assumptions!$B$74))*12+(MONTH(I35)-MONTH(Assumptions!$B$74))) -> 7 | K35: =IF(B35="Solar",Assumptions!$B$34,IF(B35="Wind",Assumptions!$B$35,IF(B35="WSH",Assumptions!$E$40,Assumptions!$E$41))) -> 0.5 | L35: =MAX(0,MIN(12,60)-MAX(0,$J35)) -> 5 | M35: =$E35*1000*8760*$K35*$G35*L35/12/10000000 -> 73.85994 | N35: =MAX(0,MIN(24,60)-MAX(12,$J35)) -> 12 | O35: =$E35*1000*8760*$K35*$G35*N35/12/10000000 -> 177.26386 | P35: =MAX(0,MIN(36,60)-MAX(24,$J35)) -> 12 | Q35: =$E35*1000*8760*$K35*$G35*P35/12/10000000 -> 177.26386 | R35: =MAX(0,MIN(48,60)-MAX(36,$J35)) -> 12 | S35: =$E35*1000*8760*$K35*$G35*R35/12/10000000 -> 177.26386 | T35: =MAX(0,MIN(60,60)-MAX(48,$J35)) -> 12 | U35: =$E35*1000*8760*$K35*$G35*T35/12/10000000 -> 177.26386
... A40: UCC | B40: FDRE | C40: Juniper Green Sigma Eight Pvt Ltd | D40: TPCL | E40: 140 | F40: 4.76 | G40: =IF(D40="Merchant",Assumptions!$E$49,IF(AND(A40="Operational",OR(B40="WSH",B40="FDRE")),Assumptions!$B$37,F40)) -> 4.76 | H40: 45923 | I40: 46676 | J40: =MAX(0,(YEAR(I40)-YEAR(Assumptions!$B$74))*12+(MONTH(I40)-MONTH(Assumptions!$B$74))) -> 18 | K40: =IF(B40="Solar",Assumptions!$B$34,IF(B40="Wind",Assumptions!$B$35,IF(B40="WSH",Assumptions!$E$40,Assumptions!$E$41))) -> 0.5 | L40: =MAX(0,MIN(12,60)-MAX(0,$J40)) -> 0 | M40: =$E40*1000*8760*$K40*$G40*L40/12/10000000 -> 0 | N40: =MAX(0,MIN(24,60)-MAX(12,$J40)) -> 6 | O40: =$E40*1000*8760*$K40*$G40*N40/12/10000000 -> 145.9416 | P40: =MAX(0,MIN(36,60)-MAX(24,$J40)) -> 12 | Q40: =$E40*1000*8760*$K40*$G40*P40/12/10000000 -> 291.8832 | R40: =MAX(0,MIN(48,60)-MAX(36,$J40)) -> 12 | S40: =$E40*1000*8760*$K40*$G40*R40/12/10000000 -> 291.8832 | T40: =MAX(0,MIN(60,60)-MAX(48,$J40)) -> 12 | U40: =$E40*1000*8760*$K40*$G40*T40/12/10000000 -> 291.8832
A41: UCA | B41: WSH | C41: Juniper Green Beam Six Pvt Ltd | D41: SECI | E41: 180 | F41: 3.25 | G41: =IF(D41="Merchant",Assumptions!$E$49,IF(AND(A41="Operational",OR(B41="WSH",B41="FDRE")),Assumptions!$B$37,F41)) -> 3.25 | H41: 45580 | I41: =EDATE(H41,ROUND(Assumptions!$E$44,0)) -> 47041 | J41: =MAX(0,(YEAR(I41)-YEAR(Assumptions!$B$74))*12+(MONTH(I41)-MONTH(Assumptions!$B$74))) -> 30 | K41: =IF(B41="Solar",Assumptions!$B$34,IF(B41="Wind",Assumptions!$B$35,IF(B41="WSH",Assumptions!$E$40,Assumptions!$E$41))) -> 0.4 | L41: =MAX(0,MIN(12,60)-MAX(0,$J41)) -> 0 | M41: =$E41*1000*8760*$K41*$G41*L41/12/10000000 -> 0 | N41: =MAX(0,MIN(24,60)-MAX(12,$J41)) -> 0 | O41: =$E41*1000*8760*$K41*$G41*N41/12/10000000 -> 0 | P41: =MAX(0,MIN(36,60)-MAX(24,$J41)) -> 6 | Q41: =$E41*1000*8760*$K41*$G41*P41/12/10000000 -> 102.492 | R41: =MAX(0,MIN(48,60)-MAX(36,$J41)) -> 12 | S41: =$E41*1000*8760*$K41*$G41*R41/12/10000000 -> 204.984 | T41: =MAX(0,MIN(60,60)-MAX(48,$J41)) -> 12 | U41: =$E41*1000*8760*$K41*$G41*T41/12/10000000 -> 204.984
A42: UCA | B42: WSH | C42: Juniper Green Light Four Pvt Ltd | D42: SJVN | E42: 180 | F42: 3.43 | G42: =IF(D42="Merchant",Assumptions!$E$49,IF(AND(A42="Operational",OR(B42="WSH",B42="FDRE")),Assumptions!$B$37,F42)) -> 3.43 | H42: 45357 | I42: =EDATE(H42,ROUND(Assumptions!$E$44,0)) -> 46818 | J42: =MAX(0,(YEAR(I42)-YEAR(Assumptions!$B$74))*12+(MONTH(I42)-MONTH(Assumptions!$B$74))) -> 23 | K42: =IF(B42="Solar",Assumptions!$B$34,IF(B42="Wind",Assumptions!$B$35,IF(B42="WSH",Assumptions!$E$40,Assumptions!$E$41))) -> 0.4 | L42: =MAX(0,MIN(12,60)-MAX(0,$J42)) -> 0 | M42: =$E42*1000*8760*$K42*$G42*L42/12/10000000 -> 0 | N42: =MAX(0,MIN(24,60)-MAX(12,$J42)) -> 1 | O42: =$E42*1000*8760*$K42*$G42*N42/12/10000000 -> 18.02808 | P42: =MAX(0,MIN(36,60)-MAX(24,$J42)) -> 12 | Q42: =$E42*1000*8760*$K42*$G42*P42/12/10000000 -> 216.33696 | R42: =MAX(0,MIN(48,60)-MAX(36,$J42)) -> 12 | S42: =$E42*1000*8760*$K42*$G42*R42/12/10000000 -> 216.33696 | T42: =MAX(0,MIN(60,60)-MAX(48,$J42)) -> 12 | U42: =$E42*1000*8760*$K42*$G42*T42/12/10000000 -> 216.33696
A43: UCA | B43: WSH | C43: Juniper Green Alpha Three Pvt Ltd | D43: SJVN | E43: 360 | F43: 3.19 | G43: =IF(D43="Merchant",Assumptions!$E$49,IF(AND(A43="Operational",OR(B43="WSH",B43="FDRE")),Assumptions!$B$37,F43)) -> 3.19 | H43: 45630 | I43: =EDATE(H43,ROUND(Assumptions!$E$44,0)) -> 47091 | J43: =MAX(0,(YEAR(I43)-YEAR(Assumptions!$B$74))*12+(MONTH(I43)-MONTH(Assumptions!$B$74))) -> 32 | K43: =IF(B43="Solar",Assumptions!$B$34,IF(B43="Wind",Assumptions!$B$35,IF(B43="WSH",Assumptions!$E$40,Assumptions!$E$41))) -> 0.4 | L43: =MAX(0,MIN(12,60)-MAX(0,$J43)) -> 0 | M43: =$E43*1000*8760*$K43*$G43*L43/12/10000000 -> 0 | N43: =MAX(0,MIN(24,60)-MAX(12,$J43)) -> 0 | O43: =$E43*1000*8760*$K43*$G43*N43/12/10000000 -> 0 | P43: =MAX(0,MIN(36,60)-MAX(24,$J43)) -> 4 | Q43: =$E43*1000*8760*$K43*$G43*P43/12/10000000 -> 134.13312 | R43: =MAX(0,MIN(48,60)-MAX(36,$J43)) -> 12 | S43: =$E43*1000*8760*$K43*$G43*R43/12/10000000 -> 402.39936 | T43: =MAX(0,MIN(60,60)-MAX(48,$J43)) -> 12 | U43: =$E43*1000*8760*$K43*$G43*T43/12/10000000 -> 402.39936
A44: UCA | B44: WSH | C44: Juniper Green Energy Ltd | D44: NTPC | E44: 360 | F44: 3.29 | G44: =IF(D44="Merchant",Assumptions!$E$49,IF(AND(A44="Operational",OR(B44="WSH",B44="FDRE")),Assumptions!$B$37,F44)) -> 3.29 | H44: 45405 | I44: =EDATE(H44,ROUND(Assumptions!$E$44,0)) -> 46866 | J44: =MAX(0,(YEAR(I44)-YEAR(Assumptions!$B$74))*12+(MONTH(I44)-MONTH(Assumptions!$B$74))) -> 24 | K44: =IF(B44="Solar",Assumptions!$B$34,IF(B44="Wind",Assumptions!$B$35,IF(B44="WSH",Assumptions!$E$40,Assumptions!$E$41))) -> 0.4 | L44: =MAX(0,MIN(12,60)-MAX(0,$J44)) -> 0 | M44: =$E44*1000*8760*$K44*$G44*L44/12/10000000 -> 0 | N44: =MAX(0,MIN(24,60)-MAX(12,$J44)) -> 0 | O44: =$E44*1000*8760*$K44*$G44*N44/12/10000000 -> 0 | P44: =MAX(0,MIN(36,60)-MAX(24,$J44)) -> 12 | Q44: =$E44*1000*8760*$K44*$G44*P44/12/10000000 -> 415.01376 | R44: =MAX(0,MIN(48,60)-MAX(36,$J44)) -> 12 | S44: =$E44*1000*8760*$K44*$G44*R44/12/10000000 -> 415.01376 | T44: =MAX(0,MIN(60,60)-MAX(48,$J44)) -> 12 | U44: =$E44*1000*8760*$K44*$G44*T44/12/10000000 -> 415.01376
A45: UCA | B45: WSH | C45: Juniper Green Gem Pvt Ltd | D45: NHPC | E45: 180 | F45: 3.48 | G45: =IF(D45="Merchant",Assumptions!$E$49,IF(AND(A45="Operational",OR(B45="WSH",B45="FDRE")),Assumptions!$B$37,F45)) -> 3.48 | H45: 45341 | I45: =EDATE(H45,ROUND(Assumptions!$E$44,0)) -> 46802 | J45: =MAX(0,(YEAR(I45)-YEAR(Assumptions!$B$74))*12+(MONTH(I45)-MONTH(Assumptions!$B$74))) -> 22 | K45: =IF(B45="Solar",Assumptions!$B$34,IF(B45="Wind",Assumptions!$B$35,IF(B45="WSH",Assumptions!$E$40,Assumptions!$E$41))) -> 0.4 | L45: =MAX(0,MIN(12,60)-MAX(0,$J45)) -> 0 | M45: =$E45*1000*8760*$K45*$G45*L45/12/10000000 -> 0 | N45: =MAX(0,MIN(24,60)-MAX(12,$J45)) -> 2 | O45: =$E45*1000*8760*$K45*$G45*N45/12/10000000 -> 36.58176 | P45: =MAX(0,MIN(36,60)-MAX(24,$J45)) -> 12 | Q45: =$E45*1000*8760*$K45*$G45*P45/12/10000000 -> 219.49056 | R45: =MAX(0,MIN(48,60)-MAX(36,$J45)) -> 12 | S45: =$E45*1000*8760*$K45*$G45*R45/12/10000000 -> 219.49056 | T45: =MAX(0,MIN(60,60)-MAX(48,$J45)) -> 12 | U45: =$E45*1000*8760*$K45*$G45*T45/12/10000000 -> 219.49056
A46: UCA | B46: WSH | C46: Juniper Green India Eight Pvt Ltd | D46: SECI | E46: 180 | F46: 3.43 | G46: =IF(D46="Merchant",Assumptions!$E$49,IF(AND(A46="Operational",OR(B46="WSH",B46="FDRE")),Assumptions!$B$37,F46)) -> 3.43 | H46: 45463 | I46: =EDATE(H46,ROUND(Assumptions!$E$44,0)) -> 46924 | J46: =MAX(0,(YEAR(I46)-YEAR(Assumptions!$B$74))*12+(MONTH(I46)-MONTH(Assumptions!$B$74))) -> 26 | K46: =IF(B46="Solar",Assumptions!$B$34,IF(B46="Wind",Assumptions!$B$35,IF(B46="WSH",Assumptions!$E$40,Assumptions!$E$41))) -> 0.4 | L46: =MAX(0,MIN(12,60)-MAX(0,$J46)) -> 0 | M46: =$E46*1000*8760*$K46*$G46*L46/12/10000000 -> 0 | N46: =MAX(0,MIN(24,60)-MAX(12,$J46)) -> 0 | O46: =$E46*1000*8760*$K46*$G46*N46/12/10000000 -> 0 | P46: =MAX(0,MIN(36,60)-MAX(24,$J46)) -> 10 | Q46: =$E46*1000*8760*$K46*$G46*P46/12/10000000 -> 180.2808 | R46: =MAX(0,MIN(48,60)-MAX(36,$J46)) -> 12 | S46: =$E46*1000*8760*$K46*$G46*R46/12/10000000 -> 216.33696 | T46: =MAX(0,MIN(60,60)-MAX(48,$J46)) -> 12 | U46: =$E46*1000*8760*$K46*$G46*T46/12/10000000 -> 216.33696
A47: UCA | B47: WSH | C47: Juniper Green Infinite Pvt Ltd | D47: NTPC | E47: 180 | F47: 3.43 | G47: =IF(D47="Merchant",Assumptions!$E$49,IF(AND(A47="Operational",OR(B47="WSH",B47="FDRE")),Assumptions!$B$37,F47)) -> 3.43 | H47: 45427 | I47: =EDATE(H47,ROUND(Assumptions!$E$44,0)) -> 46888 | J47: =MAX(0,(YEAR(I47)-YEAR(Assumptions!$B$74))*12+(MONTH(I47)-MONTH(Assumptions!$B$74))) -> 25 | K47: =IF(B47="Solar",Assumptions!$B$34,IF(B47="Wind",Assumptions!$B$35,IF(B47="WSH",Assumptions!$E$40,Assumptions!$E$41))) -> 0.4 | L47: =MAX(0,MIN(12,60)-MAX(0,$J47)) -> 0 | M47: =$E47*1000*8760*$K47*$G47*L47/12/10000000 -> 0 | N47: =MAX(0,MIN(24,60)-MAX(12,$J47)) -> 0 | O47: =$E47*1000*8760*$K47*$G47*N47/12/10000000 -> 0 | P47: =MAX(0,MIN(36,60)-MAX(24,$J47)) -> 11 | Q47: =$E47*1000*8760*$K47*$G47*P47/12/10000000 -> 198.30888 | R47: =MAX(0,MIN(48,60)-MAX(36,$J47)) -> 12 | S47: =$E47*1000*8760*$K47*$G47*R47/12/10000000 -> 216.33696 | T47: =MAX(0,MIN(60,60)-MAX(48,$J47)) -> 12 | U47: =$E47*1000*8760*$K47*$G47*T47/12/10000000 -> 216.33696
A48: UCA | B48: WSH | C48: Juniper Green India Alpha Pvt Ltd | D48: NTPC | E48: 180 | F48: 3.43 | G48: =IF(D48="Merchant",Assumptions!$E$49,IF(AND(A48="Operational",OR(B48="WSH",B48="FDRE")),Assumptions!$B$37,F48)) -> 3.43 | H48: 45526 | I48: =EDATE(H48,ROUND(Assumptions!$E$44,0)) -> 46987 | J48: =MAX(0,(YEAR(I48)-YEAR(Assumptions!$B$74))*12+(MONTH(I48)-MONTH(Assumptions!$B$74))) -> 28 | K48: =IF(B48="Solar",Assumptions!$B$34,IF(B48="Wind",Assumptions!$B$35,IF(B48="WSH",Assumptions!$E$40,Assumptions!$E$41))) -> 0.4 | L48: =MAX(0,MIN(12,60)-MAX(0,$J48)) -> 0 | M48: =$E48*1000*8760*$K48*$G48*L48/12/10000000 -> 0 | N48: =MAX(0,MIN(24,60)-MAX(12,$J48)) -> 0 | O48: =$E48*1000*8760*$K48*$G48*N48/12/10000000 -> 0 | P48: =MAX(0,MIN(36,60)-MAX(24,$J48)) -> 8 | Q48: =$E48*1000*8760*$K48*$G48*P48/12/10000000 -> 144.22464 | R48: =MAX(0,MIN(48,60)-MAX(36,$J48)) -> 12 | S48: =$E48*1000*8760*$K48*$G48*R48/12/10000000 -> 216.33696 | T48: =MAX(0,MIN(60,60)-MAX(48,$J48)) -> 12 | U48: =$E48*1000*8760*$K48*$G48*T48/12/10000000 -> 216.33696
A49: UCA | B49: WSH | C49: Juniper Green Sigma Six Pvt Ltd | D49: SJVN | E49: 180 | F49: 3.41 | G49: =IF(D49="Merchant",Assumptions!$E$49,IF(AND(A49="Operational",OR(B49="WSH",B49="FDRE")),Assumptions!$B$37,F49)) -> 3.41 | H49: 45469 | I49: =EDATE(H49,ROUND(Assumptions!$E$44,0)) -> 46930 | J49: =MAX(0,(YEAR(I49)-YEAR(Assumptions!$B$74))*12+(MONTH(I49)-MONTH(Assumptions!$B$74))) -> 26 | K49: =IF(B49="Solar",Assumptions!$B$34,IF(B49="Wind",Assumptions!$B$35,IF(B49="WSH",Assumptions!$E$40,Assumptions!$E$41))) -> 0.4 | L49: =MAX(0,MIN(12,60)-MAX(0,$J49)) -> 0 | M49: =$E49*1000*8760*$K49*$G49*L49/12/10000000 -> 0 | N49: =MAX(0,MIN(24,60)-MAX(12,$J49)) -> 0 | O49: =$E49*1000*8760*$K49*$G49*N49/12/10000000 -> 0 | P49: =MAX(0,MIN(36,60)-MAX(24,$J49)) -> 10 | Q49: =$E49*1000*8760*$K49*$G49*P49/12/10000000 -> 179.2296 | R49: =MAX(0,MIN(48,60)-MAX(36,$J49)) -> 12 | S49: =$E49*1000*8760*$K49*$G49*R49/12/10000000 -> 215.07552 | T49: =MAX(0,MIN(60,60)-MAX(48,$J49)) -> 12 | U49: =$E49*1000*8760*$K49*$G49*T49/12/10000000 -> 215.07552
A50: UCA | B50: FDRE | C50: Juniper Green Beam Alpha Pvt Ltd | D50: NHPC | E50: 400 | F50: 4.56 | G50: =IF(D50="Merchant",Assumptions!$E$49,IF(AND(A50="Operational",OR(B50="WSH",B50="FDRE")),Assumptions!$B$37,F50)) -> 4.56 | H50: 45687 | I50: =EDATE(H50,ROUND(Assumptions!$E$45,0)) -> 47329 | J50: =MAX(0,(YEAR(I50)-YEAR(Assumptions!$B$74))*12+(MONTH(I50)-MONTH(Assumptions!$B$74))) -> 39 | K50: =IF(B50="Solar",Assumptions!$B$34,IF(B50="Wind",Assumptions!$B$35,IF(B50="WSH",Assumptions!$E$40,Assumptions!$E$41))) -> 0.5 | L50: =MAX(0,MIN(12,60)-MAX(0,$J50)) -> 0 | M50: =$E50*1000*8760*$K50*$G50*L50/12/10000000 -> 0 | N50: =MAX(0,MIN(24,60)-MAX(12,$J50)) -> 0 | O50: =$E50*1000*8760*$K50*$G50*N50/12/10000000 -> 0 | P50: =MAX(0,MIN(36,60)-MAX(24,$J50)) -> 0 | Q50: =$E50*1000*8760*$K50*$G50*P50/12/10000000 -> 0 | R50: =MAX(0,MIN(48,60)-MAX(36,$J50)) -> 9 | S50: =$E50*1000*8760*$K50*$G50*R50/12/10000000 -> 599.184 | T50: =MAX(0,MIN(60,60)-MAX(48,$J50)) -> 12 | U50: =$E50*1000*8760*$K50*$G50*T50/12/10000000 -> 798.912
A51: UCA | B51: FDRE | C51: Juniper Green Power Omega Pvt Ltd | D51: NHPC | E51: 500 | F51: 4.48 | G51: =IF(D51="Merchant",Assumptions!$E$49,IF(AND(A51="Operational",OR(B51="WSH",B51="FDRE")),Assumptions!$B$37,F51)) -> 4.48 | H51: 45687 | I51: =EDATE(H51,ROUND(Assumptions!$E$45,0)) -> 47329 | J51: =MAX(0,(YEAR(I51)-YEAR(Assumptions!$B$74))*12+(MONTH(I51)-MONTH(Assumptions!$B$74))) -> 39 | K51: =IF(B51="Solar",Assumptions!$B$34,IF(B51="Wind",Assumptions!$B$35,IF(B51="WSH",Assumptions!$E$40,Assumptions!$E$41))) -> 0.5 | L51: =MAX(0,MIN(12,60)-MAX(0,$J51)) -> 0 | M51: =$E51*1000*8760*$K51*$G51*L51/12/10000000 -> 0 | N51: =MAX(0,MIN(24,60)-MAX(12,$J51)) -> 0 | O51: =$E51*1000*8760*$K51*$G51*N51/12/10000000 -> 0 | P51: =MAX(0,MIN(36,60)-MAX(24,$J51)) -> 0 | Q51: =$E51*1000*8760*$K51*$G51*P51/12/10000000 -> 0 | R51: =MAX(0,MIN(48,60)-MAX(36,$J51)) -> 9 | S51: =$E51*1000*8760*$K51*$G51*R51/12/10000000 -> 735.84 | T51: =MAX(0,MIN(60,60)-MAX(48,$J51)) -> 12 | U51: =$E51*1000*8760*$K51*$G51*T51/12/10000000 -> 981.12
A52: UCA | B52: FDRE | C52: Juniper Green Bess One Pvt Ltd | D52: SJVN | E52: 360 | F52: 4.25 | G52: =IF(D52="Merchant",Assumptions!$E$49,IF(AND(A52="Operational",OR(B52="WSH",B52="FDRE")),Assumptions!$B$37,F52)) -> 4.25 | H52: 45691 | I52: =EDATE(H52,ROUND(Assumptions!$E$45,0)) -> 47333 | J52: =MAX(0,(YEAR(I52)-YEAR(Assumptions!$B$74))*12+(MONTH(I52)-MONTH(Assumptions!$B$74))) -> 40 | K52: =IF(B52="Solar",Assumptions!$B$34,IF(B52="Wind",Assumptions!$B$35,IF(B52="WSH",Assumptions!$E$40,Assumptions!$E$41))) -> 0.5 | L52: =MAX(0,MIN(12,60)-MAX(0,$J52)) -> 0 | M52: =$E52*1000*8760*$K52*$G52*L52/12/10000000 -> 0 | N52: =MAX(0,MIN(24,60)-MAX(12,$J52)) -> 0 | O52: =$E52*1000*8760*$K52*$G52*N52/12/10000000 -> 0 | P52: =MAX(0,MIN(36,60)-MAX(24,$J52)) -> 0 | Q52: =$E52*1000*8760*$K52*$G52*P52/12/10000000 -> 0 | R52: =MAX(0,MIN(48,60)-MAX(36,$J52)) -> 8 | S52: =$E52*1000*8760*$K52*$G52*R52/12/10000000 -> 446.76 | T52: =MAX(0,MIN(60,60)-MAX(48,$J52)) -> 12 | U52: =$E52*1000*8760*$K52*$G52*T52/12/10000000 -> 670.14
C54: TOTAL REVENUE (Rs crore) | M54: =SUM(M5:M52) -> 2437.5935 | O54: =SUM(O5:O52) -> 5937.1108 | Q54: =SUM(Q5:Q52) -> 8038.7308 | S54: =SUM(S5:S52) -> 10353.315 | U54: =SUM(U5:U52) -> 11021.703
C56: Operational AC MW at FY-end (cumulative COD'd capacity) | M56: =SUMIF($J$5:$J$52,"<12",$E$5:$E$52) -> 3328.2 | O56: =SUMIF($J$5:$J$52,"<24",$E$5:$E$52) -> 5030.2 | Q56: =SUMIF($J$5:$J$52,"<36",$E$5:$E$52) -> 6650.2 | S56: =SUMIF($J$5:$J$52,"<48",$E$5:$E$52) -> 7910.2 | U56: =SUMIF($J$5:$J$52,"<60",$E$5:$E$52) -> 7910.2

Sheet Capex Model
A1: CAPEX MODEL — SPV LEVEL PHASING (UCC & UCA only; Operational projects require no further capex)
A2: Cash capex spread evenly over construction window (Start->COD). Capitalisation to Gross Block occurs as a lump sum in the FY that COD falls in (CWIP->PPE transfer convention). Rs crore.
A4: Category | B4: Tech | C4: Entity | D4: Planned AC MW | E4: Rs cr/MW | F4: Total Project Cost | G4: Start Date | H4: COD | I4: Start Mth Idx | J4: COD Mth Idx | K4: Constr. Months | L4: FY27 Capex (cash) | M4: FY28 Capex (cash) | N4: FY29 Capex (cash) | O4: FY30 Capex (cash) | P4: FY31 Capex (cash) | Q4: Capitalised in FY | R4: Cash Spend Base (Rs cr)
A5: UCC | B5: Solar | C5: Juniper Green Beta Pvt Ltd | D5: 20 | E5: =Assumptions!$B$52 -> 8.6126981 | F5: =D5*E5 -> 172.25396 | G5: 45292 | H5: ='Revenue Model'!I23 -> 46192 | I5: =MAX(0,(YEAR(G5)-YEAR(Assumptions!$B$74))*12+(MONTH(G5)-MONTH(Assumptions!$B$74))) -> 0 | J5: ='Revenue Model'!J23 -> 2 | K5: =MAX(1,MAX($J5,$I5+1)-$I5) -> 2 | L5: =MAX(0,MIN(12,MAX($J5,$I5+1))-MAX(0,$I5))/$K5*$R5 -> 62.56847 | M5: =MAX(0,MIN(24,MAX($J5,$I5+1))-MAX(12,$I5))/$K5*$R5 -> 0 | N5: =MAX(0,MIN(36,MAX($J5,$I5+1))-MAX(24,$I5))/$K5*$R5 -> 0 | O5: =MAX(0,MIN(48,MAX($J5,$I5+1))-MAX(36,$I5))/$K5*$R5 -> 0 | P5: =MAX(0,MIN(60,MAX($J5,$I5+1))-MAX(48,$I5))/$K5*$R5 -> 0 | Q5: =IF(AND($J5>=0,$J5<12),"FY27",IF($J5<24,"FY28",IF($J5<36,"FY29",IF($J5<48,"FY30",IF($J5<60,"FY31","Beyond"))))) -> FY27 | R5: =IF(A5="UCC",F5*Assumptions!$B$54,F5) -> 62.56847
A6: UCC | B6: Wind | C6: Juniper Green Kite Pvt Ltd | D6: 70 | E6: =Assumptions!$B$52 -> 8.6126981 | F6: =D6*E6 -> 602.88886 | G6: 45463 | H6: ='Revenue Model'!I24 -> 46192 | I6: =MAX(0,(YEAR(G6)-YEAR(Assumptions!$B$74))*12+(MONTH(G6)-MONTH(Assumptions!$B$74))) -> 0 | J6: ='Revenue Model'!J24 -> 2 | K6: =MAX(1,MAX($J6,$I6+1)-$I6) -> 2 | L6: =MAX(0,MIN(12,MAX($J6,$I6+1))-MAX(0,$I6))/$K6*$R6 -> 218.98965 | M6: =MAX(0,MIN(24,MAX($J6,$I6+1))-MAX(12,$I6))/$K6*$R6 -> 0 | N6: =MAX(0,MIN(36,MAX($J6,$I6+1))-MAX(24,$I6))/$K6*$R6 -> 0 | O6: =MAX(0,MIN(48,MAX($J6,$I6+1))-MAX(36,$I6))/$K6*$R6 -> 0 | P6: =MAX(0,MIN(60,MAX($J6,$I6+1))-MAX(48,$I6))/$K6*$R6 -> 0 | Q6: =IF(AND($J6>=0,$J6<12),"FY27",IF($J6<24,"FY28",IF($J6<36,"FY29",IF($J6<48,"FY30",IF($J6<60,"FY31","Beyond"))))) -> FY27 | R6: =IF(A6="UCC",F6*Assumptions!$B$54,F6) -> 218.98965
A7: UCC | B7: Wind | C7: Juniper Green Bess Two Pvt Ltd | D7: 100 | E7: =Assumptions!$B$52 -> 8.6126981 | F7: =D7*E7 -> 861.26981 | G7: 45856 | H7: ='Revenue Model'!I25 -> 46585 | I7: =MAX(0,(YEAR(G7)-YEAR(Assumptions!$B$74))*12+(MONTH(G7)-MONTH(Assumptions!$B$74))) -> 0 | J7: ='Revenue Model'!J25 -> 15 | K7: =MAX(1,MAX($J7,$I7+1)-$I7) -> 15 | L7: =MAX(0,MIN(12,MAX($J7,$I7+1))-MAX(0,$I7))/$K7*$R7 -> 250.27388 | M7: =MAX(0,MIN(24,MAX($J7,$I7+1))-MAX(12,$I7))/$K7*$R7 -> 62.56847 | N7: =MAX(0,MIN(36,MAX($J7,$I7+1))-MAX(24,$I7))/$K7*$R7 -> 0 | O7: =MAX(0,MIN(48,MAX($J7,$I7+1))-MAX(36,$I7))/$K7*$R7 -> 0 | P7: =MAX(0,MIN(60,MAX($J7,$I7+1))-MAX(48,$I7))/$K7*$R7 -> 0 | Q7: =IF(AND($J7>=0,$J7<12),"FY27",IF($J7<24,"FY28",IF($J7<36,"FY29",IF($J7<48,"FY30",IF($J7<60,"FY31","Beyond"))))) -> FY28 | R7: =IF(A7="UCC",F7*Assumptions!$B$54,F7) -> 312.84235
A8: UCC | B8: Wind | C8: Juniper Green Bess Delta Pvt Ltd | D8: 50 | E8: =Assumptions!$B$52 -> 8.6126981 | F8: =D8*E8 -> 430.6349 | G8: 45852 | H8: ='Revenue Model'!I26 -> 46697 | I8: =MAX(0,(YEAR(G8)-YEAR(Assumptions!$B$74))*12+(MONTH(G8)-MONTH(Assumptions!$B$74))) -> 0 | J8: ='Revenue Model'!J26 -> 19 | K8: =MAX(1,MAX($J8,$I8+1)-$I8) -> 19 | L8: =MAX(0,MIN(12,MAX($J8,$I8+1))-MAX(0,$I8))/$K8*$R8 -> 98.792322 | M8: =MAX(0,MIN(24,MAX($J8,$I8+1))-MAX(12,$I8))/$K8*$R8 -> 57.628854 | N8: =MAX(0,MIN(36,MAX($J8,$I8+1))-MAX(24,$I8))/$K8*$R8 -> 0 | O8: =MAX(0,MIN(48,MAX($J8,$I8+1))-MAX(36,$I8))/$K8*$R8 -> 0 | P8: =MAX(0,MIN(60,MAX($J8,$I8+1))-MAX(48,$I8))/$K8*$R8 -> 0 | Q8: =IF(AND($J8>=0,$J8<12),"FY27",IF($J8<24,"FY28",IF($J8<36,"FY29",IF($J8<48,"FY30",IF($J8<60,"FY31","Beyond"))))) -> FY28 | R8: =IF(A8="UCC",F8*Assumptions!$B$54,F8) -> 156.42118
A9: UCC | B9: WSH | C9: Juniper Green Beam Eight Pvt Ltd | D9: 75 | E9: =Assumptions!$B$52 -> 8.6126981 | F9: =D9*E9 -> 645.95235 | G9: 45380 | H9: ='Revenue Model'!I27 -> 46134 | I9: =MAX(0,(YEAR(G9)-YEAR(Assumptions!$B$74))*12+(MONTH(G9)-MONTH(Assumptions!$B$74))) -> 0 | J9: ='Revenue Model'!J27 -> 0 | K9: =MAX(1,MAX($J9,$I9+1)-$I9) -> 1 | L9: =MAX(0,MIN(12,MAX($J9,$I9+1))-MAX(0,$I9))/$K9*$R9 -> 234.63176 | M9: =MAX(0,MIN(24,MAX($J9,$I9+1))-MAX(12,$I9))/$K9*$R9 -> 0 | N9: =MAX(0,MIN(36,MAX($J9,$I9+1))-MAX(24,$I9))/$K9*$R9 -> 0 | O9: =MAX(0,MIN(48,MAX($J9,$I9+1))-MAX(36,$I9))/$K9*$R9 -> 0 | P9: =MAX(0,MIN(60,MAX($J9,$I9+1))-MAX(48,$I9))/$K9*$R9 -> 0 | Q9: =IF(AND($J9>=0,$J9<12),"FY27",IF($J9<24,"FY28",IF($J9<36,"FY29",IF($J9<48,"FY30",IF($J9<60,"FY31","Beyond"))))) -> FY27 | R9: =IF(A9="UCC",F9*Assumptions!$B$54,F9) -> 234.63176
A10: UCC | B10: WSH | C10: Juniper Green Energy Ltd | D10: 50 | E10: =Assumptions!$B$52 -> 8.6126981 | F10: =D10*E10 -> 430.6349 | G10: 45477 | H10: ='Revenue Model'!I28 -> 46206 | I10: =MAX(0,(YEAR(G10)-YEAR(Assumptions!$B$74))*12+(MONTH(G10)-MONTH(Assumptions!$B$74))) -> 0 | J10: ='Revenue Model'!J28 -> 3 | K10: =MAX(1,MAX($J10,$I10+1)-$I10) -> 3 | L10: =MAX(0,MIN(12,MAX($J10,$I10+1))-MAX(0,$I10))/$K10*$R10 -> 156.42118 | M10: =MAX(0,MIN(24,MAX($J10,$I10+1))-MAX(12,$I10))/$K10*$R10 -> 0 | N10: =MAX(0,MIN(36,MAX($J10,$I10+1))-MAX(24,$I10))/$K10*$R10 -> 0 | O10: =MAX(0,MIN(48,MAX($J10,$I10+1))-MAX(36,$I10))/$K10*$R10 -> 0 | P10: =MAX(0,MIN(60,MAX($J10,$I10+1))-MAX(48,$I10))/$K10*$R10 -> 0 | Q10: =IF(AND($J10>=0,$J10<12),"FY27",IF($J10<24,"FY28",IF($J10<36,"FY29",IF($J10<48,"FY30",IF($J10<60,"FY31","Beyond"))))) -> FY27 | R10: =IF(A10="UCC",F10*Assumptions!$B$54,F10) -> 156.42118
A11: UCC | B11: WSH | C11: Juniper Green Beta Pvt Ltd | D11: 185 | E11: =Assumptions!$B$52 -> 8.6126981 | F11: =D11*E11 -> 1593.3491 | G11: 45463 | H11: ='Revenue Model'!I29 -> 46396 | I11: =MAX(0,(YEAR(G11)-YEAR(Assumptions!$B$74))*12+(MONTH(G11)-MONTH(Assumptions!$B$74))) -> 0 | J11: ='Revenue Model'!J29 -> 9 | K11: =MAX(1,MAX($J11,$I11+1)-$I11) -> 9 | L11: =MAX(0,MIN(12,MAX($J11,$I11+1))-MAX(0,$I11))/$K11*$R11 -> 578.75835 | M11: =MAX(0,MIN(24,MAX($J11,$I11+1))-MAX(12,$I11))/$K11*$R11 -> 0 | N11: =MAX(0,MIN(36,MAX($J11,$I11+1))-MAX(24,$I11))/$K11*$R11 -> 0 | O11: =MAX(0,MIN(48,MAX($J11,$I11+1))-MAX(36,$I11))/$K11*$R11 -> 0 | P11: =MAX(0,MIN(60,MAX($J11,$I11+1))-MAX(48,$I11))/$K11*$R11 -> 0 | Q11: =IF(AND($J11>=0,$J11<12),"FY27",IF($J11<24,"FY28",IF($J11<36,"FY29",IF($J11<48,"FY30",IF($J11<60,"FY31","Beyond"))))) -> FY27 | R11: =IF(A11="UCC",F11*Assumptions!$B$54,F11) -> 578.75835
A12: UCC | B12: WSH | C12: Juniper Green Beta Pvt Ltd | D12: 238.1 | E12: =Assumptions!$B$52 -> 8.6126981 | F12: =D12*E12 -> 2050.6834 | G12: 45472 | H12: ='Revenue Model'!I30 -> 46201 | I12: =MAX(0,(YEAR(G12)-YEAR(Assumptions!$B$74))*12+(MONTH(G12)-MONTH(Assumptions!$B$74))) -> 0 | J12: ='Revenue Model'!J30 -> 2 | K12: =MAX(1,MAX($J12,$I12+1)-$I12) -> 2 | L12: =MAX(0,MIN(12,MAX($J12,$I12+1))-MAX(0,$I12))/$K12*$R12 -> 744.87764 | M12: =MAX(0,MIN(24,MAX($J12,$I12+1))-MAX(12,$I12))/$K12*$R12 -> 0 | N12: =MAX(0,MIN(36,MAX($J12,$I12+1))-MAX(24,$I12))/$K12*$R12 -> 0 | O12: =MAX(0,MIN(48,MAX($J12,$I12+1))-MAX(36,$I12))/$K12*$R12 -> 0 | P12: =MAX(0,MIN(60,MAX($J12,$I12+1))-MAX(48,$I12))/$K12*$R12 -> 0 | Q12: =IF(AND($J12>=0,$J12<12),"FY27",IF($J12<24,"FY28",IF($J12<36,"FY29",IF($J12<48,"FY30",IF($J12<60,"FY31","Beyond"))))) -> FY27 | R12: =IF(A12="UCC",F12*Assumptions!$B$54,F12) -> 744.87764
A13: UCC | B13: WSH | C13: Juniper Green Power Five Pvt Ltd + Juniper Green ETA Five Pvt Ltd | D13: 127.8 | E13: =Assumptions!$B$52 -> 8.6126981 | F13: =D13*E13 -> 1100.7028 | G13: 45614 | H13: ='Revenue Model'!I31 -> 46343 | I13: =MAX(0,(YEAR(G13)-YEAR(Assumptions!$B$74))*12+(MONTH(G13)-MONTH(Assumptions!$B$74))) -> 0 | J13: ='Revenue Model'!J31 -> 7 | K13: =MAX(1,MAX($J13,$I13+1)-$I13) -> 7 | L13: =MAX(0,MIN(12,MAX($J13,$I13+1))-MAX(0,$I13))/$K13*$R13 -> 399.81253 | M13: =MAX(0,MIN(24,MAX($J13,$I13+1))-MAX(12,$I13))/$K13*$R13 -> 0 | N13: =MAX(0,MIN(36,MAX($J13,$I13+1))-MAX(24,$I13))/$K13*$R13 -> 0 | O13: =MAX(0,MIN(48,MAX($J13,$I13+1))-MAX(36,$I13))/$K13*$R13 -> 0 | P13: =MAX(0,MIN(60,MAX($J13,$I13+1))-MAX(48,$I13))/$K13*$R13 -> 0 | Q13: =IF(AND($J13>=0,$J13<12),"FY27",IF($J13<24,"FY28",IF($J13<36,"FY29",IF($J13<48,"FY30",IF($J13<60,"FY31","Beyond"))))) -> FY27 | R13: =IF(A13="UCC",F13*Assumptions!$B$54,F13) -> 399.81253
A14: UCC | B14: WSH | C14: Juniper Green Spark Ten Pvt Ltd | D14: 25 | E14: =Assumptions!$B$52 -> 8.6126981 | F14: =D14*E14 -> 215.31745 | G14: 45614 | H14: ='Revenue Model'!I32 -> 46343 | I14: =MAX(0,(YEAR(G14)-YEAR(Assumptions!$B$74))*12+(MONTH(G14)-MONTH(Assumptions!$B$74))) -> 0 | J14: ='Revenue Model'!J32 -> 7 | K14: =MAX(1,MAX($J14,$I14+1)-$I14) -> 7 | L14: =MAX(0,MIN(12,MAX($J14,$I14+1))-MAX(0,$I14))/$K14*$R14 -> 78.210588 | M14: =MAX(0,MIN(24,MAX($J14,$I14+1))-MAX(12,$I14))/$K14*$R14 -> 0 | N14: =MAX(0,MIN(36,MAX($J14,$I14+1))-MAX(24,$I14))/$K14*$R14 -> 0 | O14: =MAX(0,MIN(48,MAX($J14,$I14+1))-MAX(36,$I14))/$K14*$R14 -> 0 | P14: =MAX(0,MIN(60,MAX($J14,$I14+1))-MAX(48,$I14))/$K14*$R14 -> 0 | Q14: =IF(AND($J14>=0,$J14<12),"FY27",IF($J14<24,"FY28",IF($J14<36,"FY29",IF($J14<48,"FY30",IF($J14<60,"FY31","Beyond"))))) -> FY27 | R14: =IF(A14="UCC",F14*Assumptions!$B$54,F14) -> 78.210588
A15: UCC | B15: WSH | C15: Juniper Green Spark Four Pvt Ltd | D15: 90 | E15: =Assumptions!$B$52 -> 8.6126981 | F15: =D15*E15 -> 775.14283 | G15: 45575 | H15: ='Revenue Model'!I33 -> 46304 | I15: =MAX(0,(YEAR(G15)-YEAR(Assumptions!$B$74))*12+(MONTH(G15)-MONTH(Assumptions!$B$74))) -> 0 | J15: ='Revenue Model'!J33 -> 6 | K15: =MAX(1,MAX($J15,$I15+1)-$I15) -> 6 | L15: =MAX(0,MIN(12,MAX($J15,$I15+1))-MAX(0,$I15))/$K15*$R15 -> 281.55812 | M15: =MAX(0,MIN(24,MAX($J15,$I15+1))-MAX(12,$I15))/$K15*$R15 -> 0 | N15: =MAX(0,MIN(36,MAX($J15,$I15+1))-MAX(24,$I15))/$K15*$R15 -> 0 | O15: =MAX(0,MIN(48,MAX($J15,$I15+1))-MAX(36,$I15))/$K15*$R15 -> 0 | P15: =MAX(0,MIN(60,MAX($J15,$I15+1))-MAX(48,$I15))/$K15*$R15 -> 0 | Q15: =IF(AND($J15>=0,$J15<12),"FY27",IF($J15<24,"FY28",IF($J15<36,"FY29",IF($J15<48,"FY30",IF($J15<60,"FY31","Beyond"))))) -> FY27 | R15: =IF(A15="UCC",F15*Assumptions!$B$54,F15) -> 281.55812
A16: UCC | B16: FDRE | C16: Juniper Green Stellar Pvt Ltd | D16: 209.7 | E16: =Assumptions!$B$52 -> 8.6126981 | F16: =D16*E16 -> 1806.0828 | G16: 45412 | H16: ='Revenue Model'!I34 -> 46356 | I16: =MAX(0,(YEAR(G16)-YEAR(Assumptions!$B$74))*12+(MONTH(G16)-MONTH(Assumptions!$B$74))) -> 0 | J16: ='Revenue Model'!J34 -> 7 | K16: =MAX(1,MAX($J16,$I16+1)-$I16) -> 7 | L16: =MAX(0,MIN(12,MAX($J16,$I16+1))-MAX(0,$I16))/$K16*$R16 -> 656.03041 | M16: =MAX(0,MIN(24,MAX($J16,$I16+1))-MAX(12,$I16))/$K16*$R16 -> 0 | N16: =MAX(0,MIN(36,MAX($J16,$I16+1))-MAX(24,$I16))/$K16*$R16 -> 0 | O16: =MAX(0,MIN(48,MAX($J16,$I16+1))-MAX(36,$I16))/$K16*$R16 -> 0 | P16: =MAX(0,MIN(60,MAX($J16,$I16+1))-MAX(48,$I16))/$K16*$R16 -> 0 | Q16: =IF(AND($J16>=0,$J16<12),"FY27",IF($J16<24,"FY28",IF($J16<36,"FY29",IF($J16<48,"FY30",IF($J16<60,"FY31","Beyond"))))) -> FY27 | R16: =IF(A16="UCC",F16*Assumptions!$B$54,F16) -> 656.03041
... A22: UCC | B22: FDRE | C22: Juniper Green Sigma Eight Pvt Ltd | D22: 140 | E22: =Assumptions!$B$52 -> 8.6126981 | F22: =D22*E22 -> 1205.7777 | G22: 45923 | H22: ='Revenue Model'!I40 -> 46676 | I22: =MAX(0,(YEAR(G22)-YEAR(Assumptions!$B$74))*12+(MONTH(G22)-MONTH(Assumptions!$B$74))) -> 0 | J22: ='Revenue Model'!J40 -> 18 | K22: =MAX(1,MAX($J22,$I22+1)-$I22) -> 18 | L22: =MAX(0,MIN(12,MAX($J22,$I22+1))-MAX(0,$I22))/$K22*$R22 -> 291.9862 | M22: =MAX(0,MIN(24,MAX($J22,$I22+1))-MAX(12,$I22))/$K22*$R22 -> 145.9931 | N22: =MAX(0,MIN(36,MAX($J22,$I22+1))-MAX(24,$I22))/$K22*$R22 -> 0 | O22: =MAX(0,MIN(48,MAX($J22,$I22+1))-MAX(36,$I22))/$K22*$R22 -> 0 | P22: =MAX(0,MIN(60,MAX($J22,$I22+1))-MAX(48,$I22))/$K22*$R22 -> 0 | Q22: =IF(AND($J22>=0,$J22<12),"FY27",IF($J22<24,"FY28",IF($J22<36,"FY29",IF($J22<48,"FY30",IF($J22<60,"FY31","Beyond"))))) -> FY28 | R22: =IF(A22="UCC",F22*Assumptions!$B$54,F22) -> 437.97929
A23: UCA | B23: WSH | C23: Juniper Green Beam Six Pvt Ltd | D23: 180 | E23: =Assumptions!$B$53 -> 5.8797426 | F23: =D23*E23 -> 1058.3537 | G23: 45580 | H23: ='Revenue Model'!I41 -> 47041 | I23: =MAX(0,(YEAR(G23)-YEAR(Assumptions!$B$74))*12+(MONTH(G23)-MONTH(Assumptions!$B$74))) -> 0 | J23: ='Revenue Model'!J41 -> 30 | K23: =MAX(1,MAX($J23,$I23+1)-$I23) -> 30 | L23: =MAX(0,MIN(12,MAX($J23,$I23+1))-MAX(0,$I23))/$K23*$R23 -> 423.34147 | M23: =MAX(0,MIN(24,MAX($J23,$I23+1))-MAX(12,$I23))/$K23*$R23 -> 423.34147 | N23: =MAX(0,MIN(36,MAX($J23,$I23+1))-MAX(24,$I23))/$K23*$R23 -> 211.67073 | O23: =MAX(0,MIN(48,MAX($J23,$I23+1))-MAX(36,$I23))/$K23*$R23 -> 0 | P23: =MAX(0,MIN(60,MAX($J23,$I23+1))-MAX(48,$I23))/$K23*$R23 -> 0 | Q23: =IF(AND($J23>=0,$J23<12),"FY27",IF($J23<24,"FY28",IF($J23<36,"FY29",IF($J23<48,"FY30",IF($J23<60,"FY31","Beyond"))))) -> FY29 | R23: =IF(A23="UCC",F23*Assumptions!$B$54,F23) -> 1058.3537
A24: UCA | B24: WSH | C24: Juniper Green Light Four Pvt Ltd | D24: 180 | E24: =Assumptions!$B$53 -> 5.8797426 | F24: =D24*E24 -> 1058.3537 | G24: 45357 | H24: ='Revenue Model'!I42 -> 46818 | I24: =MAX(0,(YEAR(G24)-YEAR(Assumptions!$B$74))*12+(MONTH(G24)-MONTH(Assumptions!$B$74))) -> 0 | J24: ='Revenue Model'!J42 -> 23 | K24: =MAX(1,MAX($J24,$I24+1)-$I24) -> 23 | L24: =MAX(0,MIN(12,MAX($J24,$I24+1))-MAX(0,$I24))/$K24*$R24 -> 552.18452 | M24: =MAX(0,MIN(24,MAX($J24,$I24+1))-MAX(12,$I24))/$K24*$R24 -> 506.16914 | N24: =MAX(0,MIN(36,MAX($J24,$I24+1))-MAX(24,$I24))/$K24*$R24 -> 0 | O24: =MAX(0,MIN(48,MAX($J24,$I24+1))-MAX(36,$I24))/$K24*$R24 -> 0 | P24: =MAX(0,MIN(60,MAX($J24,$I24+1))-MAX(48,$I24))/$K24*$R24 -> 0 | Q24: =IF(AND($J24>=0,$J24<12),"FY27",IF($J24<24,"FY28",IF($J24<36,"FY29",IF($J24<48,"FY30",IF($J24<60,"FY31","Beyond"))))) -> FY28 | R24: =IF(A24="UCC",F24*Assumptions!$B$54,F24) -> 1058.3537
A25: UCA | B25: WSH | C25: Juniper Green Alpha Three Pvt Ltd | D25: 360 | E25: =Assumptions!$B$53 -> 5.8797426 | F25: =D25*E25 -> 2116.7073 | G25: 45630 | H25: ='Revenue Model'!I43 -> 47091 | I25: =MAX(0,(YEAR(G25)-YEAR(Assumptions!$B$74))*12+(MONTH(G25)-MONTH(Assumptions!$B$74))) -> 0 | J25: ='Revenue Model'!J43 -> 32 | K25: =MAX(1,MAX($J25,$I25+1)-$I25) -> 32 | L25: =MAX(0,MIN(12,MAX($J25,$I25+1))-MAX(0,$I25))/$K25*$R25 -> 793.76525 | M25: =MAX(0,MIN(24,MAX($J25,$I25+1))-MAX(12,$I25))/$K25*$R25 -> 793.76525 | N25: =MAX(0,MIN(36,MAX($J25,$I25+1))-MAX(24,$I25))/$K25*$R25 -> 529.17683 | O25: =MAX(0,MIN(48,MAX($J25,$I25+1))-MAX(36,$I25))/$K25*$R25 -> 0 | P25: =MAX(0,MIN(60,MAX($J25,$I25+1))-MAX(48,$I25))/$K25*$R25 -> 0 | Q25: =IF(AND($J25>=0,$J25<12),"FY27",IF($J25<24,"FY28",IF($J25<36,"FY29",IF($J25<48,"FY30",IF($J25<60,"FY31","Beyond"))))) -> FY29 | R25: =IF(A25="UCC",F25*Assumptions!$B$54,F25) -> 2116.7073
A26: UCA | B26: WSH | C26: Juniper Green Energy Ltd | D26: 360 | E26: =Assumptions!$B$53 -> 5.8797426 | F26: =D26*E26 -> 2116.7073 | G26: 45405 | H26: ='Revenue Model'!I44 -> 46866 | I26: =MAX(0,(YEAR(G26)-YEAR(Assumptions!$B$74))*12+(MONTH(G26)-MONTH(Assumptions!$B$74))) -> 0 | J26: ='Revenue Model'!J44 -> 24 | K26: =MAX(1,MAX($J26,$I26+1)-$I26) -> 24 | L26: =MAX(0,MIN(12,MAX($J26,$I26+1))-MAX(0,$I26))/$K26*$R26 -> 1058.3537 | M26: =MAX(0,MIN(24,MAX($J26,$I26+1))-MAX(12,$I26))/$K26*$R26 -> 1058.3537 | N26: =MAX(0,MIN(36,MAX($J26,$I26+1))-MAX(24,$I26))/$K26*$R26 -> 0 | O26: =MAX(0,MIN(48,MAX($J26,$I26+1))-MAX(36,$I26))/$K26*$R26 -> 0 | P26: =MAX(0,MIN(60,MAX($J26,$I26+1))-MAX(48,$I26))/$K26*$R26 -> 0 | Q26: =IF(AND($J26>=0,$J26<12),"FY27",IF($J26<24,"FY28",IF($J26<36,"FY29",IF($J26<48,"FY30",IF($J26<60,"FY31","Beyond"))))) -> FY29 | R26: =IF(A26="UCC",F26*Assumptions!$B$54,F26) -> 2116.7073
A27: UCA | B27: WSH | C27: Juniper Green Gem Pvt Ltd | D27: 180 | E27: =Assumptions!$B$53 -> 5.8797426 | F27: =D27*E27 -> 1058.3537 | G27: 45341 | H27: ='Revenue Model'!I45 -> 46802 | I27: =MAX(0,(YEAR(G27)-YEAR(Assumptions!$B$74))*12+(MONTH(G27)-MONTH(Assumptions!$B$74))) -> 0 | J27: ='Revenue Model'!J45 -> 22 | K27: =MAX(1,MAX($J27,$I27+1)-$I27) -> 22 | L27: =MAX(0,MIN(12,MAX($J27,$I27+1))-MAX(0,$I27))/$K27*$R27 -> 577.28382 | M27: =MAX(0,MIN(24,MAX($J27,$I27+1))-MAX(12,$I27))/$K27*$R27 -> 481.06985 | N27: =MAX(0,MIN(36,MAX($J27,$I27+1))-MAX(24,$I27))/$K27*$R27 -> 0 | O27: =MAX(0,MIN(48,MAX($J27,$I27+1))-MAX(36,$I27))/$K27*$R27 -> 0 | P27: =MAX(0,MIN(60,MAX($J27,$I27+1))-MAX(48,$I27))/$K27*$R27 -> 0 | Q27: =IF(AND($J27>=0,$J27<12),"FY27",IF($J27<24,"FY28",IF($J27<36,"FY29",IF($J27<48,"FY30",IF($J27<60,"FY31","Beyond"))))) -> FY28 | R27: =IF(A27="UCC",F27*Assumptions!$B$54,F27) -> 1058.3537
A28: UCA | B28: WSH | C28: Juniper Green India Eight Pvt Ltd | D28: 180 | E28: =Assumptions!$B$53 -> 5.8797426 | F28: =D28*E28 -> 1058.3537 | G28: 45463 | H28: ='Revenue Model'!I46 -> 46924 | I28: =MAX(0,(YEAR(G28)-YEAR(Assumptions!$B$74))*12+(MONTH(G28)-MONTH(Assumptions!$B$74))) -> 0 | J28: ='Revenue Model'!J46 -> 26 | K28: =MAX(1,MAX($J28,$I28+1)-$I28) -> 26 | L28: =MAX(0,MIN(12,MAX($J28,$I28+1))-MAX(0,$I28))/$K28*$R28 -> 488.47092 | M28: =MAX(0,MIN(24,MAX($J28,$I28+1))-MAX(12,$I28))/$K28*$R28 -> 488.47092 | N28: =MAX(0,MIN(36,MAX($J28,$I28+1))-MAX(24,$I28))/$K28*$R28 -> 81.411821 | O28: =MAX(0,MIN(48,MAX($J28,$I28+1))-MAX(36,$I28))/$K28*$R28 -> 0 | P28: =MAX(0,MIN(60,MAX($J28,$I28+1))-MAX(48,$I28))/$K28*$R28 -> 0 | Q28: =IF(AND($J28>=0,$J28<12),"FY27",IF($J28<24,"FY28",IF($J28<36,"FY29",IF($J28<48,"FY30",IF($J28<60,"FY31","Beyond"))))) -> FY29 | R28: =IF(A28="UCC",F28*Assumptions!$B$54,F28) -> 1058.3537
A29: UCA | B29: WSH | C29: Juniper Green Infinite Pvt Ltd | D29: 180 | E29: =Assumptions!$B$53 -> 5.8797426 | F29: =D29*E29 -> 1058.3537 | G29: 45427 | H29: ='Revenue Model'!I47 -> 46888 | I29: =MAX(0,(YEAR(G29)-YEAR(Assumptions!$B$74))*12+(MONTH(G29)-MONTH(Assumptions!$B$74))) -> 0 | J29: ='Revenue Model'!J47 -> 25 | K29: =MAX(1,MAX($J29,$I29+1)-$I29) -> 25 | L29: =MAX(0,MIN(12,MAX($J29,$I29+1))-MAX(0,$I29))/$K29*$R29 -> 508.00976 | M29: =MAX(0,MIN(24,MAX($J29,$I29+1))-MAX(12,$I29))/$K29*$R29 -> 508.00976 | N29: =MAX(0,MIN(36,MAX($J29,$I29+1))-MAX(24,$I29))/$K29*$R29 -> 42.334147 | O29: =MAX(0,MIN(48,MAX($J29,$I29+1))-MAX(36,$I29))/$K29*$R29 -> 0 | P29: =MAX(0,MIN(60,MAX($J29,$I29+1))-MAX(48,$I29))/$K29*$R29 -> 0 | Q29: =IF(AND($J29>=0,$J29<12),"FY27",IF($J29<24,"FY28",IF($J29<36,"FY29",IF($J29<48,"FY30",IF($J29<60,"FY31","Beyond"))))) -> FY29 | R29: =IF(A29="UCC",F29*Assumptions!$B$54,F29) -> 1058.3537
A30: UCA | B30: WSH | C30: Juniper Green India Alpha Pvt Ltd | D30: 180 | E30: =Assumptions!$B$53 -> 5.8797426 | F30: =D30*E30 -> 1058.3537 | G30: 45526 | H30: ='Revenue Model'!I48 -> 46987 | I30: =MAX(0,(YEAR(G30)-YEAR(Assumptions!$B$74))*12+(MONTH(G30)-MONTH(Assumptions!$B$74))) -> 0 | J30: ='Revenue Model'!J48 -> 28 | K30: =MAX(1,MAX($J30,$I30+1)-$I30) -> 28 | L30: =MAX(0,MIN(12,MAX($J30,$I30+1))-MAX(0,$I30))/$K30*$R30 -> 453.58014 | M30: =MAX(0,MIN(24,MAX($J30,$I30+1))-MAX(12,$I30))/$K30*$R30 -> 453.58014 | N30: =MAX(0,MIN(36,MAX($J30,$I30+1))-MAX(24,$I30))/$K30*$R30 -> 151.19338 | O30: =MAX(0,MIN(48,MAX($J30,$I30+1))-MAX(36,$I30))/$K30*$R30 -> 0 | P30: =MAX(0,MIN(60,MAX($J30,$I30+1))-MAX(48,$I30))/$K30*$R30 -> 0 | Q30: =IF(AND($J30>=0,$J30<12),"FY27",IF($J30<24,"FY28",IF($J30<36,"FY29",IF($J30<48,"FY30",IF($J30<60,"FY31","Beyond"))))) -> FY29 | R30: =IF(A30="UCC",F30*Assumptions!$B$54,F30) -> 1058.3537
A31: UCA | B31: WSH | C31: Juniper Green Sigma Six Pvt Ltd | D31: 180 | E31: =Assumptions!$B$53 -> 5.8797426 | F31: =D31*E31 -> 1058.3537 | G31: 45469 | H31: ='Revenue Model'!I49 -> 46930 | I31: =MAX(0,(YEAR(G31)-YEAR(Assumptions!$B$74))*12+(MONTH(G31)-MONTH(Assumptions!$B$74))) -> 0 | J31: ='Revenue Model'!J49 -> 26 | K31: =MAX(1,MAX($J31,$I31+1)-$I31) -> 26 | L31: =MAX(0,MIN(12,MAX($J31,$I31+1))-MAX(0,$I31))/$K31*$R31 -> 488.47092 | M31: =MAX(0,MIN(24,MAX($J31,$I31+1))-MAX(12,$I31))/$K31*$R31 -> 488.47092 | N31: =MAX(0,MIN(36,MAX($J31,$I31+1))-MAX(24,$I31))/$K31*$R31 -> 81.411821 | O31: =MAX(0,MIN(48,MAX($J31,$I31+1))-MAX(36,$I31))/$K31*$R31 -> 0 | P31: =MAX(0,MIN(60,MAX($J31,$I31+1))-MAX(48,$I31))/$K31*$R31 -> 0 | Q31: =IF(AND($J31>=0,$J31<12),"FY27",IF($J31<24,"FY28",IF($J31<36,"FY29",IF($J31<48,"FY30",IF($J31<60,"FY31","Beyond"))))) -> FY29 | R31: =IF(A31="UCC",F31*Assumptions!$B$54,F31) -> 1058.3537
A32: UCA | B32: FDRE | C32: Juniper Green Beam Alpha Pvt Ltd | D32: 400 | E32: =Assumptions!$B$53 -> 5.8797426 | F32: =D32*E32 -> 2351.897 | G32: 45687 | H32: ='Revenue Model'!I50 -> 47329 | I32: =MAX(0,(YEAR(G32)-YEAR(Assumptions!$B$74))*12+(MONTH(G32)-MONTH(Assumptions!$B$74))) -> 0 | J32: ='Revenue Model'!J50 -> 39 | K32: =MAX(1,MAX($J32,$I32+1)-$I32) -> 39 | L32: =MAX(0,MIN(12,MAX($J32,$I32+1))-MAX(0,$I32))/$K32*$R32 -> 723.66063 | M32: =MAX(0,MIN(24,MAX($J32,$I32+1))-MAX(12,$I32))/$K32*$R32 -> 723.66063 | N32: =MAX(0,MIN(36,MAX($J32,$I32+1))-MAX(24,$I32))/$K32*$R32 -> 723.66063 | O32: =MAX(0,MIN(48,MAX($J32,$I32+1))-MAX(36,$I32))/$K32*$R32 -> 180.91516 | P32: =MAX(0,MIN(60,MAX($J32,$I32+1))-MAX(48,$I32))/$K32*$R32 -> 0 | Q32: =IF(AND($J32>=0,$J32<12),"FY27",IF($J32<24,"FY28",IF($J32<36,"FY29",IF($J32<48,"FY30",IF($J32<60,"FY31","Beyond"))))) -> FY30 | R32: =IF(A32="UCC",F32*Assumptions!$B$54,F32) -> 2351.897
A33: UCA | B33: FDRE | C33: Juniper Green Power Omega Pvt Ltd | D33: 500 | E33: =Assumptions!$B$53 -> 5.8797426 | F33: =D33*E33 -> 2939.8713 | G33: 45687 | H33: ='Revenue Model'!I51 -> 47329 | I33: =MAX(0,(YEAR(G33)-YEAR(Assumptions!$B$74))*12+(MONTH(G33)-MONTH(Assumptions!$B$74))) -> 0 | J33: ='Revenue Model'!J51 -> 39 | K33: =MAX(1,MAX($J33,$I33+1)-$I33) -> 39 | L33: =MAX(0,MIN(12,MAX($J33,$I33+1))-MAX(0,$I33))/$K33*$R33 -> 904.57578 | M33: =MAX(0,MIN(24,MAX($J33,$I33+1))-MAX(12,$I33))/$K33*$R33 -> 904.57578 | N33: =MAX(0,MIN(36,MAX($J33,$I33+1))-MAX(24,$I33))/$K33*$R33 -> 904.57578 | O33: =MAX(0,MIN(48,MAX($J33,$I33+1))-MAX(36,$I33))/$K33*$R33 -> 226.14395 | P33: =MAX(0,MIN(60,MAX($J33,$I33+1))-MAX(48,$I33))/$K33*$R33 -> 0 | Q33: =IF(AND($J33>=0,$J33<12),"FY27",IF($J33<24,"FY28",IF($J33<36,"FY29",IF($J33<48,"FY30",IF($J33<60,"FY31","Beyond"))))) -> FY30 | R33: =IF(A33="UCC",F33*Assumptions!$B$54,F33) -> 2939.8713
A34: UCA | B34: FDRE | C34: Juniper Green Bess One Pvt Ltd | D34: 360 | E34: =Assumptions!$B$53 -> 5.8797426 | F34: =D34*E34 -> 2116.7073 | G34: 45691 | H34: ='Revenue Model'!I52 -> 47333 | I34: =MAX(0,(YEAR(G34)-YEAR(Assumptions!$B$74))*12+(MONTH(G34)-MONTH(Assumptions!$B$74))) -> 0 | J34: ='Revenue Model'!J52 -> 40 | K34: =MAX(1,MAX($J34,$I34+1)-$I34) -> 40 | L34: =MAX(0,MIN(12,MAX($J34,$I34+1))-MAX(0,$I34))/$K34*$R34 -> 635.0122 | M34: =MAX(0,MIN(24,MAX($J34,$I34+1))-MAX(12,$I34))/$K34*$R34 -> 635.0122 | N34: =MAX(0,MIN(36,MAX($J34,$I34+1))-MAX(24,$I34))/$K34*$R34 -> 635.0122 | O34: =MAX(0,MIN(48,MAX($J34,$I34+1))-MAX(36,$I34))/$K34*$R34 -> 211.67073 | P34: =MAX(0,MIN(60,MAX($J34,$I34+1))-MAX(48,$I34))/$K34*$R34 -> 0 | Q34: =IF(AND($J34>=0,$J34<12),"FY27",IF($J34<24,"FY28",IF($J34<36,"FY29",IF($J34<48,"FY30",IF($J34<60,"FY31","Beyond"))))) -> FY30 | R34: =IF(A34="UCC",F34*Assumptions!$B$54,F34) -> 2116.7073
C36: TOTAL CASH CAPEX (Rs crore) | L36: =SUM(L5:L34) -> 16094.872 | M36: =SUM(M5:M34) -> 7971.7857 | N36: =SUM(N5:N34) -> 3360.4473 | O36: =SUM(O5:O34) -> 618.72984 | P36: =SUM(P5:P34) -> 0
L37: FY27 | M37: FY28 | N37: FY29 | O37: FY30 | P37: FY31
C38: CAPITALISED TO GROSS BLOCK, BY FY (Rs crore) | L38: =SUMIF($Q$5:$Q$34,"FY27",$F$5:$F$34) -> 13206.711 | M38: =SUMIF($Q$5:$Q$34,"FY28",$F$5:$F$34) -> 13674.948 | N38: =SUMIF($Q$5:$Q$34,"FY29",$F$5:$F$34) -> 9525.183 | O38: =SUMIF($Q$5:$Q$34,"FY30",$F$5:$F$34) -> 7408.4757 | P38: =SUMIF($Q$5:$Q$34,"FY31",$F$5:$F$34) -> 0
C40: of which: Solar-tech capitalised (25yr life) | L40: =SUMIFS($F$5:$F$34,$Q$5:$Q$34,"FY27",$B$5:$B$34,"Solar") -> 172.25396 | M40: =SUMIFS($F$5:$F$34,$Q$5:$Q$34,"FY28",$B$5:$B$34,"Solar") -> 0 | N40: =SUMIFS($F$5:$F$34,$Q$5:$Q$34,"FY29",$B$5:$B$34,"Solar") -> 0 | O40: =SUMIFS($F$5:$F$34,$Q$5:$Q$34,"FY30",$B$5:$B$34,"Solar") -> 0 | P40: =SUMIFS($F$5:$F$34,$Q$5:$Q$34,"FY31",$B$5:$B$34,"Solar") -> 0
C41: of which: Wind/WSH/FDRE capitalised (22yr life) | L41: =SUMIFS($F$5:$F$34,$Q$5:$Q$34,"FY27",$B$5:$B$34,"<>Solar") -> 13034.457 | M41: =SUMIFS($F$5:$F$34,$Q$5:$Q$34,"FY28",$B$5:$B$34,"<>Solar") -> 13674.948 | N41: =SUMIFS($F$5:$F$34,$Q$5:$Q$34,"FY29",$B$5:$B$34,"<>Solar") -> 9525.183 | O41: =SUMIFS($F$5:$F$34,$Q$5:$Q$34,"FY30",$B$5:$B$34,"<>Solar") -> 7408.4757 | P41: =SUMIFS($F$5:$F$34,$Q$5:$Q$34,"FY31",$B$5:$B$34,"<>Solar") -> 0

Sheet Debt Model
A1: DEBT MODEL — CONSOLIDATED (Beginning-of-period interest convention to avoid circularity)
A2: Opening balance = prior FY closing (FY27 opening = FY26 actual per RHP). Interest computed on OPENING balance only (standard non-circular convention). Rs crore.
B4: FY27 | C4: FY28 | D4: FY29 | E4: FY30 | F4: FY31
A5: Opening Debt Balance | B5: 12920.541 | C5: =B10 -> 28051.549 | D5: =C10 -> 33479.504 | E5: =D10 -> 33935.895 | F5: =E10 -> 32168.486
A6: (+) New Debt Draws (75% of Cash Capex) | B6: =Assumptions!$B$22*'Capex Model'!L$36 -> 12875.898 | C6: =Assumptions!$B$22*'Capex Model'!M$36 -> 6377.4285 | D6: =Assumptions!$B$22*'Capex Model'!N$36 -> 2688.3579 | E6: =Assumptions!$B$22*'Capex Model'!O$36 -> 494.98387 | F6: =Assumptions!$B$22*'Capex Model'!P$36 -> 0
A7: (+) Equity Shortfall -> Additional Debt (plug, visible) | B7: =MAX(0,B14-B16) -> 4528.4003 | C7: =MAX(0,C14-C16) -> 920.63018 | D7: =MAX(0,D14-D16) -> 0 | E7: =MAX(0,E14-E16) -> 0 | F7: =MAX(0,F14-F16) -> 0
A8: (-) IPO-funded Debt Repayment (FY27 only, Objects of Issue) | B8: =Assumptions!$B$68 -> 1411.921 | C8: 0 | D8: 0 | E8: 0 | F8: 0
A9: (-) Scheduled Amortisation (Opening Bal / Assumed Tenor) | B9: =B5/Assumptions!$B$26 -> 861.3694 | C9: =C5/Assumptions!$B$26 -> 1870.1032 | D9: =D5/Assumptions!$B$26 -> 2231.9669 | E9: =E5/Assumptions!$B$26 -> 2262.393 | F9: =F5/Assumptions!$B$26 -> 2144.5657
A10: Closing Debt Balance | B10: =B5+B6+B7-B8-B9 -> 28051.549 | C10: =C5+C6+C7-C8-C9 -> 33479.504 | D10: =D5+D6+D7-D8-D9 -> 33935.895 | E10: =E5+E6+E7-E8-E9 -> 32168.486 | F10: =F5+F6+F7-F8-F9 -> 30023.92
A12: Interest Expense (Opening Balance x Blended Rate) | B12: =B5*Assumptions!$B$25 -> 1130.5473 | C12: =C5*Assumptions!$B$25 -> 2454.5105 | D12: =D5*Assumptions!$B$25 -> 2929.4566 | E12: =E5*Assumptions!$B$25 -> 2969.3908 | F12: =F5*Assumptions!$B$25 -> 2814.7425
A14: MEMO: Equity Required for New Capex (25%) | B14: =Assumptions!$B$23*'Capex Model'!L$36 -> 3218.9744 | C14: =Assumptions!$B$23*'Capex Model'!M$36 -> 1594.3571 | D14: =Assumptions!$B$23*'Capex Model'!N$36 -> 672.08947 | E14: =Assumptions!$B$23*'Capex Model'!O$36 -> 123.74597 | F14: =Assumptions!$B$23*'Capex Model'!P$36 -> 0
A15: MEMO: CFO Proxy Available (PAT + D&A, pre-shortfall) | B15: ='P&L'!E38+'P&L'!E29 -> 963.8645 | C15: ='P&L'!F38+'P&L'!F29 -> 2543.8302 | D15: ='P&L'!G38+'P&L'!G29 -> 3697.2077 | E15: ='P&L'!H38+'P&L'!H29 -> 5304.8591 | F15: ='P&L'!I38+'P&L'!I29 -> 5848.5618
A16: MEMO: Residual after Debt Service | B16: =B15-B9-B8 -> -1309.4259 | C16: =C15-C9-C8 -> 673.72696 | D16: =D15-D9-D8 -> 1465.2408 | E16: =E15-E9-E8 -> 3042.466 | F16: =F15-F9-F8 -> 3703.9961

Sheet P&L
A1: PROFIT & LOSS STATEMENT (Rs crore) — FY24A-FY26A tie exactly to RHP Restated Financials
B3: FY24A | C3: FY25A | D3: FY26A | E3: FY27E | F3: FY28E | G3: FY29E | H3: FY30E | I3: FY31E
A5: Revenue from Operations | B5: 391.55 | C5: 508.678 | D5: 718.934 | E5: ='Revenue Model'!M54 -> 2437.5935 | F5: ='Revenue Model'!O54 -> 5937.1108 | G5: ='Revenue Model'!Q54 -> 8038.7308 | H5: ='Revenue Model'!S54 -> 10353.315 | I5: ='Revenue Model'!U54 -> 11021.703
A7: Other Income | B7: 32.897 | C7: 61.102 | D7: 85.996 | E7: =D7*(1+Assumptions!$B$17) -> 90.2958 | F7: =E7*(1+Assumptions!$B$17) -> 94.81059 | G7: =F7*(1+Assumptions!$B$17) -> 99.55112 | H7: =G7*(1+Assumptions!$B$17) -> 104.52868 | I7: =H7*(1+Assumptions!$B$17) -> 109.75511
A8: Total Income | B8: =B5+B7 -> 424.447 | C8: =C5+C7 -> 569.78 | D8: =D5+D7 -> 804.93 | E8: =E5+E7 -> 2527.8893 | F8: =F5+F7 -> 6031.9213 | G8: =G5+G7 -> 8138.2819 | H8: =H5+H7 -> 10457.844 | I8: =I5+I7 -> 11131.459
A10: Cost of Power Purchased | B10: 0 | C10: 0 | D10: 2.323 | E10: =D10*(1+Assumptions!$B$17) -> 2.43915 | F10: =E10*(1+Assumptions!$B$17) -> 2.5611075 | G10: =F10*(1+Assumptions!$B$17) -> 2.6891629 | H10: =G10*(1+Assumptions!$B$17) -> 2.823621 | I10: =H10*(1+Assumptions!$B$17) -> 2.9648021
A12: Employee Benefits Expense
A13: Cash Salary, Wages & Bonus | B13: 11.308 | C13: 19.051 | D13: 16.663 | E13: =D13*('Revenue Model'!M56/Assumptions!$B$76)*(1+Assumptions!$B$17) -> 43.974238 | F13: =E13*('Revenue Model'!O56/'Revenue Model'!M56)*(1+Assumptions!$B$17) -> 69.785222 | G13: =F13*('Revenue Model'!Q56/'Revenue Model'!O56)*(1+Assumptions!$B$17) -> 96.872881 | H13: =G13*('Revenue Model'!S56/'Revenue Model'!Q56)*(1+Assumptions!$B$17) -> 120.98855 | I13: =H13*('Revenue Model'!U56/'Revenue Model'!S56)*(1+Assumptions!$B$17) -> 127.03798
A14: Statutory add-ons (PF/Gratuity/Leave, % of salary) | B14: 1.29 | C14: 2.213 | D14: 2.48 | E14: =E13*Assumptions!$B$77 -> 6.5433667 | F14: =F13*Assumptions!$B$77 -> 10.384041 | G14: =G13*Assumptions!$B$77 -> 14.414685 | H14: =H13*Assumptions!$B$77 -> 18.003096 | I14: =I13*Assumptions!$B$77 -> 18.903251
A15: Staff Welfare | B15: 1.522 | C15: 2.178 | D15: 2.514 | E15: =D15*('Revenue Model'!M56/Assumptions!$B$76)*(1+Assumptions!$B$17) -> 6.6345337 | F15: =E15*('Revenue Model'!O56/'Revenue Model'!M56)*(1+Assumptions!$B$17) -> 10.528719 | G15: =F15*('Revenue Model'!Q56/'Revenue Model'!O56)*(1+Assumptions!$B$17) -> 14.615521 | H15: =G15*('Revenue Model'!S56/'Revenue Model'!Q56)*(1+Assumptions!$B$17) -> 18.253929 | I15: =H15*('Revenue Model'!U56/'Revenue Model'!S56)*(1+Assumptions!$B$17) -> 19.166625
A16: ESOP Expense (held flat at FY26) | B16: 0 | C16: 0 | D16: 8.866 | E16: =D16 -> 8.866 | F16: =E16 -> 8.866 | G16: =F16 -> 8.866 | H16: =G16 -> 8.866 | I16: =H16 -> 8.866
A17: Total Employee Benefits | B17: =SUM(B13:B16) -> 14.12 | C17: =SUM(C13:C16) -> 23.442 | D17: =SUM(D13:D16) -> 30.523 | E17: =SUM(E13:E16) -> 66.018139 | F17: =SUM(F13:F16) -> 99.563982 | G17: =SUM(G13:G16) -> 134.76909 | H17: =SUM(H13:H16) -> 166.11157 | I17: =SUM(I13:I16) -> 173.97385
A19: Other Expenses
A20: Fixed (corporate overhead) - grown at inflation | B20: 8.522 | C20: 12.898 | D20: 18.534 | E20: =D20*(1+Assumptions!$B$17) -> 19.4607 | F20: =E20*(1+Assumptions!$B$17) -> 20.433735 | G20: =F20*(1+Assumptions!$B$17) -> 21.455422 | H20: =G20*(1+Assumptions!$B$17) -> 22.528193 | I20: =H20*(1+Assumptions!$B$17) -> 23.654602
A21: Variable (MW-linked) - MW growth + inflation | B21: 28.652 | C21: 46.181 | D21: 57.043 | E21: =D21*('Revenue Model'!M56/Assumptions!$B$76)*(1+Assumptions!$B$17) -> 150.53847 | F21: =E21*('Revenue Model'!O56/'Revenue Model'!M56)*(1+Assumptions!$B$17) -> 238.89806 | G21: =F21*('Revenue Model'!Q56/'Revenue Model'!O56)*(1+Assumptions!$B$17) -> 331.62814 | H21: =G21*('Revenue Model'!S56/'Revenue Model'!Q56)*(1+Assumptions!$B$17) -> 414.18411 | I21: =H21*('Revenue Model'!U56/'Revenue Model'!S56)*(1+Assumptions!$B$17) -> 434.89332
A22: CSR (2% of trailing 3yr avg PAT, statutory formula) | B22: 0.542 | C22: 0.994 | D22: 1.405 | E22: =Assumptions!$B$71*AVERAGE(B38,C38,D38) -> 0.78004 | F22: =Assumptions!$B$71*AVERAGE(C38,D38,E38) -> 2.6930368 | G22: =Assumptions!$B$71*AVERAGE(D38,E38,F38) -> 10.93123 | H22: =Assumptions!$B$71*AVERAGE(E38,F38,G38) -> 23.379471 | I22: =Assumptions!$B$71*AVERAGE(F38,G38,H38) -> 42.327158
A23: One-offs (FX/loss on disposal/liquidated damages) - held at zero fwd | B23: 1.758 | C23: 0.58 | D23: 2.918 | E23: 0 | F23: 0 | G23: 0 | H23: 0 | I23: 0
A24: Total Other Expenses | B24: =SUM(B20:B23) -> 39.474 | C24: =SUM(C20:C23) -> 60.653 | D24: =SUM(D20:D23) -> 79.9 | E24: =SUM(E20:E23) -> 170.77921 | F24: =SUM(F20:F23) -> 262.02483 | G24: =SUM(G20:G23) -> 364.01479 | H24: =SUM(H20:H23) -> 460.09178 | I24: =SUM(I20:I23) -> 500.87508
A26: EBITDA | B26: =B8-B10-B17-B24 -> 370.853 | C26: =C8-C10-C17-C24 -> 485.685 | D26: =D8-D10-D17-D24 -> 692.184 | E26: =E8-E10-E17-E24 -> 2288.6528 | F26: =F8-F10-F17-F24 -> 5667.7714 | G26: =G8-G10-G17-G24 -> 7636.8088 | H26: =H8-H10-H17-H24 -> 9828.8172 | I26: =I8-I10-I17-I24 -> 10453.645
A27: EBITDA Margin % | B27: =B26/B8 -> 0.87373217 | C27: =C26/C8 -> 0.85240795 | D27: =D26/D8 -> 0.85993068 | E27: =E26/E8 -> 0.90536117 | F27: =F26/F8 -> 0.93962953 | G27: =G26/G8 -> 0.93838097 | H27: =H26/H8 -> 0.93985118 | I27: =I26/I8 -> 0.93910827
A28: EV/EBITDA | B28: =B26*10 -> 3708.53 | C28: =C26*10 -> 4856.85 | D28: =D26*10 -> 6921.84 | E28: =E26*10 -> 22886.528 | F28: =F26*10 -> 56677.714 | G28: =G26*10 -> 76368.088 | H28: =H26*10 -> 98288.172 | I28: =I26*10 -> 104536.45
A29: Depreciation & Amortisation | B29: 122.152 | C29: 166.378 | D29: 236.864 | E29: =E55 -> 636.85099 | F29: =F55 -> 1271.6232 | G29: =G55 -> 1789.5076 | H29: =H55 -> 2135.6924 | I29: =I55 -> 2227.3774
A30: EBIT | B30: =B26-B29 -> 248.701 | C30: =C26-C29 -> 319.307 | D30: =D26-D29 -> 455.32 | E30: =E26-E29 -> 1651.8018 | F30: =F26-F29 -> 4396.1483 | G30: =G26-G29 -> 5847.3012 | H30: =H26-H29 -> 7693.1248 | I30: =I26-I29 -> 8226.2674
A32: Finance Cost - Debt Interest | B32: 178.223 | C32: 245.07 | D32: 360.574 | E32: ='Debt Model'!B12 -> 1130.5473 | F32: ='Debt Model'!C12 -> 2454.5105 | G32: ='Debt Model'!D12 -> 2929.4566 | H32: ='Debt Model'!E12 -> 2969.3908 | I32: ='Debt Model'!F12 -> 2814.7425
A33: Finance Cost - Other (lease/decommissioning unwind/misc) | B33: 12.973 | C33: 19.339 | D33: 39.552 | E33: =E71 -> 82.310185 | F33: =F71 -> 233.9773 | G33: =G71 -> 357.17335 | H33: =H71 -> 469.81901 | I33: =I71 -> 550.87469
A34: Total Finance Cost | B34: =B32+B33 -> 191.196 | C34: =C32+C33 -> 264.409 | D34: =D32+D33 -> 400.126 | E34: =E32+E33 -> 1212.8575 | F34: =F32+F33 -> 2688.4878 | G34: =G32+G33 -> 3286.63 | H34: =H32+H33 -> 3439.2098 | I34: =I32+I33 -> 3365.6172
A36: Profit Before Tax | B36: =B30-B34 -> 57.505 | C36: =C30-C34 -> 54.898 | D36: =D30-D34 -> 55.194 | E36: =E30-E34 -> 438.94431 | F36: =F30-F34 -> 1707.6605 | G36: =G30-G34 -> 2560.6713 | H36: =H30-H34 -> 4253.9149 | I36: =I30-I34 -> 4860.6502
A37: Tax Expense | B37: 17.431 | C37: 18.42 | D37: 14.73 | E37: =E36*Assumptions!$B$14 -> 111.9308 | F37: =F36*Assumptions!$B$14 -> 435.45342 | G37: =G36*Assumptions!$B$14 -> 652.97118 | H37: =H36*Assumptions!$B$14 -> 1084.7483 | I37: =I36*Assumptions!$B$14 -> 1239.4658
A38: Profit After Tax (PAT) | B38: 40.064 | C38: 36.478 | D38: 40.464 | E38: =E36-E37 -> 327.01351 | F38: =F36-F37 -> 1272.207 | G38: =G36-G37 -> 1907.7001 | H38: =H36-H37 -> 3169.1666 | I38: =I36-I37 -> 3621.1844
A39: P/E | B39: =B38*20 -> 801.28 | C39: =C38*20 -> 729.56 | D39: =D38*20 -> 809.28 | E39: =E38*20 -> 6540.2703 | F39: =F38*20 -> 25444.141 | G39: =G38*20 -> 38154.002 | H39: =H38*20 -> 63383.333 | I39: =I38*20 -> 72423.688
A42: D&A SUPPORTING SCHEDULE (Net Block roll-forward, half-year convention on new capitalisation)
B44: FY24A | C44: FY25A | D44: FY26A | E44: FY27E | F44: FY28E | G44: FY29E | H44: FY30E | I44: FY31E
A45: Solar Net Block - Opening (FY27 opening = FY26 closing, per Balance Sheet allocation) | E45: =D48 -> 3327.5 | F45: =E48 -> 3363.2089 | G45: =F48 -> 3228.6805 | H45: =G48 -> 3099.5333 | I45: =H48 -> 2975.552
A46: (+) Capitalised (Solar, from Capex Model) | E46: ='Capex Model'!L40 -> 172.25396 | F46: ='Capex Model'!M40 -> 0 | G46: ='Capex Model'!N40 -> 0 | H46: ='Capex Model'!O40 -> 0 | I46: ='Capex Model'!P40 -> 0
A47: (-) Depreciation (Opening/25 + Capitalised/25 x 0.5) | E47: =E45/Assumptions!$B$29+E46/Assumptions!$B$29*0.5 -> 136.54508 | F47: =F45/Assumptions!$B$29+F46/Assumptions!$B$29*0.5 -> 134.52836 | G47: =G45/Assumptions!$B$29+G46/Assumptions!$B$29*0.5 -> 129.14722 | H47: =H45/Assumptions!$B$29+H46/Assumptions!$B$29*0.5 -> 123.98133 | I47: =I45/Assumptions!$B$29+I46/Assumptions!$B$29*0.5 -> 119.02208
A48: Solar Net Block - Closing | D48: 3327.5 | E48: =E45+E46-E47 -> 3363.2089 | F48: =F45+F46-F47 -> 3228.6805 | G48: =G45+G46-G47 -> 3099.5333 | H48: =H45+H46-H47 -> 2975.552 | I48: =I45+I46-I47 -> 2856.5299
A50: Other (Wind/WSH/FDRE/BESS) Net Block - Opening | E50: =D53 -> 3059.3 | F50: =E53 -> 15658.46 | G50: =F53 -> 28310.866 | H50: =G53 -> 36332.71 | I50: =H53 -> 41921.325
A51: (+) Capitalised (Other, from Capex Model) | E51: ='Capex Model'!L41 -> 13034.457 | F51: ='Capex Model'!M41 -> 13674.948 | G51: ='Capex Model'!N41 -> 9525.183 | H51: ='Capex Model'!O41 -> 7408.4757 | I51: ='Capex Model'!P41 -> 0
A52: (-) Depreciation (Opening/22 + Capitalised/22 x 0.5) | E52: =E50/Assumptions!$B$30+E51/Assumptions!$B$30*0.5 -> 435.29676 | F52: =F50/Assumptions!$B$30+F51/Assumptions!$B$30*0.5 -> 1022.5425 | G52: =G50/Assumptions!$B$30+G51/Assumptions!$B$30*0.5 -> 1503.339 | H52: =H50/Assumptions!$B$30+H51/Assumptions!$B$30*0.5 -> 1819.8613 | I52: =I50/Assumptions!$B$30+I51/Assumptions!$B$30*0.5 -> 1905.5148
A53: Other Net Block - Closing | D53: 3059.3 | E53: =E50+E51-E52 -> 15658.46 | F53: =F50+F51-F52 -> 28310.866 | G53: =G50+G51-G52 -> 36332.71 | H53: =H50+H51-H52 -> 41921.325 | I53: =I50+I51-I52 -> 40015.81
A55: TOTAL D&A (Solar + Other) | E55: =E47+E52+E61 -> 636.85099 | F55: =F47+F52+F61 -> 1271.6232 | G55: =G47+G52+G61 -> 1789.5076 | H55: =H47+H52+H61 -> 2135.6924 | I55: =I47+I52+I61 -> 2227.3774
A57: ROU ASSET & LEASE LIABILITY SCHEDULE (new leases driven by New MW Added, not revenue — per user request)
A58: New MW Added in Year (from Revenue Model operational roll-forward) | E58: ='Revenue Model'!M56-Assumptions!$B$76 -> 2004 | F58: ='Revenue Model'!O56-'Revenue Model'!M56 -> 1702 | G58: ='Revenue Model'!Q56-'Revenue Model'!O56 -> 1620 | H58: ='Revenue Model'!S56-'Revenue Model'!Q56 -> 1260 | I58: ='Revenue Model'!U56-'Revenue Model'!S56 -> 0
A59: ROU Asset - Opening | D59: 0 | E59: =D62 -> 1073.196 | F59: =E62 -> 2632.3258 | G59: =F62 -> 3897.1569 | H59: =G62 -> 5053.0622 | I59: =H62 -> 5882.3776
A60: (+) New ROU Additions (New MW x Rs cr/MW intensity) | E60: =E58*Assumptions!$B$83 -> 1624.1389 | F60: =F58*Assumptions!$B$83 -> 1379.3835 | G60: =G58*Assumptions!$B$83 -> 1312.9267 | H60: =H58*Assumptions!$B$83 -> 1021.1652 | I60: =I58*Assumptions!$B$83 -> 0
A61: (-) ROU Amortisation (Opening/29yr + New Additions/29yr x 0.5, half-year convention) | E61: =E59/Assumptions!$B$31+E60/Assumptions!$B$31*0.5 -> 65.009154 | F61: =F59/Assumptions!$B$31+F60/Assumptions!$B$31*0.5 -> 114.55233 | G61: =G59/Assumptions!$B$31+G60/Assumptions!$B$31*0.5 -> 157.02139 | H61: =H59/Assumptions!$B$31+H60/Assumptions!$B$31*0.5 -> 191.84982 | I61: =I59/Assumptions!$B$31+I60/Assumptions!$B$31*0.5 -> 202.84061
A62: ROU Asset - Closing | D62: ='Balance Sheet'!D8 -> 1073.196 | E62: =E59+E60-E61 -> 2632.3258 | F62: =F59+F60-F61 -> 3897.1569 | G62: =G59+G60-G61 -> 5053.0622 | H62: =H59+H60-H61 -> 5882.3776 | I62: =I59+I60-I61 -> 5679.537
A64: Lease Liability - Opening | E64: =D67 -> 839.984 | F64: =E67 -> 2435.158 | G64: =F67 -> 3730.5705 | H64: =G67 -> 4914.8568 | I64: =H67 -> 5766.5442
A65: (+) New Lease Liabilities (= New ROU Additions) | E65: =E60 -> 1624.1389 | F65: =F60 -> 1379.3835 | G65: =G60 -> 1312.9267 | H65: =H60 -> 1021.1652 | I65: =I60 -> 0
A66: (-) Lease Repayment (Opening/29yr, straight-line simplification) | E66: =E64/Assumptions!$B$31 -> 28.964966 | F66: =F64/Assumptions!$B$31 -> 83.970965 | G66: =G64/Assumptions!$B$31 -> 128.64036 | H66: =H64/Assumptions!$B$31 -> 169.47782 | I66: =I64/Assumptions!$B$31 -> 198.84635
A67: Lease Liability - Closing | D67: ='Balance Sheet'!D20 -> 839.984 | E67: =E64+E65-E66 -> 2435.158 | F67: =F64+F65-F66 -> 3730.5705 | G67: =G64+G65-G66 -> 4914.8568 | H67: =H64+H65-H66 -> 5766.5442 | I67: =I64+I65-I66 -> 5567.6978
A69: Lease Interest Expense (Opening Lease Liability x effective rate) | E69: =E64*Assumptions!$B$82 -> 79.79848 | F69: =F64*Assumptions!$B$82 -> 231.34001 | G69: =G64*Assumptions!$B$82 -> 354.4042 | H69: =H64*Assumptions!$B$82 -> 466.9114 | I69: =I64*Assumptions!$B$82 -> 547.8217
A70: Non-Lease Other Finance Cost (decommissioning unwind + other borrowing + FX; FY26A base x inflation) | D70: 2.3921 | E70: =D70*(1+Assumptions!$B$17) -> 2.511705 | F70: =E70*(1+Assumptions!$B$17) -> 2.6372903 | G70: =F70*(1+Assumptions!$B$17) -> 2.7691548 | H70: =G70*(1+Assumptions!$B$17) -> 2.9076125 | I70: =H70*(1+Assumptions!$B$17) -> 3.0529931
A71: Total Finance Cost - Other (= Lease Interest + Non-Lease Other) | E71: =E69+E70 -> 82.310185 | F71: =F69+F70 -> 233.9773 | G71: =G69+G70 -> 357.17335 | H71: =H69+H70 -> 469.81901 | I71: =I69+I70 -> 550.87469

Sheet Balance Sheet
A1: BALANCE SHEET (Rs crore) — FY24A-FY26A tie exactly to RHP Summary of Restated Consolidated Assets & Liabilities, p.94
B3: FY24A | C3: FY25A | D3: FY26A | E3: FY27E | F3: FY28E | G3: FY29E | H3: FY30E | I3: FY31E
A5: ASSETS
A6: Net Property, Plant & Equipment | B6: 3143.608 | C6: 3976.938 | D6: 6386.762 | E6: ='P&L'!E48+'P&L'!E53 -> 19021.669 | F6: ='P&L'!F48+'P&L'!F53 -> 31539.547 | G6: ='P&L'!G48+'P&L'!G53 -> 39432.243 | H6: ='P&L'!H48+'P&L'!H53 -> 44896.877 | I6: ='P&L'!I48+'P&L'!I53 -> 42872.34
A7: Capital Work-in-Progress | B7: 412.709 | C7: 2019.251 | D7: 7373.078 | E7: =MAX(0,D7+'Capex Model'!L36-('Capex Model'!L40+'Capex Model'!L41)) -> 10261.239 | F7: =MAX(0,E7+'Capex Model'!M36-('Capex Model'!M40+'Capex Model'!M41)) -> 4558.0765 | G7: =MAX(0,F7+'Capex Model'!N36-('Capex Model'!N40+'Capex Model'!N41)) -> 0 | H7: =MAX(0,G7+'Capex Model'!O36-('Capex Model'!O40+'Capex Model'!O41)) -> 0 | I7: =MAX(0,H7+'Capex Model'!P36-('Capex Model'!P40+'Capex Model'!P41)) -> 0
A8: Right-of-Use Assets | B8: 299.167 | C8: 622.071 | D8: 1073.196 | E8: ='P&L'!E62 -> 2632.3258 | F8: ='P&L'!F62 -> 3897.1569 | G8: ='P&L'!G62 -> 5053.0622 | H8: ='P&L'!H62 -> 5882.3776 | I8: ='P&L'!I62 -> 5679.537
A9: Trade Receivables | B9: 62.887 | C9: 72.379 | D9: 111.937 | E9: ='P&L'!E5*Assumptions!$B$56/365 -> 146.12204 | F9: ='P&L'!F5*Assumptions!$B$56/365 -> 355.90132 | G9: ='P&L'!G5*Assumptions!$B$56/365 -> 481.88337 | H9: ='P&L'!H5*Assumptions!$B$56/365 -> 620.63162 | I9: ='P&L'!I5*Assumptions!$B$56/365 -> 660.69828
A10: Cash & Bank Balances (incl. investments/other bank balances) | B10: 857.574 | C10: 2652.51 | D10: 3357.497 | E10: ='Cash Flow & FCFE'!E27 -> 2882.6229 | F10: ='Cash Flow & FCFE'!F27 -> 2694.9691 | G10: ='Cash Flow & FCFE'!G27 -> 3386.1301 | H10: ='Cash Flow & FCFE'!H27 -> 6189.2424 | I10: ='Cash Flow & FCFE'!I27 -> 9866.972
A11: Other Assets (financial + non-financial, held flat fwd — non-core) | B11: 210.499 | C11: 1013.657 | D11: 1235.983 | E11: =D11 -> 1235.983 | F11: =E11 -> 1235.983 | G11: =F11 -> 1235.983 | H11: =G11 -> 1235.983 | I11: =H11 -> 1235.983
A12: TOTAL ASSETS | B12: =SUM(B6:B11) -> 4986.444 | C12: =SUM(C6:C11) -> 10356.806 | D12: =SUM(D6:D11) -> 19538.453 | E12: =SUM(E6:E11) -> 36179.962 | F12: =SUM(F6:F11) -> 44281.634 | G12: =SUM(G6:G11) -> 49589.302 | H12: =SUM(H6:H11) -> 58825.111 | I12: =SUM(I6:I11) -> 60315.53
A14: EQUITY & LIABILITIES
A15: Equity Share Capital | B15: 25.906 | C15: 488.99 | D15: 488.99 | E15: =$D$15+Assumptions!$B$63*10/10000000 -> 568.99 | F15: =E15 -> 568.99 | G15: =F15 -> 568.99 | H15: =G15 -> 568.99 | I15: =H15 -> 568.99
A16: Other Equity (Securities Premium + Retained Earnings) | B16: 1705.771 | C16: 2870.908 | D16: 2934.893 | E16: =D16+'P&L'!E38+(Assumptions!$B$62-Assumptions!$B$63*10/10000000) -> 4981.9065 | F16: =E16+'P&L'!F38 -> 6254.1135 | G16: =F16+'P&L'!G38 -> 8161.8137 | H16: =G16+'P&L'!H38 -> 11330.98 | I16: =H16+'P&L'!I38 -> 14952.165
A17: TOTAL EQUITY | B17: =B15+B16 -> 1731.677 | C17: =C15+C16 -> 3359.898 | D17: =D15+D16 -> 3423.883 | E17: =E15+E16 -> 5550.8965 | F17: =F15+F16 -> 6823.1035 | G17: =G15+G16 -> 8730.8037 | H17: =H15+H16 -> 11899.97 | I17: =I15+I16 -> 15521.155
A19: Borrowings | B19: 2671.701 | C19: 5502.529 | D19: 12920.541 | E19: ='Debt Model'!B10 -> 28051.549 | F19: ='Debt Model'!C10 -> 33479.504 | G19: ='Debt Model'!D10 -> 33935.895 | H19: ='Debt Model'!E10 -> 32168.486 | I19: ='Debt Model'!F10 -> 30023.92
A20: Lease Liabilities | B20: 222.429 | C20: 468.151 | D20: 839.984 | E20: ='P&L'!E67 -> 2435.158 | F20: ='P&L'!F67 -> 3730.5705 | G20: ='P&L'!G67 -> 4914.8568 | H20: ='P&L'!H67 -> 5766.5442 | I20: ='P&L'!I67 -> 5567.6978
A21: Decommissioning & Other Provisions | B21: 56.173 | C21: 76.236 | D21: 88.259 | E21: =D21+(E6-D6)*0.01 -> 214.60807 | F21: =E21+(F6-E6)*0.01 -> 339.78685 | G21: =F21+(G6-F6)*0.01 -> 418.71381 | H21: =G21+(H6-G6)*0.01 -> 473.36015 | I21: =H21+(I6-H6)*0.01 -> 453.11478
A22: Trade Payables | B22: 9.018 | C22: 14.184 | D22: 21.079 | E22: =('P&L'!E10+'P&L'!E17+'P&L'!E24)*Assumptions!$B$57/365 -> 29.49491 | F22: =('P&L'!F10+'P&L'!F17+'P&L'!F24)*Assumptions!$B$57/365 -> 44.895196 | G22: =('P&L'!G10+'P&L'!G17+'P&L'!G24)*Assumptions!$B$57/365 -> 61.825444 | H22: =('P&L'!H10+'P&L'!H17+'P&L'!H24)*Assumptions!$B$57/365 -> 77.55127 | I22: =('P&L'!I10+'P&L'!I17+'P&L'!I24)*Assumptions!$B$57/365 -> 83.566077
A23: Deferred Tax Liabilities (net, held flat fwd) | B23: 38.994 | C23: 50.366 | D23: 47.693 | E23: =D23 -> 47.693 | F23: =E23 -> 47.693 | G23: =F23 -> 47.693 | H23: =G23 -> 47.693 | I23: =H23 -> 47.693
A24: Other Liabilities (incl. capital creditors, tracks CWIP activity) | B24: 256.452 | C24: 885.442 | D24: 2197.014 | E24: =E12-E17-E19-E20-E21-E22-E23 -> -149.43711 | F24: =F12-F17-F19-F20-F21-F22-F23 -> -183.91967 | G24: =G12-G17-G19-G20-G21-G22-G23 -> 1479.5144 | H24: =H12-H17-H19-H20-H21-H22-H23 -> 8391.5063 | I24: =I12-I17-I19-I20-I21-I22-I23 -> 8618.3834
A25: TOTAL LIABILITIES | B25: =SUM(B19:B24) -> 3254.767 | C25: =SUM(C19:C24) -> 6996.908 | D25: =SUM(D19:D24) -> 16114.57 | E25: =SUM(E19:E24) -> 30629.065 | F25: =SUM(F19:F24) -> 37458.53 | G25: =SUM(G19:G24) -> 40858.499 | H25: =SUM(H19:H24) -> 46925.141 | I25: =SUM(I19:I24) -> 44794.375
A27: TOTAL EQUITY + LIABILITIES | B27: =B17+B25 -> 4986.444 | C27: =C17+C25 -> 10356.806 | D27: =D17+D25 -> 19538.453 | E27: =E17+E25 -> 36179.962 | F27: =F17+F25 -> 44281.634 | G27: =G17+G25 -> 49589.302 | H27: =H17+H25 -> 58825.111 | I27: =I17+I25 -> 60315.53
A28: CHECK (Assets - Equity&Liabilities) | B28: =B12-B27 -> 0 | C28: =C12-C27 -> 0 | D28: =D12-D27 -> 0 | E28: =E12-E27 -> 0 | F28: =F12-F27 -> 0 | G28: =G12-G27 -> 0 | H28: =H12-H27 -> 0 | I28: =I12-I27 -> 0

Sheet Cash Flow & FCFE
A1: CASH FLOW STATEMENT & FCFE (Rs crore)
A2: FY24A-FY26A CFO/CFI/CFF tie exactly to RHP MD&A Cash Flows table, p.645. FCFE excludes the FY27 one-time IPO-funded debt repayment & its offsetting equity effect (model values post-IPO ongoing cash flows to post-issue share count).
B4: FY24A | C4: FY25A | D4: FY26A | E4: FY27E | F4: FY28E | G4: FY29E | H4: FY30E | I4: FY31E
A6: CASH FLOW FROM OPERATIONS
A7: Profit After Tax | B7: 40.064 | C7: 36.478 | D7: 40.464 | E7: ='P&L'!E38 -> 327.01351 | F7: ='P&L'!F38 -> 1272.207 | G7: ='P&L'!G38 -> 1907.7001 | H7: ='P&L'!H38 -> 3169.1666 | I7: ='P&L'!I38 -> 3621.1844
A8: (+) D&A (non-cash) | B8: 122.152 | C8: 166.378 | D8: 236.864 | E8: ='P&L'!E29 -> 636.85099 | F8: ='P&L'!F29 -> 1271.6232 | G8: ='P&L'!G29 -> 1789.5076 | H8: ='P&L'!H29 -> 2135.6924 | I8: ='P&L'!I29 -> 2227.3774
A9: (+) Interest on Decommissioning Provision (non-cash unwind) | B9: 0 | C9: 0 | D9: 0 | E9: =6.1*(1+Assumptions!$B$17)^1 -> 6.405 | F9: =6.1*(1+Assumptions!$B$17)^2 -> 6.72525 | G9: =6.1*(1+Assumptions!$B$17)^3 -> 7.0615125 | H9: =6.1*(1+Assumptions!$B$17)^4 -> 7.4145881 | I9: =6.1*(1+Assumptions!$B$17)^5 -> 7.7853175
A10: (-) Increase in Trade Receivables | B10: 0 | C10: 0 | D10: 0 | E10: =('Balance Sheet'!E9-'Balance Sheet'!D9) -> 34.185044 | F10: =('Balance Sheet'!F9-'Balance Sheet'!E9) -> 209.77928 | G10: =('Balance Sheet'!G9-'Balance Sheet'!F9) -> 125.98204 | H10: =('Balance Sheet'!H9-'Balance Sheet'!G9) -> 138.74826 | I10: =('Balance Sheet'!I9-'Balance Sheet'!H9) -> 40.066656
A11: (+) Increase in Trade Payables | B11: 0 | C11: 0 | D11: 0 | E11: =('Balance Sheet'!E22-'Balance Sheet'!D22) -> 8.4159105 | F11: =('Balance Sheet'!F22-'Balance Sheet'!E22) -> 15.400285 | G11: =('Balance Sheet'!G22-'Balance Sheet'!F22) -> 16.930248 | H11: =('Balance Sheet'!H22-'Balance Sheet'!G22) -> 15.725827 | I11: =('Balance Sheet'!I22-'Balance Sheet'!H22) -> 6.0148063
A12: CFO | B12: 322.225 | C12: 365.068 | D12: 469.992 | E12: =SUM(E7:E9)-E10+E11 -> 944.50037 | F12: =SUM(F7:F9)-F10+F11 -> 2356.1765 | G12: =SUM(G7:G9)-G10+G11 -> 3595.2174 | H12: =SUM(H7:H9)-H10+H11 -> 5189.2512 | I12: =SUM(I7:I9)-I10+I11 -> 5822.2953
A14: CASH FLOW FROM INVESTING
A15: (-) Capex (cash basis) | B15: 1073.22 | C15: 2941.292 | D15: 8515.52 | E15: ='Capex Model'!L36 -> 16094.872 | F15: ='Capex Model'!M36 -> 7971.7857 | G15: ='Capex Model'!N36 -> 3360.4473 | H15: ='Capex Model'!O36 -> 618.72984 | I15: ='Capex Model'!P36 -> 0
A16: CFI | B16: -1579.544 | C16: -4182.819 | D16: -6509.769 | E16: =-E15 -> -16094.872 | F16: =-F15 -> -7971.7857 | G16: =-G15 -> -3360.4473 | H16: =-H15 -> -618.72984 | I16: =-I15 -> 0
A18: CASH FLOW FROM FINANCING
A19: (+) New Debt Draws + Shortfall Plug | E19: ='Debt Model'!B6+'Debt Model'!B7 -> 17404.298 | F19: ='Debt Model'!C6+'Debt Model'!C7 -> 7298.0587 | G19: ='Debt Model'!D6+'Debt Model'!D7 -> 2688.3579 | H19: ='Debt Model'!E6+'Debt Model'!E7 -> 494.98387 | I19: ='Debt Model'!F6+'Debt Model'!F7 -> 0
A20: (-) Scheduled Amortisation | E20: ='Debt Model'!B9 -> 861.3694 | F20: ='Debt Model'!C9 -> 1870.1032 | G20: ='Debt Model'!D9 -> 2231.9669 | H20: ='Debt Model'!E9 -> 2262.393 | I20: ='Debt Model'!F9 -> 2144.5657
A21: (-) IPO-funded Debt Repayment (one-time, FY27) | E21: ='Debt Model'!B8 -> 1411.921 | F21: ='Debt Model'!C8 -> 0 | G21: ='Debt Model'!D8 -> 0 | H21: ='Debt Model'!E8 -> 0 | I21: ='Debt Model'!F8 -> 0
A22: (+) IPO Gross Equity Proceeds (one-time, FY27) | E22: =Assumptions!$B$62 -> 1800 | F22: 0 | G22: 0 | H22: 0 | I22: 0
A23: CFF | B23: 1231.381 | C23: 4071.221 | D23: 6866.196 | E23: =E19-E20-E21+E22 -> 16931.008 | F23: =F19-F20-F21+F22 -> 5427.9555 | G23: =G19-G20-G21+G22 -> 456.39094 | H23: =H19-H20-H21+H22 -> -1767.4091 | I23: =I19-I20-I21+I22 -> -2144.5657
A25: NET CHANGE IN CASH | B25: =B12+B16+B23 -> -25.938 | C25: =C12+C16+C23 -> 253.47 | D25: =D12+D16+D23 -> 826.419 | E25: =E12+E16+E23 -> 1780.6359 | F25: =F12+F16+F23 -> -187.65374 | G25: =G12+G16+G23 -> 691.16101 | H25: =H12+H16+H23 -> 2803.1122 | I25: =I12+I16+I23 -> 3677.7296
A26: Opening Cash | B26: 0 | C26: =B27 -> 22.072 | D26: =C27 -> 275.552 | E26: =D27 -> 1101.987 | F26: =E27 -> 2882.6229 | G26: =F27 -> 2694.9691 | H26: =G27 -> 3386.1301 | I26: =H27 -> 6189.2424
A27: Closing Cash | B27: 22.072 | C27: 275.552 | D27: 1101.987 | E27: =E26+E25 -> 2882.6229 | F27: =F26+F25 -> 2694.9691 | G27: =G26+G25 -> 3386.1301 | H27: =H26+H25 -> 6189.2424 | I27: =I26+I25 -> 9866.972
A29: FCFE CALCULATION (excl. one-time IPO deleveraging event)
A30: Profit After Tax | B30: =B7 -> 40.064 | C30: =C7 -> 36.478 | D30: =D7 -> 40.464 | E30: =E7 -> 327.01351 | F30: =F7 -> 1272.207 | G30: =G7 -> 1907.7001 | H30: =H7 -> 3169.1666 | I30: =I7 -> 3621.1844
A31: (+) D&A | B31: =B8 -> 122.152 | C31: =C8 -> 166.378 | D31: =D8 -> 236.864 | E31: =E8 -> 636.85099 | F31: =F8 -> 1271.6232 | G31: =G8 -> 1789.5076 | H31: =H8 -> 2135.6924 | I31: =I8 -> 2227.3774
A32: (-) Capex (cash basis) | B32: =-B15 -> -1073.22 | C32: =-C15 -> -2941.292 | D32: =-D15 -> -8515.52 | E32: =E15 -> 16094.872 | F32: =F15 -> 7971.7857 | G32: =G15 -> 3360.4473 | H32: =H15 -> 618.72984 | I32: =I15 -> 0
A33: (-) Increase in NWC | B33: 0 | C33: 0 | D33: 0 | E33: =E10-E11 -> 25.769134 | F33: =F10-F11 -> 194.37899 | G33: =G10-G11 -> 109.0518 | H33: =H10-H11 -> 123.02243 | I33: =I10-I11 -> 34.05185
A34: (+) Net Borrowing (New Draws + Shortfall - Scheduled Amortisation) | B34: =B23 -> 1231.381 | C34: =C23 -> 4071.221 | D34: =D23 -> 6866.196 | E34: ='Debt Model'!B6+'Debt Model'!B7-'Debt Model'!B9 -> 16542.929 | F34: ='Debt Model'!C6+'Debt Model'!C7-'Debt Model'!C9 -> 5427.9555 | G34: ='Debt Model'!D6+'Debt Model'!D7-'Debt Model'!D9 -> 456.39094 | H34: ='Debt Model'!E6+'Debt Model'!E7-'Debt Model'!E9 -> -1767.4091 | I34: ='Debt Model'!F6+'Debt Model'!F7-'Debt Model'!F9 -> -2144.5657
A35: FCFE | B35: =B30+B31+B32-B33+B34 -> 320.377 | C35: =C30+C31+C32-C33+C34 -> 1332.785 | D35: =D30+D31+D32-D33+D34 -> -1371.996 | E35: =E30+E31-E32-E33+E34 -> 1386.1519 | F35: =F30+F31-F32-F33+F34 -> -194.37899 | G35: =G30+G31-G32-G33+G34 -> 684.09949 | H35: =H30+H31-H32-H33+H34 -> 2795.6977 | I35: =I30+I31-I32-I33+I34 -> 3669.9443

Sheet Valuation
A1: VALUATION — FCFE/DCF & TRADING MULTIPLES
A3: 1. FCFE DCF VALUATION
B5: FY27E | C5: FY28E | D5: FY29E | E5: FY30E | F5: FY31E | G5: FY32E | H5: FY33E | I5: FY34E | J5: Terminal
A6: FCFE (Rs crore) | B6: ='Cash Flow & FCFE'!E35 -> 1386.1519 | C6: ='Cash Flow & FCFE'!F35 -> -194.37899 | D6: ='Cash Flow & FCFE'!G35 -> 684.09949 | E6: ='Cash Flow & FCFE'!H35 -> 2795.6977 | F6: ='Cash Flow & FCFE'!I35 -> 3669.9443 | G6: =F6*(1+Assumptions!$B$18) -> 3963.5398 | H6: =G6*(1+Assumptions!$B$18) -> 4280.623 | I6: =H6*(1+Assumptions!$B$18) -> 4623.0728 | J6: =I6*(1+Assumptions!$B$19)/(Assumptions!$B$11-Assumptions!$B$19) -> 40330.895
A7: Discount Period (years, mid-year convention) | B7: 1 | C7: =B7+1 -> 2 | D7: =C7+1 -> 3 | E7: =D7+1 -> 4 | F7: =E7+1 -> 5 | G7: =F7+1 -> 6 | H7: =G7+1 -> 7 | I7: =H7+1 -> 8 | J7: =I7+1 -> 9
A8: Discount Factor @ Ke | B8: =1/(1+Assumptions!$B$11)^B7 -> 0.85443795 | C8: =1/(1+Assumptions!$B$11)^C7 -> 0.73006421 | D8: =1/(1+Assumptions!$B$11)^D7 -> 0.62379457 | E8: =1/(1+Assumptions!$B$11)^E7 -> 0.53299375 | F8: =1/(1+Assumptions!$B$11)^F7 -> 0.45541009 | G8: =1/(1+Assumptions!$B$11)^G7 -> 0.38911966 | H8: =1/(1+Assumptions!$B$11)^H7 -> 0.33247861 | I8: =1/(1+Assumptions!$B$11)^I7 -> 0.28408234 | J8: =1/(1+Assumptions!$B$11)^J7 -> 0.24273073
A9: PV of FCFE | B9: =B6*B8 -> 1184.3808 | C9: =C6*C8 -> -141.90915 | D9: =D6*D8 -> 426.73755 | E9: =E6*E8 -> 1490.0894 | F9: =F6*F8 -> 1671.3296 | G9: =G6*G8 -> 1542.2913 | H9: =H6*H8 -> 1423.2156 | I9: =I6*I8 -> 1313.3334 | J9: =J6*J8 -> 9789.5476
A11: Sum PV of Explicit FCFE (FY27-31) | B11: =SUM(B9:F9) -> 4630.6282
A12: Sum PV of Fade-period FCFE (FY32-34) | B12: =SUM(G9:I9) -> 4278.8402
A13: PV of Terminal Value | B13: =J9 -> 9789.5476
A14: TOTAL EQUITY VALUE (Rs crore) | B14: =B11+B12+B13 -> 18699.016
A16: Post-Issue Shares Outstanding | B16: =Assumptions!$B$64 -> 568989292
A17: VALUE PER SHARE (Rs) | B17: =B14*10000000/B16 -> 328.63564
A18: CMP | B18: ='Executive Summary'!B16 -> 256
A19: Implied Upside/(Downside) vs IPO Price | B19: =B17/B18-1 -> 0.28373297
A22: 2. TRADING MULTIPLES (based on IPO price & post-issue market cap)
A24: Market Capitalisation (Rs cr) | B24: =B16*B18/10000000 -> 14566.126
A25: (+) Total Debt (FY26A, as-is at listing) | B25: ='Balance Sheet'!D19 -> 12920.541
A26: (-) Cash & Bank (FY26A, as-is at listing) | B26: ='Balance Sheet'!D10 -> 3357.497
A27: ENTERPRISE VALUE (Rs cr) | B27: =B24+B25-B26 -> 24129.17
A28: Note: EV uses FY26A (as-is, pre-listing) net debt — the FY27 IPO-funded debt repayment is a post-listing event, not netted off here. See Cash Flow tab for its cash flow treatment.
B30: FY24A | C30: FY25A | D30: FY26A | E30: FY27E | F30: FY28E | G30: FY29E | H30: FY30E | I30: FY31E
A31: EBITDA (Rs cr) | B31: ='P&L'!B26 -> 370.853 | C31: ='P&L'!C26 -> 485.685 | D31: ='P&L'!D26 -> 692.184 | E31: ='P&L'!E26 -> 2288.6528 | F31: ='P&L'!F26 -> 5667.7714 | G31: ='P&L'!G26 -> 7636.8088 | H31: ='P&L'!H26 -> 9828.8172 | I31: ='P&L'!I26 -> 10453.645
A32: EV / EBITDA | B32: =$B$27/B31 -> 65.063974 | C32: =$B$27/C31 -> 49.680698 | D32: =$B$27/D31 -> 34.859474 | E32: =$B$27/E31 -> 10.542958 | F32: =$B$27/F31 -> 4.2572588 | G32: =$B$27/G31 -> 3.159588 | H32: =$B$27/H31 -> 2.4549414 | I32: =$B$27/I31 -> 2.3082064
A34: PAT (Rs cr) | B34: ='P&L'!B38 -> 40.064 | C34: ='P&L'!C38 -> 36.478 | D34: ='P&L'!D38 -> 40.464 | E34: ='P&L'!E38 -> 327.01351 | F34: ='P&L'!F38 -> 1272.207 | G34: ='P&L'!G38 -> 1907.7001 | H34: ='P&L'!H38 -> 3169.1666 | I34: ='P&L'!I38 -> 3621.1844
A35: P / E | B35: =$B$24/B34 -> 363.57143 | C35: =$B$24/C34 -> 399.31262 | D35: =$B$24/D34 -> 359.97741 | E35: =$B$24/E34 -> 44.542887 | F35: =$B$24/F34 -> 11.449493 | G35: =$B$24/G34 -> 7.635438 | H35: =$B$24/H34 -> 4.5962007 | I35: =$B$24/I34 -> 4.0224756
A37: Revenue (Rs cr) | B37: ='P&L'!B5 -> 391.55 | C37: ='P&L'!C5 -> 508.678 | D37: ='P&L'!D5 -> 718.934 | E37: ='P&L'!E5 -> 2437.5935 | F37: ='P&L'!F5 -> 5937.1108 | G37: ='P&L'!G5 -> 8038.7308 | H37: ='P&L'!H5 -> 10353.315 | I37: ='P&L'!I5 -> 11021.703
A38: P / S | B38: =$B$24/B37 -> 37.20119 | C38: =$B$24/C37 -> 28.635258 | D38: =$B$24/D37 -> 20.260728 | E38: =$B$24/E37 -> 5.9756172 | F38: =$B$24/F37 -> 2.4534031 | G38: =$B$24/G37 -> 1.8119932 | H38: =$B$24/H37 -> 1.4069045 | I38: =$B$24/I37 -> 1.3215857
A40: Historical = current EV/Market Cap against each past year's actuals (FY24A-FY26A). Trailing = FY26A column. Forward = FY27E-FY31E.
A43: 3. PEER COMPARISON (FY26 actuals, per RHP KPI comparison table p.192-194)
A45: Company | B45: Market Cap (Rs cr) [FILL IN] | C45: Revenue FY26 (Rs cr) | D45: EBITDA FY26 (Rs cr) | E45: PAT FY26 (Rs cr) | F45: EV/EBITDA | G45: P/E | H45: P/S | I45: EBITDA Margin %
A46: Juniper Green Energy | B46: =Assumptions!$B$65 -> 12802.259 | C46: 7189.34 | D46: 6921.84 | E46: 404.64 | F46: =IF(B46="","",B46/D46) -> 1.8495457 | G46: =IF(B46="","",B46/E46) -> 31.638639 | H46: =IF(B46="","",B46/C46) -> 1.780728 | I46: =D46/C46 -> 0.96279213
A47: ACME Solar Holdings | B47: 270030 | C47: 2023.379 | D47: 2265.037 | E47: 497.885 | F47: =IF(B47="","",B47/D47) -> 119.2166 | G47: =IF(B47="","",B47/E47) -> 542.35416 | H47: =IF(B47="","",B47/C47) -> 133.45498 | I47: =D47/C47 -> 1.1194329
A48: ReNew Power Global | C48: 13430.5 | D48: 8849.2 | E48: 1038.5 | F48: =IF(B48="","",B48/D48) | G48: =IF(B48="","",B48/E48) | H48: =IF(B48="","",B48/C48) | I48: =D48/C48 -> 0.65888835
A49: Adani Green Energy | B49: 2281650 | C49: 12928 | D49: 11659 | E49: 1987 | F49: =IF(B49="","",B49/D49) -> 195.6986 | G49: =IF(B49="","",B49/E49) -> 1148.2889 | H49: =IF(B49="","",B49/C49) -> 176.48902 | I49: =D49/C49 -> 0.90184097
A50: NTPC Green Energy | B50: 764270 | C50: 2858.42 | D50: 2471.61 | E50: 521.31 | F50: =IF(B50="","",B50/D50) -> 309.2195 | G50: =IF(B50="","",B50/E50) -> 1466.0567 | H50: =IF(B50="","",B50/C50) -> 267.37498 | I50: =D50/C50 -> 0.86467699
A52: Market Cap column left blank for peers (except Juniper, computed from this model) — fill in from current market data. EV proxied by Market Cap for peers (net debt not separately modeled here).

Sheet Ratios
A1: RATIO ANALYSIS
B3: FY24A | C3: FY25A | D3: FY26A | E3: FY27E | F3: FY28E | G3: FY29E | H3: FY30E | I3: FY31E
A5: PROFITABILITY
A6: EBITDA Margin % | B6: ='P&L'!B27 -> 0.87373217 | C6: ='P&L'!C27 -> 0.85240795 | D6: ='P&L'!D27 -> 0.85993068 | E6: ='P&L'!E27 -> 0.90536117 | F6: ='P&L'!F27 -> 0.93962953 | G6: ='P&L'!G27 -> 0.93838097 | H6: ='P&L'!H27 -> 0.93985118 | I6: ='P&L'!I27 -> 0.93910827
A7: Operating EBITDA Margin % (=EBITDA/Revenue, excl. Other Income) | B7: ='P&L'!B26/'P&L'!B5 -> 0.94714085 | C7: ='P&L'!C26/'P&L'!C5 -> 0.95479852 | D7: ='P&L'!D26/'P&L'!D5 -> 0.96279213 | E7: ='P&L'!E26/'P&L'!E5 -> 0.93889847 | F7: ='P&L'!F26/'P&L'!F5 -> 0.95463461 | G7: ='P&L'!G26/'P&L'!G5 -> 0.95000182 | H7: ='P&L'!H26/'P&L'!H5 -> 0.94934006 | I7: ='P&L'!I26/'P&L'!I5 -> 0.94846
A8: PAT Margin % | B8: ='P&L'!B38/'P&L'!B8 -> 0.094391055 | C8: ='P&L'!C38/'P&L'!C8 -> 0.064021201 | D8: ='P&L'!D38/'P&L'!D8 -> 0.05027021 | E8: ='P&L'!E38/'P&L'!E8 -> 0.12936228 | F8: ='P&L'!F38/'P&L'!F8 -> 0.2109124 | G8: ='P&L'!G38/'P&L'!G8 -> 0.23441067 | H8: ='P&L'!H38/'P&L'!H8 -> 0.30304206 | I8: ='P&L'!I38/'P&L'!I8 -> 0.32531086
A9: ROE (PAT / Avg Total Equity) | B9: ='P&L'!B38/'Balance Sheet'!B17 -> 0.023135954 | C9: ='P&L'!C38/AVERAGE('Balance Sheet'!B17,'Balance Sheet'!C17) -> 0.014328769 | D9: ='P&L'!D38/AVERAGE('Balance Sheet'!C17,'Balance Sheet'!D17) -> 0.01192963 | E9: ='P&L'!E38/AVERAGE('Balance Sheet'!D17,'Balance Sheet'!E17) -> 0.072873882 | F9: ='P&L'!F38/AVERAGE('Balance Sheet'!E17,'Balance Sheet'!F17) -> 0.20562583 | G9: ='P&L'!G38/AVERAGE('Balance Sheet'!F17,'Balance Sheet'!G17) -> 0.24530172 | H9: ='P&L'!H38/AVERAGE('Balance Sheet'!G17,'Balance Sheet'!H17) -> 0.30722712 | I9: ='P&L'!I38/AVERAGE('Balance Sheet'!H17,'Balance Sheet'!I17) -> 0.2641164
A10: ROCE (EBIT / Avg (Equity+Debt)) | B10: ='P&L'!B30/('Balance Sheet'!B17+'Balance Sheet'!B19) -> 0.056479594 | C10: ='P&L'!C30/AVERAGE('Balance Sheet'!B17+'Balance Sheet'!B19,'Balance Sheet'!C17+'Balance Sheet'!C19) -> 0.04813986 | D10: ='P&L'!D30/AVERAGE('Balance Sheet'!C17+'Balance Sheet'!C19,'Balance Sheet'!D17+'Balance Sheet'!D19) -> 0.036126686 | E10: ='P&L'!E30/AVERAGE('Balance Sheet'!D17+'Balance Sheet'!D19,'Balance Sheet'!E17+'Balance Sheet'!E19) -> 0.066142357 | F10: ='P&L'!F30/AVERAGE('Balance Sheet'!E17+'Balance Sheet'!E19,'Balance Sheet'!F17+'Balance Sheet'!F19) -> 0.11896746 | G10: ='P&L'!G30/AVERAGE('Balance Sheet'!F17+'Balance Sheet'!F19,'Balance Sheet'!G17+'Balance Sheet'!G19) -> 0.14095095 | H10: ='P&L'!H30/AVERAGE('Balance Sheet'!G17+'Balance Sheet'!G19,'Balance Sheet'!H17+'Balance Sheet'!H19) -> 0.17739346 | I10: ='P&L'!I30/AVERAGE('Balance Sheet'!H17+'Balance Sheet'!H19,'Balance Sheet'!I17+'Balance Sheet'!I19) -> 0.18359431
A12: LEVERAGE / CREDIT
A13: Debt / Equity | B13: ='Balance Sheet'!B19/'Balance Sheet'!B17 -> 1.5428403 | C13: ='Balance Sheet'!C19/'Balance Sheet'!C17 -> 1.6377072 | D13: ='Balance Sheet'!D19/'Balance Sheet'!D17 -> 3.7736514 | E13: ='Balance Sheet'!E19/'Balance Sheet'!E17 -> 5.0535168 | F13: ='Balance Sheet'!F19/'Balance Sheet'!F17 -> 4.9067853 | G13: ='Balance Sheet'!G19/'Balance Sheet'!G17 -> 3.8869154 | H13: ='Balance Sheet'!H19/'Balance Sheet'!H17 -> 2.7032409 | I13: ='Balance Sheet'!I19/'Balance Sheet'!I17 -> 1.934387
A14: Net Debt / Equity | B14: =('Balance Sheet'!B19-'Balance Sheet'!B10)/'Balance Sheet'!B17 -> 1.0476128 | C14: =('Balance Sheet'!C19-'Balance Sheet'!C10)/'Balance Sheet'!C17 -> 0.84824569 | D14: =('Balance Sheet'!D19-'Balance Sheet'!D10)/'Balance Sheet'!D17 -> 2.7930405 | E14: =('Balance Sheet'!E19-'Balance Sheet'!E10)/'Balance Sheet'!E17 -> 4.5342092 | F14: =('Balance Sheet'!F19-'Balance Sheet'!F10)/'Balance Sheet'!F17 -> 4.5118083 | G14: =('Balance Sheet'!G19-'Balance Sheet'!G10)/'Balance Sheet'!G17 -> 3.4990782 | H14: =('Balance Sheet'!H19-'Balance Sheet'!H10)/'Balance Sheet'!H17 -> 2.1831352 | I14: =('Balance Sheet'!I19-'Balance Sheet'!I10)/'Balance Sheet'!I17 -> 1.2986758
A15: Debt / EBITDA | B15: ='Balance Sheet'!B19/'P&L'!B26 -> 7.2042049 | C15: ='Balance Sheet'!C19/'P&L'!C26 -> 11.329419 | D15: ='Balance Sheet'!D19/'P&L'!D26 -> 18.666339 | E15: ='Balance Sheet'!E19/'P&L'!E26 -> 12.256795 | F15: ='Balance Sheet'!F19/'P&L'!F26 -> 5.9069962 | G15: ='Balance Sheet'!G19/'P&L'!G26 -> 4.4437272 | H15: ='Balance Sheet'!H19/'P&L'!H26 -> 3.2728746 | I15: ='Balance Sheet'!I19/'P&L'!I26 -> 2.8721007
A16: Net Debt / EBITDA | B16: =('Balance Sheet'!B19-'Balance Sheet'!B10)/'P&L'!B26 -> 4.8917684 | C16: =('Balance Sheet'!C19-'Balance Sheet'!C10)/'P&L'!C26 -> 5.86804 | D16: =('Balance Sheet'!D19-'Balance Sheet'!D10)/'P&L'!D26 -> 13.815754 | E16: =('Balance Sheet'!E19-'Balance Sheet'!E10)/'P&L'!E26 -> 10.997267 | F16: =('Balance Sheet'!F19-'Balance Sheet'!F10)/'P&L'!F26 -> 5.4315061 | G16: =('Balance Sheet'!G19-'Balance Sheet'!G10)/'P&L'!G26 -> 4.0003312 | H16: =('Balance Sheet'!H19-'Balance Sheet'!H10)/'P&L'!H26 -> 2.6431709 | I16: =('Balance Sheet'!I19-'Balance Sheet'!I10)/'P&L'!I26 -> 1.928222
A17: Interest Coverage (EBIT / Finance Cost) | B17: ='P&L'!B30/'P&L'!B34 -> 1.3007647 | C17: ='P&L'!C30/'P&L'!C34 -> 1.2076253 | D17: ='P&L'!D30/'P&L'!D34 -> 1.1379415 | E17: ='P&L'!E30/'P&L'!E34 -> 1.3619092 | F17: ='P&L'!F30/'P&L'!F34 -> 1.6351751 | G17: ='P&L'!G30/'P&L'!G34 -> 1.7791176 | H17: ='P&L'!H30/'P&L'!H34 -> 2.2368873 | I17: ='P&L'!I30/'P&L'!I34 -> 2.4442077
A19: LIQUIDITY
A20: Current Ratio (approx: Cash+AR / AP) | B20: =('Balance Sheet'!B10+'Balance Sheet'!B9)/'Balance Sheet'!B22 -> 102.06931 | C20: =('Balance Sheet'!C10+'Balance Sheet'!C9)/'Balance Sheet'!C22 -> 192.11005 | D20: =('Balance Sheet'!D10+'Balance Sheet'!D9)/'Balance Sheet'!D22 -> 164.59196 | E20: =('Balance Sheet'!E10+'Balance Sheet'!E9)/'Balance Sheet'!E22 -> 102.68704 | F20: =('Balance Sheet'!F10+'Balance Sheet'!F9)/'Balance Sheet'!F22 -> 67.955388 | G20: =('Balance Sheet'!G10+'Balance Sheet'!G9)/'Balance Sheet'!G22 -> 62.563457 | H20: =('Balance Sheet'!H10+'Balance Sheet'!H9)/'Balance Sheet'!H22 -> 87.81125 | I20: =('Balance Sheet'!I10+'Balance Sheet'!I9)/'Balance Sheet'!I22 -> 125.98019
A21: Cash & Bank / Total Debt | B21: ='Balance Sheet'!B10/'Balance Sheet'!B19 -> 0.32098427 | C21: ='Balance Sheet'!C10/'Balance Sheet'!C19 -> 0.48205289 | D21: ='Balance Sheet'!D10/'Balance Sheet'!D19 -> 0.25985731 | E21: ='Balance Sheet'!E10/'Balance Sheet'!E19 -> 0.10276163 | F21: ='Balance Sheet'!F10/'Balance Sheet'!F19 -> 0.080496088 | G21: ='Balance Sheet'!G10/'Balance Sheet'!G19 -> 0.099780192 | H21: ='Balance Sheet'!H10/'Balance Sheet'!H19 -> 0.1924008 | I21: ='Balance Sheet'!I10/'Balance Sheet'!I19 -> 0.32863703
A23: EFFICIENCY / WORKING CAPITAL
A24: Days Receivable | B24: ='Balance Sheet'!B9/'P&L'!B5*365 -> 58.622794 | C24: ='Balance Sheet'!C9/'P&L'!C5*365 -> 51.935281 | D24: =('Balance Sheet'!D9/'P&L'!D5)*365 -> 56.82998 | E24: ='Balance Sheet'!E9/'P&L'!E5*365 -> 21.88 | F24: ='Balance Sheet'!F9/'P&L'!F5*365 -> 21.88 | G24: ='Balance Sheet'!G9/'P&L'!G5*365 -> 21.88 | H24: ='Balance Sheet'!H9/'P&L'!H5*365 -> 21.88 | I24: ='Balance Sheet'!I9/'P&L'!I5*365 -> 21.88
A25: Days Payable | B25: ='Balance Sheet'!B22/('P&L'!B10+'P&L'!B17+'P&L'!B24)*365 -> 61.416763 | C25: ='Balance Sheet'!C22/('P&L'!C10+'P&L'!C17+'P&L'!C24)*365 -> 61.563232 | D25: ='Balance Sheet'!D22/('P&L'!D10+'P&L'!D17+'P&L'!D24)*365 -> 68.240425 | E25: ='Balance Sheet'!E22/('P&L'!E10+'P&L'!E17+'P&L'!E24)*365 -> 45 | F25: ='Balance Sheet'!F22/('P&L'!F10+'P&L'!F17+'P&L'!F24)*365 -> 45 | G25: ='Balance Sheet'!G22/('P&L'!G10+'P&L'!G17+'P&L'!G24)*365 -> 45 | H25: ='Balance Sheet'!H22/('P&L'!H10+'P&L'!H17+'P&L'!H24)*365 -> 45 | I25: ='Balance Sheet'!I22/('P&L'!I10+'P&L'!I17+'P&L'!I24)*365 -> 45
A27: GROWTH
A28: Revenue Growth % | B28: ="" | C28: =IF(B28<>0,'P&L'!C5/'P&L'!B5-1,"") -> 0.29913932 | D28: =IF(C28<>0,'P&L'!D5/'P&L'!C5-1,"") -> 0.4133381 | E28: =IF(D28<>0,'P&L'!E5/'P&L'!D5-1,"") -> 2.3905665 | F28: =IF(E28<>0,'P&L'!F5/'P&L'!E5-1,"") -> 1.4356443 | G28: =IF(F28<>0,'P&L'!G5/'P&L'!F5-1,"") -> 0.35398026 | H28: =IF(G28<>0,'P&L'!H5/'P&L'!G5-1,"") -> 0.28792913 | I28: =IF(H28<>0,'P&L'!I5/'P&L'!H5-1,"") -> 0.06455787
A29: EBITDA Growth % | B29: ="" | C29: ='P&L'!C26/'P&L'!B26-1 -> 0.3096429 | D29: ='P&L'!D26/'P&L'!C26-1 -> 0.42517064 | E29: ='P&L'!E26/'P&L'!D26-1 -> 2.3064226 | F29: ='P&L'!F26/'P&L'!E26-1 -> 1.4764662 | G29: ='P&L'!G26/'P&L'!F26-1 -> 0.34740946 | H29: ='P&L'!H26/'P&L'!G26-1 -> 0.28703198 | I29: ='P&L'!I26/'P&L'!H26-1 -> 0.063570993
A30: PAT Growth % | B30: ="" | C30: ='P&L'!C38/'P&L'!B38-1 -> -0.089506789 | D30: ='P&L'!D38/'P&L'!C38-1 -> 0.10927134 | E30: ='P&L'!E38/'P&L'!D38-1 -> 7.0815914 | F30: ='P&L'!F38/'P&L'!E38-1 -> 2.8903806 | G30: ='P&L'!G38/'P&L'!F38-1 -> 0.49952017 | H30: ='P&L'!H38/'P&L'!G38-1 -> 0.66124991 | I30: ='P&L'!I38/'P&L'!H38-1 -> 0.14262986
A32: VALUATION (current EV/Market Cap against each period)
A33: EV / EBITDA | B33: =Valuation!$B$27/'P&L'!B26 -> 65.063974 | C33: =Valuation!$B$27/'P&L'!C26 -> 49.680698 | D33: =Valuation!$B$27/'P&L'!D26 -> 34.859474 | E33: =Valuation!$B$27/'P&L'!E26 -> 10.542958 | F33: =Valuation!$B$27/'P&L'!F26 -> 4.2572588 | G33: =Valuation!$B$27/'P&L'!G26 -> 3.159588 | H33: =Valuation!$B$27/'P&L'!H26 -> 2.4549414 | I33: =Valuation!$B$27/'P&L'!I26 -> 2.3082064
A34: P / E | B34: =Valuation!$B$24/'P&L'!B38 -> 363.57143 | C34: =Valuation!$B$24/'P&L'!C38 -> 399.31262 | D34: =Valuation!$B$24/'P&L'!D38 -> 359.97741 | E34: =Valuation!$B$24/'P&L'!E38 -> 44.542887 | F34: =Valuation!$B$24/'P&L'!F38 -> 11.449493 | G34: =Valuation!$B$24/'P&L'!G38 -> 7.635438 | H34: =Valuation!$B$24/'P&L'!H38 -> 4.5962007 | I34: =Valuation!$B$24/'P&L'!I38 -> 4.0224756
A35: P / S | B35: =Valuation!$B$24/'P&L'!B5 -> 37.20119 | C35: =Valuation!$B$24/'P&L'!C5 -> 28.635258 | D35: =Valuation!$B$24/'P&L'!D5 -> 20.260728 | E35: =Valuation!$B$24/'P&L'!E5 -> 5.9756172 | F35: =Valuation!$B$24/'P&L'!F5 -> 2.4534031 | G35: =Valuation!$B$24/'P&L'!G5 -> 1.8119932 | H35: =Valuation!$B$24/'P&L'!H5 -> 1.4069045 | I35: =Valuation!$B$24/'P&L'!I5 -> 1.3215857
A37: EV/EBITDA ~15x | B37: =Valuation!B31*15 -> 5562.795 | C37: =Valuation!C31*15 -> 7285.275 | D37: =Valuation!D31*15 -> 10382.76 | E37: =Valuation!E31*15 -> 34329.792 | F37: =Valuation!F31*15 -> 85016.571 | G37: =Valuation!G31*15 -> 114552.13 | H37: =Valuation!H31*15 -> 147432.26 | I37: =Valuation!I31*15 -> 156804.67
A38: P/E ~35x | B38: ='P&L'!B38*35 -> 1402.24 | C38: ='P&L'!C38*35 -> 1276.73 | D38: ='P&L'!D38*35 -> 1416.24 | E38: ='P&L'!E38*35 -> 11445.473 | F38: ='P&L'!F38*35 -> 44527.246 | G38: ='P&L'!G38*35 -> 66769.504 | H38: ='P&L'!H38*35 -> 110920.83 | I38: ='P&L'!I38*35 -> 126741.45
